Workbook

Sheet INVENTARIO
B1: PROCESO/PROCEDIMIENTO | P1: CLASIFICACIÓN | S1: CRITICIDAD
A2: ID | B2: TIPO DE PROCESO | C2: TIPO DE MACROPROCESO | D2: CODIGO MACROPROCESO | E2: PROCESO | F2: SUBPROCESO | G2: PROCEDIMIENTO | H2: NOMBRE | I2: DESCRIPCIÓN | J2: RESPONSABLE | K2: CUSTODIO | L2: UBICACIÓN | M2: MEDIO DE CONSERVACIÓN | N2: TIPO DE ACTIVO | O2: CATEGORÍA | P2: CONFIDENCIALIDAD | Q2: INTEGRIDAD | R2: DISPONIBILIDAD | S2: VALORACION | T2: CRITICIDAD | U2: ACCESO EXTERNO | V2: FECHA DE REGISTRO | W2: FECHA DE SALIDA | X2: RIESGO EVALUADO
A3: 1-GAD | B3: APOYO | C3: Gestión Administrativa | D3: GAD | E3: Comunicación y Asistencia Gerencial | F3: - | G3: Recepción y registro de documentos | H3: Matriz de control de documentos Gerencia | I3: Reporte que genera el sistema Ventanilla Virtual - Administra Procesos y opera la S de Gerencia | J3: Secretaria de Gerencia General | K3: Secretaria de Gerencia General | L3: UBICACIÓN DIGITAL-EQUIPO DEL RESPONSABLE | M3: DISCOS DUROS, SERVIDORES, DISCOS O MEDIOS PORTÁTILES, CINTAS O MEDIOS DE VIDEO Y AUDIO, ETC. | N3: PRIMARIOS | O3: DOCUMENTOS TÉCNICOS | P3: USO INTERNO(2) | Q3: BAJA(1) | R3: BAJA(1) | S3: =+(IF(P3="PUBLICA(1)",1,IF(P3="USO INTERNO(2)",2,IF(P3="RESTRINGIDO(3)",3,3))))+(IF(Q3="BAJA(1)",1,IF(Q3="MEDIA(2)",2,IF(Q3="ALTA(3)",3,3))))+(IF(R3="BAJA(1)",1,IF(R3="MEDIA(2)",2,IF(R3="ALTA(3)",3,3)))) | T3: =+IF(S3<6,"BAJA",IF(S3<8,"MEDIA","ALTA")) | U3: - | V3: 45673 | W3: N/A | X3: =+IFERROR(IF(VLOOKUP(Tabla2[[#This Row],[ID]],'EVALUACION DE RIESGO'!A:A,1,FALSE)=Tabla2[[#This Row],[ID]],"SI","NO"),"NO")
A4: 2-GAD | B4: APOYO | C4: Gestión Administrativa | D4: GAD | E4: Comunicación y Asistencia Gerencial | F4: - | G4: Recepción y registro de documentos | H4: Registro de entrega recepción de documentos | I4: Recepción de archivos físicos como digitales | J4: Secretaria de Gerencia General | K4: Secretaria de Gerencia General | L4: UBICACIÓN FISICA-MATRIZ ATUNTAQUI | M4: DOCUMENTO DE ARCHIVO-FÍSICO | N4: PRIMARIOS | O4: DOCUMENTOS HABILITANTES | P4: USO INTERNO(2) | Q4: BAJA(1) | R4: BAJA(1) | S4: =+(IF(P4="PUBLICA(1)",1,IF(P4="USO INTERNO(2)",2,IF(P4="RESTRINGIDO(3)",3,3))))+(IF(Q4="BAJA(1)",1,IF(Q4="MEDIA(2)",2,IF(Q4="ALTA(3)",3,3))))+(IF(R4="BAJA(1)",1,IF(R4="MEDIA(2)",2,IF(R4="ALTA(3)",3,3)))) | T4: =+IF(S4<6,"BAJA",IF(S4<8,"MEDIA","ALTA")) | U4: - | V4: 45673 | W4: N/A | X4: =+IFERROR(IF(VLOOKUP(Tabla2[[#This Row],[ID]],'EVALUACION DE RIESGO'!A:A,1,FALSE)=Tabla2[[#This Row],[ID]],"SI","NO"),"NO")
A5: 3-GAD | B5: APOYO | C5: Gestión Administrativa | D5: GAD | E5: Comunicación y Asistencia Gerencial | F5: - | G5: Seguimiento y cierre de trámites | H5: Matriz de control de documentos Gerencia (Seguimiento) | I5: Matriz de control de documentos Gerencia | J5: Secretaria de Gerencia General | K5: Secretaria de Gerencia General | L5: UBICACIÓN DIGITAL-EQUIPO DEL RESPONSABLE | M5: DISCOS DUROS, SERVIDORES, DISCOS O MEDIOS PORTÁTILES, CINTAS O MEDIOS DE VIDEO Y AUDIO, ETC. | N5: PRIMARIOS | O5: DOCUMENTOS TÉCNICOS | P5: USO INTERNO(2) | Q5: MEDIA(2) | R5: BAJA(1) | S5: =+(IF(P5="PUBLICA(1)",1,IF(P5="USO INTERNO(2)",2,IF(P5="RESTRINGIDO(3)",3,3))))+(IF(Q5="BAJA(1)",1,IF(Q5="MEDIA(2)",2,IF(Q5="ALTA(3)",3,3))))+(IF(R5="BAJA(1)",1,IF(R5="MEDIA(2)",2,IF(R5="ALTA(3)",3,3)))) | T5: =+IF(S5<6,"BAJA",IF(S5<8,"MEDIA","ALTA")) | U5: - | V5: 45673 | W5: N/A | X5: =+IFERROR(IF(VLOOKUP(Tabla2[[#This Row],[ID]],'EVALUACION DE RIESGO'!A:A,1,FALSE)=Tabla2[[#This Row],[ID]],"SI","NO"),"NO")
A6: 4-GAD | B6: APOYO | C6: Gestión Administrativa | D6: GAD | E6: Comunicación y Asistencia Gerencial | F6: - | G6: Despacho de oficios generados en otras áreas | H6: Oficio Memorandos | I6: Archivos físicos como digitales de Gerencia | J6: Secretaria de Gerencia General | K6: Secretaria de Gerencia General | L6: UBICACIÓN DIGITAL-EQUIPO DEL RESPONSABLE | M6: DOCUMENTO DE ARCHIVO-FÍSICO | N6: PRIMARIOS | O6: DOCUMENTOS HABILITANTES | P6: RESTRINGIDO(3) | Q6: BAJA(1) | R6: MEDIA(2) | S6: =+(IF(P6="PUBLICA(1)",1,IF(P6="USO INTERNO(2)",2,IF(P6="RESTRINGIDO(3)",3,3))))+(IF(Q6="BAJA(1)",1,IF(Q6="MEDIA(2)",2,IF(Q6="ALTA(3)",3,3))))+(IF(R6="BAJA(1)",1,IF(R6="MEDIA(2)",2,IF(R6="ALTA(3)",3,3)))) | T6: =+IF(S6<6,"BAJA",IF(S6<8,"MEDIA","ALTA")) | U6: - | V6: 45673 | W6: N/A | X6: =+IFERROR(IF(VLOOKUP(Tabla2[[#This Row],[ID]],'EVALUACION DE RIESGO'!A:A,1,FALSE)=Tabla2[[#This Row],[ID]],"SI","NO"),"NO")
A7: 5-GAD | B7: APOYO | C7: Gestión Administrativa | D7: GAD | E7: Comunicación y Asistencia Gerencial | F7: - | G7: Manejo de Agenda | H7: Agenda gerencial | I7: Reporte mensual que se presenta a gerencia | J7: Secretaria de Gerencia General | K7: Secretaria de Gerencia General | L7: UBICACIÓN DIGITAL-EQUIPO DEL RESPONSABLE | M7: DISCOS DUROS, SERVIDORES, DISCOS O MEDIOS PORTÁTILES, CINTAS O MEDIOS DE VIDEO Y AUDIO, ETC. | N7: PRIMARIOS | O7: DOCUMENTOS TÉCNICOS | P7: RESTRINGIDO(3) | Q7: MEDIA(2) | R7: BAJA(1) | S7: =+(IF(P7="PUBLICA(1)",1,IF(P7="USO INTERNO(2)",2,IF(P7="RESTRINGIDO(3)",3,3))))+(IF(Q7="BAJA(1)",1,IF(Q7="MEDIA(2)",2,IF(Q7="ALTA(3)",3,3))))+(IF(R7="BAJA(1)",1,IF(R7="MEDIA(2)",2,IF(R7="ALTA(3)",3,3)))) | T7: =+IF(S7<6,"BAJA",IF(S7<8,"MEDIA","ALTA")) | U7: - | V7: 45673 | W7: N/A | X7: =+IFERROR(IF(VLOOKUP(Tabla2[[#This Row],[ID]],'EVALUACION DE RIESGO'!A:A,1,FALSE)=Tabla2[[#This Row],[ID]],"SI","NO"),"NO")
A8: 6-GAD | B8: APOYO | C8: Gestión Administrativa | D8: GAD | E8: Comunicación y Asistencia Gerencial | F8: - | G8: N/A | H8: Archivo de Secretaria de Gerencia | I8: Archivos físicos que reposan en el archivo del área | J8: Secretaria de Gerencia General | K8: Secretaria de Gerencia General | L8: DOCUMENTOS FISICOS-ARCHIVOS DE LA OFICINA | M8: DOCUMENTO DE ARCHIVO-FÍSICO | N8: PRIMARIOS | O8: DOCUMENTOS HABILITANTES | P8: RESTRINGIDO(3) | Q8: MEDIA(2) | R8: MEDIA(2) | S8: =+(IF(P8="PUBLICA(1)",1,IF(P8="USO INTERNO(2)",2,IF(P8="RESTRINGIDO(3)",3,3))))+(IF(Q8="BAJA(1)",1,IF(Q8="MEDIA(2)",2,IF(Q8="ALTA(3)",3,3))))+(IF(R8="BAJA(1)",1,IF(R8="MEDIA(2)",2,IF(R8="ALTA(3)",3,3)))) | T8: =+IF(S8<6,"BAJA",IF(S8<8,"MEDIA","ALTA")) | U8: - | V8: 45673 | W8: N/A | X8: =+IFERROR(IF(VLOOKUP(Tabla2[[#This Row],[ID]],'EVALUACION DE RIESGO'!A:A,1,FALSE)=Tabla2[[#This Row],[ID]],"SI","NO"),"NO")
A9: 7-GAD | B9: APOYO | C9: Gestión Administrativa | D9: GAD | E9: Comunicación y Asistencia Gerencial | F9: - | G9: N/A | H9: Equipos de computación de Asistente de Gerencia | I9: Equipos de computación donde se realiza la gestión del área | J9: Secretaria de Gerencia General | K9: Secretaria de Gerencia General | L9: DOCUMENTOS FISICOS-ARCHIVOS DE LA OFICINA | M9: DOCUMENTO DE ARCHIVO-FÍSICO | N9: APOYO | O9: HARDWARE | P9: USO INTERNO(2) | Q9: BAJA(1) | R9: MEDIA(2) | S9: =+(IF(P9="PUBLICA(1)",1,IF(P9="USO INTERNO(2)",2,IF(P9="RESTRINGIDO(3)",3,3))))+(IF(Q9="BAJA(1)",1,IF(Q9="MEDIA(2)",2,IF(Q9="ALTA(3)",3,3))))+(IF(R9="BAJA(1)",1,IF(R9="MEDIA(2)",2,IF(R9="ALTA(3)",3,3)))) | T9: =+IF(S9<6,"BAJA",IF(S9<8,"MEDIA","ALTA")) | U9: - | V9: 45673 | W9: N/A | X9: =+IFERROR(IF(VLOOKUP(Tabla2[[#This Row],[ID]],'EVALUACION DE RIESGO'!A:A,1,FALSE)=Tabla2[[#This Row],[ID]],"SI","NO"),"NO")
A10: 8-GAD | B10: APOYO | C10: Gestión Administrativa | D10: GAD | E10: Comunicación y Asistencia Gerencial | F10: - | G10: N/A | H10: Asistente de Gerencia | I10: N/A | J10: Secretaria de Gerencia General | K10: Secretaria de Gerencia General | L10: N/A | M10: N/A | N10: APOYO | O10: RECURSO HUMANO | P10: USO INTERNO(2) | Q10: BAJA(1) | R10: MEDIA(2) | S10: =+(IF(P10="PUBLICA(1)",1,IF(P10="USO INTERNO(2)",2,IF(P10="RESTRINGIDO(3)",3,3))))+(IF(Q10="BAJA(1)",1,IF(Q10="MEDIA(2)",2,IF(Q10="ALTA(3)",3,3))))+(IF(R10="BAJA(1)",1,IF(R10="MEDIA(2)",2,IF(R10="ALTA(3)",3,3)))) | T10: =+IF(S10<6,"BAJA",IF(S10<8,"MEDIA","ALTA")) | U10: - | V10: 45673 | W10: N/A | X10: =+IFERROR(IF(VLOOKUP(Tabla2[[#This Row],[ID]],'EVALUACION DE RIESGO'!A:A,1,FALSE)=Tabla2[[#This Row],[ID]],"SI","NO"),"NO")
A11: 9-GAD | B11: APOYO | C11: Gestión Administrativa | D11: GAD | E11: Gestión de Activos | F11: - | G11: Registro de activos fijos | H11: Documentos habilitantes | I11: Documentos recibidos de activos fijos adquiridos, no almacena en un repositorio porque toda la información del activo se registra en FIT, serie, marca, modelo, color, custodio, oficina de destino, ubicación de la oficina. | J11: Jefe Administrativo | K11: Jefe Administrativo | L11: UBICACIÓN DIGITAL-EQUIPO DEL CUSTODIO | M11: DISCOS DUROS, SERVIDORES, DISCOS O MEDIOS PORTÁTILES, CINTAS O MEDIOS DE VIDEO Y AUDIO, ETC. | N11: PRIMARIOS | O11: DOCUMENTOS HABILITANTES | P11: PUBLICA(1) | Q11: BAJA(1) | R11: MEDIA(2) | S11: =+(IF(P11="PUBLICA(1)",1,IF(P11="USO INTERNO(2)",2,IF(P11="RESTRINGIDO(3)",3,3))))+(IF(Q11="BAJA(1)",1,IF(Q11="MEDIA(2)",2,IF(Q11="ALTA(3)",3,3))))+(IF(R11="BAJA(1)",1,IF(R11="MEDIA(2)",2,IF(R11="ALTA(3)",3,3)))) | T11: =+IF(S11<6,"BAJA",IF(S11<8,"MEDIA","ALTA")) | U11: - | V11: 45680 | W11: N/A | X11: =+IFERROR(IF(VLOOKUP(Tabla2[[#This Row],[ID]],'EVALUACION DE RIESGO'!A:A,1,FALSE)=Tabla2[[#This Row],[ID]],"SI","NO"),"NO")
A12: 10-GAD | B12: APOYO | C12: Gestión Administrativa | D12: GAD | E12: Gestión de Activos | F12: - | G12: Planificación de mantenimientos | H12: Informe de mantenimiento | I12: Informe de avances de la planificación realizada con detalles de descripción, elementos, actividad, área ubicación de mantenimiento, cantidad, observación, cronograma cumplido | J12: Jefe Administrativo | K12: Jefe Administrativo | L12: UBICACIÓN DIGITAL-EQUIPO DEL CUSTODIO | M12: DISCOS DUROS, SERVIDORES, DISCOS O MEDIOS PORTÁTILES, CINTAS O MEDIOS DE VIDEO Y AUDIO, ETC. | N12: PRIMARIOS | O12: DOCUMENTOS HABILITANTES | P12: PUBLICA(1) | Q12: BAJA(1) | R12: MEDIA(2) | S12: =+(IF(P12="PUBLICA(1)",1,IF(P12="USO INTERNO(2)",2,IF(P12="RESTRINGIDO(3)",3,3))))+(IF(Q12="BAJA(1)",1,IF(Q12="MEDIA(2)",2,IF(Q12="ALTA(3)",3,3))))+(IF(R12="BAJA(1)",1,IF(R12="MEDIA(2)",2,IF(R12="ALTA(3)",3,3)))) | T12: =+IF(S12<6,"BAJA",IF(S12<8,"MEDIA","ALTA")) | U12: - | V12: 45680 | W12: N/A | X12: =+IFERROR(IF(VLOOKUP(Tabla2[[#This Row],[ID]],'EVALUACION DE RIESGO'!A:A,1,FALSE)=Tabla2[[#This Row],[ID]],"SI","NO"),"NO")
A13: 11-GAD | B13: APOYO | C13: Gestión Administrativa | D13: GAD | E13: Gestión de Activos | F13: - | G13: Planificación de mantenimientos | H13: Cronograma/Bitácora de mantenimiento | I13: Archivo de planificación que contiene descripción, elementos, actividad, área ubicación de mantenimiento, cantidad, observación, cronograma cumplido | J13: Jefe Administrativo | K13: Jefe Administrativo | L13: UBICACIÓN DIGITAL-EQUIPO DEL CUSTODIO | M13: DISCOS DUROS, SERVIDORES, DISCOS O MEDIOS PORTÁTILES, CINTAS O MEDIOS DE VIDEO Y AUDIO, ETC. | N13: PRIMARIOS | O13: DOCUMENTOS TÉCNICOS | P13: PUBLICA(1) | Q13: BAJA(1) | R13: MEDIA(2) | S13: =+(IF(P13="PUBLICA(1)",1,IF(P13="USO INTERNO(2)",2,IF(P13="RESTRINGIDO(3)",3,3))))+(IF(Q13="BAJA(1)",1,IF(Q13="MEDIA(2)",2,IF(Q13="ALTA(3)",3,3))))+(IF(R13="BAJA(1)",1,IF(R13="MEDIA(2)",2,IF(R13="ALTA(3)",3,3)))) | T13: =+IF(S13<6,"BAJA",IF(S13<8,"MEDIA","ALTA")) | U13: - | V13: 45680 | W13: N/A | X13: =+IFERROR(IF(VLOOKUP(Tabla2[[#This Row],[ID]],'EVALUACION DE RIESGO'!A:A,1,FALSE)=Tabla2[[#This Row],[ID]],"SI","NO"),"NO")
A14: 12-GAD | B14: APOYO | C14: Gestión Administrativa | D14: GAD | E14: Gestión de Activos | F14: - | G14: Mantenimiento preventivo de bienes e inmuebles | H14: Solicitud de adquisiciones y contratación | I14: solicitudes que se gestionan en el sistema Sara con información de número de solicitud, requerimiento, justificación de la adquisición, bienes y servicio, información del plan anual, fechas inicio de proceso, documentos anexos, TDR | J14: Jefe Administrativo | K14: Jefe Administrativo | L14: UBICACIÓN DIGITAL-EQUIPO DEL CUSTODIO | M14: DISCOS DUROS, SERVIDORES, DISCOS O MEDIOS PORTÁTILES, CINTAS O MEDIOS DE VIDEO Y AUDIO, ETC. | N14: PRIMARIOS | O14: DOCUMENTOS HABILITANTES | P14: PUBLICA(1) | Q14: BAJA(1) | R14: MEDIA(2) | S14: =+(IF(P14="PUBLICA(1)",1,IF(P14="USO INTERNO(2)",2,IF(P14="RESTRINGIDO(3)",3,3))))+(IF(Q14="BAJA(1)",1,IF(Q14="MEDIA(2)",2,IF(Q14="ALTA(3)",3,3))))+(IF(R14="BAJA(1)",1,IF(R14="MEDIA(2)",2,IF(R14="ALTA(3)",3,3)))) | T14: =+IF(S14<6,"BAJA",IF(S14<8,"MEDIA","ALTA")) | U14: - | V14: 45680 | W14: N/A | X14: =+IFERROR(IF(VLOOKUP(Tabla2[[#This Row],[ID]],'EVALUACION DE RIESGO'!A:A,1,FALSE)=Tabla2[[#This Row],[ID]],"SI","NO"),"NO")
... A241: 66-GCA | B241: PRODUCTIVO | C241: Gestión de Captaciones | D241: GCA | E241: N/A | F241: - | G241: N/A | H241: Jefe de Captaciones | I241: N/A | J241: Jefe de Captaciones | K241: N/A | L241: N/A | M241: N/A | N241: APOYO | O241: RECURSO HUMANO | P241: USO INTERNO(2) | Q241: MEDIA(2) | R241: MEDIA(2) | S241: =+(IF(P241="PUBLICA(1)",1,IF(P241="USO INTERNO(2)",2,IF(P241="RESTRINGIDO(3)",3,3))))+(IF(Q241="BAJA(1)",1,IF(Q241="MEDIA(2)",2,IF(Q241="ALTA(3)",3,3))))+(IF(R241="BAJA(1)",1,IF(R241="MEDIA(2)",2,IF(R241="ALTA(3)",3,3)))) | T241: =+IF(S241<6,"BAJA",IF(S241<8,"MEDIA","ALTA")) | U241: - | V241: 45712 | W241: N/A | X241: =+IFERROR(IF(VLOOKUP(Tabla2[[#This Row],[ID]],'EVALUACION DE RIESGO'!A:A,1,FALSE)=Tabla2[[#This Row],[ID]],"SI","NO"),"NO")
A242: 1-GCO | B242: PRODUCTIVO | C242: Gestión de Colocaciones | D242: GCO | E242: Gestión de Crédito de Consumo | F242: - | G242: Solicitud de crédito | H242: File de crédito | I242: File digital que contiene toda la documentación referente a los lineamientos del tipo de crédito | J242: Jefe de Negocios | K242: FIT | L242: UBICACIÓN DIGITAL-CORE FINANCIERO | M242: DOCUMENTO DE ARCHIVO-ELECTRÓNICO | N242: PRIMARIOS | O242: INFORMACIÓN DE SOCIOS Y CLIENTES | P242: RESTRINGIDO(3) | Q242: MEDIA(2) | R242: MEDIA(2) | S242: =+(IF(P242="PUBLICA(1)",1,IF(P242="USO INTERNO(2)",2,IF(P242="RESTRINGIDO(3)",3,3))))+(IF(Q242="BAJA(1)",1,IF(Q242="MEDIA(2)",2,IF(Q242="ALTA(3)",3,3))))+(IF(R242="BAJA(1)",1,IF(R242="MEDIA(2)",2,IF(R242="ALTA(3)",3,3)))) | T242: =+IF(S242<6,"BAJA",IF(S242<8,"MEDIA","ALTA")) | U242: - | V242: 8/02/225 | W242: N/A | X242: =+IFERROR(IF(VLOOKUP(Tabla2[[#This Row],[ID]],'EVALUACION DE RIESGO'!A:A,1,FALSE)=Tabla2[[#This Row],[ID]],"SI","NO"),"NO")
A243: 2-GCO | B243: PRODUCTIVO | C243: Gestión de Colocaciones | D243: GCO | E243: Gestión de Crédito de Consumo | F243: - | G243: Solicitud de créditos con garantía de plazo fijo | H243: File de crédito / Certificado del DPF | I243: File digital que contiene toda la documentación referente a los lineamientos del tipo de crédito, de adjunta la copia del DPF | J243: Jefe de Negocios | K243: FIT | L243: UBICACIÓN DIGITAL-CORE FINANCIERO | M243: DOCUMENTO DE ARCHIVO-ELECTRÓNICO | N243: PRIMARIOS | O243: INFORMACIÓN DE SOCIOS Y CLIENTES | P243: RESTRINGIDO(3) | Q243: MEDIA(2) | R243: MEDIA(2) | S243: =+(IF(P243="PUBLICA(1)",1,IF(P243="USO INTERNO(2)",2,IF(P243="RESTRINGIDO(3)",3,3))))+(IF(Q243="BAJA(1)",1,IF(Q243="MEDIA(2)",2,IF(Q243="ALTA(3)",3,3))))+(IF(R243="BAJA(1)",1,IF(R243="MEDIA(2)",2,IF(R243="ALTA(3)",3,3)))) | T243: =+IF(S243<6,"BAJA",IF(S243<8,"MEDIA","ALTA")) | U243: - | V243: 8/02/225 | W243: N/A | X243: =+IFERROR(IF(VLOOKUP(Tabla2[[#This Row],[ID]],'EVALUACION DE RIESGO'!A:A,1,FALSE)=Tabla2[[#This Row],[ID]],"SI","NO"),"NO")
A244: 3-GCO | B244: PRODUCTIVO | C244: Gestión de Colocaciones | D244: GCO | E244: Gestión de Crédito de Consumo | F244: - | G244: Solicitud de créditos con garantía prendaria de Oro | H244: File de crédito | I244: File digital que contiene toda la documentación referente a los lineamientos del tipo de crédito | J244: Jefe de Negocios | K244: FIT | L244: UBICACIÓN DIGITAL-CORE FINANCIERO | M244: DOCUMENTO DE ARCHIVO-ELECTRÓNICO | N244: PRIMARIOS | O244: INFORMACIÓN DE SOCIOS Y CLIENTES | P244: USO INTERNO(2) | Q244: MEDIA(2) | R244: MEDIA(2) | S244: =+(IF(P244="PUBLICA(1)",1,IF(P244="USO INTERNO(2)",2,IF(P244="RESTRINGIDO(3)",3,3))))+(IF(Q244="BAJA(1)",1,IF(Q244="MEDIA(2)",2,IF(Q244="ALTA(3)",3,3))))+(IF(R244="BAJA(1)",1,IF(R244="MEDIA(2)",2,IF(R244="ALTA(3)",3,3)))) | T244: =+IF(S244<6,"BAJA",IF(S244<8,"MEDIA","ALTA")) | U244: - | V244: 8/02/225 | W244: N/A | X244: =+IFERROR(IF(VLOOKUP(Tabla2[[#This Row],[ID]],'EVALUACION DE RIESGO'!A:A,1,FALSE)=Tabla2[[#This Row],[ID]],"SI","NO"),"NO")
A245: 4-GCO | B245: PRODUCTIVO | C245: Gestión de Colocaciones | D245: GCO | E245: Gestión de Crédito de Consumo | F245: - | G245: Solicitud de créditos con garantía prendaria de Oro | H245: Prenda de oro | I245: Prenda de garantía que se recibe para otorgar el crédito | J245: Jefe de Negocios | K245: Supervisor Operativo | L245: DOCUMENTOS FISICOS-ARCHIVOS DE LA OFICINA | M245: DOCUMENTO DE ARCHIVO-FÍSICO | N245: PRIMARIOS | O245: INFORMACIÓN DE SOCIOS Y CLIENTES | P245: USO INTERNO(2) | Q245: MEDIA(2) | R245: MEDIA(2) | S245: =+(IF(P245="PUBLICA(1)",1,IF(P245="USO INTERNO(2)",2,IF(P245="RESTRINGIDO(3)",3,3))))+(IF(Q245="BAJA(1)",1,IF(Q245="MEDIA(2)",2,IF(Q245="ALTA(3)",3,3))))+(IF(R245="BAJA(1)",1,IF(R245="MEDIA(2)",2,IF(R245="ALTA(3)",3,3)))) | T245: =+IF(S245<6,"BAJA",IF(S245<8,"MEDIA","ALTA")) | U245: - | V245: 8/02/225 | W245: N/A | X245: =+IFERROR(IF(VLOOKUP(Tabla2[[#This Row],[ID]],'EVALUACION DE RIESGO'!A:A,1,FALSE)=Tabla2[[#This Row],[ID]],"SI","NO"),"NO")
A246: 5-GCO | B246: PRODUCTIVO | C246: Gestión de Colocaciones | D246: GCO | E246: Gestión de Crédito de Consumo | F246: - | G246: Solicitud de créditos con garantía prendaria de Oro | H246: Formulario y foro de la prenda para custodia | I246: Acta entrega que se realiza para la recepción de la prenda | J246: Jefe de Negocios | K246: FIT | L246: UBICACIÓN DIGITAL-CORE FINANCIERO | M246: DOCUMENTO DE ARCHIVO-ELECTRÓNICO | N246: PRIMARIOS | O246: DOCUMENTOS HABILITANTES | P246: USO INTERNO(2) | Q246: MEDIA(2) | R246: MEDIA(2) | S246: =+(IF(P246="PUBLICA(1)",1,IF(P246="USO INTERNO(2)",2,IF(P246="RESTRINGIDO(3)",3,3))))+(IF(Q246="BAJA(1)",1,IF(Q246="MEDIA(2)",2,IF(Q246="ALTA(3)",3,3))))+(IF(R246="BAJA(1)",1,IF(R246="MEDIA(2)",2,IF(R246="ALTA(3)",3,3)))) | T246: =+IF(S246<6,"BAJA",IF(S246<8,"MEDIA","ALTA")) | U246: - | V246: 8/02/225 | W246: N/A | X246: =+IFERROR(IF(VLOOKUP(Tabla2[[#This Row],[ID]],'EVALUACION DE RIESGO'!A:A,1,FALSE)=Tabla2[[#This Row],[ID]],"SI","NO"),"NO")
A247: 6-GCO | B247: PRODUCTIVO | C247: Gestión de Colocaciones | D247: GCO | E247: Gestión de Crédito de Consumo | F247: - | G247: Solicitud de novación, refinanciamiento, o reestructuración de créditos | H247: File de crédito / Informe de análisis de novación, refinanciamiento y restructuración | I247: File digital que contiene toda la documentación referente a los lineamientos del tipo de crédito / el informe de análisis se adjunta al file del crédito | J247: Jefe de Negocios | K247: FIT | L247: UBICACIÓN DIGITAL-CORE FINANCIERO | M247: DOCUMENTO DE ARCHIVO-ELECTRÓNICO | N247: PRIMARIOS | O247: INFORMACIÓN DE SOCIOS Y CLIENTES | P247: RESTRINGIDO(3) | Q247: MEDIA(2) | R247: MEDIA(2) | S247: =+(IF(P247="PUBLICA(1)",1,IF(P247="USO INTERNO(2)",2,IF(P247="RESTRINGIDO(3)",3,3))))+(IF(Q247="BAJA(1)",1,IF(Q247="MEDIA(2)",2,IF(Q247="ALTA(3)",3,3))))+(IF(R247="BAJA(1)",1,IF(R247="MEDIA(2)",2,IF(R247="ALTA(3)",3,3)))) | T247: =+IF(S247<6,"BAJA",IF(S247<8,"MEDIA","ALTA")) | U247: - | V247: 8/02/225 | W247: N/A | X247: =+IFERROR(IF(VLOOKUP(Tabla2[[#This Row],[ID]],'EVALUACION DE RIESGO'!A:A,1,FALSE)=Tabla2[[#This Row],[ID]],"SI","NO"),"NO")
A248: 7-GCO | B248: PRODUCTIVO | C248: Gestión de Colocaciones | D248: GCO | E248: Gestión de Crédito de Consumo | F248: - | G248: Seguimiento al destino del crédito | H248: Formulario de destino del crédito | I248: Formulario de detalle del destino de la solicitud del crédito | J248: Jefe de Negocios | K248: FIT | L248: UBICACIÓN DIGITAL-CORE FINANCIERO | M248: DOCUMENTO DE ARCHIVO-ELECTRÓNICO | N248: PRIMARIOS | O248: INFORMACIÓN DE SOCIOS Y CLIENTES | P248: USO INTERNO(2) | Q248: MEDIA(2) | R248: MEDIA(2) | S248: =+(IF(P248="PUBLICA(1)",1,IF(P248="USO INTERNO(2)",2,IF(P248="RESTRINGIDO(3)",3,3))))+(IF(Q248="BAJA(1)",1,IF(Q248="MEDIA(2)",2,IF(Q248="ALTA(3)",3,3))))+(IF(R248="BAJA(1)",1,IF(R248="MEDIA(2)",2,IF(R248="ALTA(3)",3,3)))) | T248: =+IF(S248<6,"BAJA",IF(S248<8,"MEDIA","ALTA")) | U248: - | V248: 8/02/225 | W248: N/A | X248: =+IFERROR(IF(VLOOKUP(Tabla2[[#This Row],[ID]],'EVALUACION DE RIESGO'!A:A,1,FALSE)=Tabla2[[#This Row],[ID]],"SI","NO"),"NO")
A249: 8-GCO | B249: PRODUCTIVO | C249: Gestión de Colocaciones | D249: GCO | E249: Gestión de PYMES | F249: - | G249: Solicitud de crédito PYME | H249: File de crédito / Formulario previo al otorgamiento del crédito | I249: File digital que contiene toda la documentación referente a los lineamientos del tipo de crédito / el formulario previo se adjunta al otorgamiento del crédito | J249: Gerente de Negocios | K249: FIT | L249: UBICACIÓN DIGITAL-CORE FINANCIERO | M249: DOCUMENTO DE ARCHIVO-ELECTRÓNICO | N249: PRIMARIOS | O249: INFORMACIÓN DE SOCIOS Y CLIENTES | P249: RESTRINGIDO(3) | Q249: MEDIA(2) | R249: MEDIA(2) | S249: =+(IF(P249="PUBLICA(1)",1,IF(P249="USO INTERNO(2)",2,IF(P249="RESTRINGIDO(3)",3,3))))+(IF(Q249="BAJA(1)",1,IF(Q249="MEDIA(2)",2,IF(Q249="ALTA(3)",3,3))))+(IF(R249="BAJA(1)",1,IF(R249="MEDIA(2)",2,IF(R249="ALTA(3)",3,3)))) | T249: =+IF(S249<6,"BAJA",IF(S249<8,"MEDIA","ALTA")) | U249: - | V249: 8/02/225 | W249: N/A | X249: =+IFERROR(IF(VLOOKUP(Tabla2[[#This Row],[ID]],'EVALUACION DE RIESGO'!A:A,1,FALSE)=Tabla2[[#This Row],[ID]],"SI","NO"),"NO")
A250: 9-GCO | B250: PRODUCTIVO | C250: Gestión de Colocaciones | D250: GCO | E250: Gestión de PYMES | F250: - | G250: Solicitud de novación, refinanciamiento, o reestructuración de créditos PYME | H250: File de crédito / Informe de análisis de novación, refinanciamiento y restructuración | I250: File digital que contiene toda la documentación referente a los lineamientos del tipo de crédito / el Informe de análisis de novación, refinanciamiento y restructuración se adjunta al file del crédito | J250: Gerente de Negocios | K250: FIT | L250: UBICACIÓN DIGITAL-CORE FINANCIERO | M250: DOCUMENTO DE ARCHIVO-ELECTRÓNICO | N250: PRIMARIOS | O250: INFORMACIÓN DE SOCIOS Y CLIENTES | P250: RESTRINGIDO(3) | Q250: MEDIA(2) | R250: MEDIA(2) | S250: =+(IF(P250="PUBLICA(1)",1,IF(P250="USO INTERNO(2)",2,IF(P250="RESTRINGIDO(3)",3,3))))+(IF(Q250="BAJA(1)",1,IF(Q250="MEDIA(2)",2,IF(Q250="ALTA(3)",3,3))))+(IF(R250="BAJA(1)",1,IF(R250="MEDIA(2)",2,IF(R250="ALTA(3)",3,3)))) | T250: =+IF(S250<6,"BAJA",IF(S250<8,"MEDIA","ALTA")) | U250: - | V250: 8/02/225 | W250: N/A | X250: =+IFERROR(IF(VLOOKUP(Tabla2[[#This Row],[ID]],'EVALUACION DE RIESGO'!A:A,1,FALSE)=Tabla2[[#This Row],[ID]],"SI","NO"),"NO")
A251: 10-GCO | B251: PRODUCTIVO | C251: Gestión de Colocaciones | D251: GCO | E251: Gestión de PYMES | F251: - | G251: Destino y control a los créditos PYME | H251: Formulario de destino del crédito | I251: Formulario adjunto al file del crédito | J251: Gerente de Negocios | K251: FIT | L251: UBICACIÓN DIGITAL-CORE FINANCIERO | M251: DOCUMENTO DE ARCHIVO-ELECTRÓNICO | N251: PRIMARIOS | O251: INFORMACIÓN DE SOCIOS Y CLIENTES | P251: USO INTERNO(2) | Q251: MEDIA(2) | R251: MEDIA(2) | S251: =+(IF(P251="PUBLICA(1)",1,IF(P251="USO INTERNO(2)",2,IF(P251="RESTRINGIDO(3)",3,3))))+(IF(Q251="BAJA(1)",1,IF(Q251="MEDIA(2)",2,IF(Q251="ALTA(3)",3,3))))+(IF(R251="BAJA(1)",1,IF(R251="MEDIA(2)",2,IF(R251="ALTA(3)",3,3)))) | T251: =+IF(S251<6,"BAJA",IF(S251<8,"MEDIA","ALTA")) | U251: - | V251: 8/02/225 | W251: N/A | X251: =+IFERROR(IF(VLOOKUP(Tabla2[[#This Row],[ID]],'EVALUACION DE RIESGO'!A:A,1,FALSE)=Tabla2[[#This Row],[ID]],"SI","NO"),"NO")
A252: 11-GCO | B252: PRODUCTIVO | C252: Gestión de Colocaciones | D252: GCO | E252: Procesamiento de Crédito | F252: - | G252: Predespacho de solicitudes de crédito | H252: Registro del sistema | I252: Registro realizado en el sistema como una etapa de la revisión y aprobación del crédito | J252: Jefe de Negocios | K252: FIT | L252: UBICACIÓN DIGITAL-CORE FINANCIERO | M252: DOCUMENTO DE ARCHIVO-ELECTRÓNICO | N252: PRIMARIOS | O252: INFORMACIÓN DE SOCIOS Y CLIENTES | P252: USO INTERNO(2) | Q252: BAJA(1) | R252: MEDIA(2) | S252: =+(IF(P252="PUBLICA(1)",1,IF(P252="USO INTERNO(2)",2,IF(P252="RESTRINGIDO(3)",3,3))))+(IF(Q252="BAJA(1)",1,IF(Q252="MEDIA(2)",2,IF(Q252="ALTA(3)",3,3))))+(IF(R252="BAJA(1)",1,IF(R252="MEDIA(2)",2,IF(R252="ALTA(3)",3,3)))) | T252: =+IF(S252<6,"BAJA",IF(S252<8,"MEDIA","ALTA")) | U252: - | V252: 8/02/225 | W252: N/A | X252: =+IFERROR(IF(VLOOKUP(Tabla2[[#This Row],[ID]],'EVALUACION DE RIESGO'!A:A,1,FALSE)=Tabla2[[#This Row],[ID]],"SI","NO"),"NO")
A253: 12-GCO | B253: PRODUCTIVO | C253: Gestión de Colocaciones | D253: GCO | E253: Procesamiento de Crédito | F253: - | G253: Verificación de Información de la Solicitud de Crédito | H253: File de crédito | I253: File digital que contiene toda la documentación referente a los lineamientos del tipo de crédito | J253: Jefe de Negocios | K253: FIT | L253: UBICACIÓN DIGITAL-CORE FINANCIERO | M253: DOCUMENTO DE ARCHIVO-ELECTRÓNICO | N253: PRIMARIOS | O253: INFORMACIÓN DE SOCIOS Y CLIENTES | P253: RESTRINGIDO(3) | Q253: MEDIA(2) | R253: MEDIA(2) | S253: =+(IF(P253="PUBLICA(1)",1,IF(P253="USO INTERNO(2)",2,IF(P253="RESTRINGIDO(3)",3,3))))+(IF(Q253="BAJA(1)",1,IF(Q253="MEDIA(2)",2,IF(Q253="ALTA(3)",3,3))))+(IF(R253="BAJA(1)",1,IF(R253="MEDIA(2)",2,IF(R253="ALTA(3)",3,3)))) | T253: =+IF(S253<6,"BAJA",IF(S253<8,"MEDIA","ALTA")) | U253: - | V253: 8/02/225 | W253: N/A | X253: =+IFERROR(IF(VLOOKUP(Tabla2[[#This Row],[ID]],'EVALUACION DE RIESGO'!A:A,1,FALSE)=Tabla2[[#This Row],[ID]],"SI","NO"),"NO")
... A295: 54-GCO | B295: PRODUCTIVO | C295: Gestión de Colocaciones | D295: GCO | E295: Gestión de Compra y Venta de Cartera | F295: - | G295: Entrega de datos y cobro de la venta | H295: Reporte de Cartera Vendida | I295: Reporte procesado por Operaciones para el registro en el Core Financiero | J295: Gerente de Negocios | K295: Gerente de Negocios | L295: UBICACIÓN DIGITAL-EQUIPO DEL RESPONSABLE | M295: DISCOS DUROS, SERVIDORES, DISCOS O MEDIOS PORTÁTILES, CINTAS O MEDIOS DE VIDEO Y AUDIO, ETC. | N295: PRIMARIOS | O295: DOCUMENTOS TÉCNICOS | P295: RESTRINGIDO(3) | Q295: MEDIA(2) | R295: MEDIA(2) | S295: =+(IF(P295="PUBLICA(1)",1,IF(P295="USO INTERNO(2)",2,IF(P295="RESTRINGIDO(3)",3,3))))+(IF(Q295="BAJA(1)",1,IF(Q295="MEDIA(2)",2,IF(Q295="ALTA(3)",3,3))))+(IF(R295="BAJA(1)",1,IF(R295="MEDIA(2)",2,IF(R295="ALTA(3)",3,3)))) | T295: =+IF(S295<6,"BAJA",IF(S295<8,"MEDIA","ALTA")) | U295: - | V295: 8/02/225 | W295: N/A | X295: =+IFERROR(IF(VLOOKUP(Tabla2[[#This Row],[ID]],'EVALUACION DE RIESGO'!A:A,1,FALSE)=Tabla2[[#This Row],[ID]],"SI","NO"),"NO")
A296: 55-GCO | B296: PRODUCTIVO | C296: Gestión de Colocaciones | D296: GCO | E296: N/A | F296: - | G296: N/A | H296: Equipos de computación | I296: Equipos de computación donde se realiza la gestión del área | J296: Gerente de Negocios | K296: Gerente de Negocios | L296: UBICACIÓN FISICA-MATRIZ ATUNTAQUI | M296: DISCOS DUROS, SERVIDORES, DISCOS O MEDIOS PORTÁTILES, CINTAS O MEDIOS DE VIDEO Y AUDIO, ETC. | N296: APOYO | O296: HARDWARE | P296: RESTRINGIDO(3) | Q296: MEDIA(2) | R296: MEDIA(2) | S296: =+(IF(P296="PUBLICA(1)",1,IF(P296="USO INTERNO(2)",2,IF(P296="RESTRINGIDO(3)",3,3))))+(IF(Q296="BAJA(1)",1,IF(Q296="MEDIA(2)",2,IF(Q296="ALTA(3)",3,3))))+(IF(R296="BAJA(1)",1,IF(R296="MEDIA(2)",2,IF(R296="ALTA(3)",3,3)))) | T296: =+IF(S296<6,"BAJA",IF(S296<8,"MEDIA","ALTA")) | U296: - | V296: 45712 | W296: N/A | X296: =+IFERROR(IF(VLOOKUP(Tabla2[[#This Row],[ID]],'EVALUACION DE RIESGO'!A:A,1,FALSE)=Tabla2[[#This Row],[ID]],"SI","NO"),"NO")
A297: 56-GCO | B297: PRODUCTIVO | C297: Gestión de Colocaciones | D297: GCO | E297: N/A | F297: - | G297: N/A | H297: Gerente de Negocios | I297: N/A | J297: Gerente de Negocios | K297: N/A | L297: N/A | M297: N/A | N297: APOYO | O297: RECURSO HUMANO | P297: USO INTERNO(2) | Q297: MEDIA(2) | R297: MEDIA(2) | S297: =+(IF(P297="PUBLICA(1)",1,IF(P297="USO INTERNO(2)",2,IF(P297="RESTRINGIDO(3)",3,3))))+(IF(Q297="BAJA(1)",1,IF(Q297="MEDIA(2)",2,IF(Q297="ALTA(3)",3,3))))+(IF(R297="BAJA(1)",1,IF(R297="MEDIA(2)",2,IF(R297="ALTA(3)",3,3)))) | T297: =+IF(S297<6,"BAJA",IF(S297<8,"MEDIA","ALTA")) | U297: - | V297: 45712 | W297: N/A | X297: =+IFERROR(IF(VLOOKUP(Tabla2[[#This Row],[ID]],'EVALUACION DE RIESGO'!A:A,1,FALSE)=Tabla2[[#This Row],[ID]],"SI","NO"),"NO")
A298: 57-GCO | B298: PRODUCTIVO | C298: Gestión de Colocaciones | D298: GCO | E298: N/A | F298: - | G298: N/A | H298: Jefe de Negocios | I298: N/A | J298: Jefe de Negocios | K298: N/A | L298: N/A | M298: N/A | N298: APOYO | O298: RECURSO HUMANO | P298: USO INTERNO(2) | Q298: MEDIA(2) | R298: MEDIA(2) | S298: =+(IF(P298="PUBLICA(1)",1,IF(P298="USO INTERNO(2)",2,IF(P298="RESTRINGIDO(3)",3,3))))+(IF(Q298="BAJA(1)",1,IF(Q298="MEDIA(2)",2,IF(Q298="ALTA(3)",3,3))))+(IF(R298="BAJA(1)",1,IF(R298="MEDIA(2)",2,IF(R298="ALTA(3)",3,3)))) | T298: =+IF(S298<6,"BAJA",IF(S298<8,"MEDIA","ALTA")) | U298: - | V298: 45712 | W298: N/A | X298: =+IFERROR(IF(VLOOKUP(Tabla2[[#This Row],[ID]],'EVALUACION DE RIESGO'!A:A,1,FALSE)=Tabla2[[#This Row],[ID]],"SI","NO"),"NO")
A299: 1-GNE | B299: PRODUCTIVO | C299: Gestión de Negocios | D299: GNE | E299: Gestión de Marketing | F299: - | G299: Elaboración del Plan de Medios | H299: Plan de Medios | I299: Estrategia detallada que describe los canales y recursos utilizados para la difusión de las campañas de marketing. | J299: Jefe de Marketing | K299: Jefe de Marketing | L299: UBICACIÓN DIGITAL-EQUIPO DEL RESPONSABLE | M299: DISCOS DUROS, SERVIDORES, DISCOS O MEDIOS PORTÁTILES, CINTAS O MEDIOS DE VIDEO Y AUDIO, ETC. | N299: PRIMARIOS | O299: DOCUMENTOS TÉCNICOS | P299: USO INTERNO(2) | Q299: MEDIA(2) | R299: BAJA(1) | S299: =+(IF(P299="PUBLICA(1)",1,IF(P299="USO INTERNO(2)",2,IF(P299="RESTRINGIDO(3)",3,3))))+(IF(Q299="BAJA(1)",1,IF(Q299="MEDIA(2)",2,IF(Q299="ALTA(3)",3,3))))+(IF(R299="BAJA(1)",1,IF(R299="MEDIA(2)",2,IF(R299="ALTA(3)",3,3)))) | T299: =+IF(S299<6,"BAJA",IF(S299<8,"MEDIA","ALTA")) | U299: - | V299: 45580 | W299: N/A | X299: =+IFERROR(IF(VLOOKUP(Tabla2[[#This Row],[ID]],'EVALUACION DE RIESGO'!A:A,1,FALSE)=Tabla2[[#This Row],[ID]],"SI","NO"),"NO")
A300: 2-GNE | B300: PRODUCTIVO | C300: Gestión de Negocios | D300: GNE | E300: Gestión de Marketing | F300: - | G300: Elaboración del Plan de Marketing | H300: Plan de Marketing | I300: Documento integral que incluye las estrategias, objetivos y tácticas para promocionar los productos o servicios de la cooperativa. | J300: Jefe de Marketing | K300: Jefe de Marketing | L300: UBICACIÓN DIGITAL-EQUIPO DEL RESPONSABLE | M300: DISCOS DUROS, SERVIDORES, DISCOS O MEDIOS PORTÁTILES, CINTAS O MEDIOS DE VIDEO Y AUDIO, ETC. | N300: PRIMARIOS | O300: DOCUMENTOS TÉCNICOS | P300: USO INTERNO(2) | Q300: BAJA(1) | R300: MEDIA(2) | S300: =+(IF(P300="PUBLICA(1)",1,IF(P300="USO INTERNO(2)",2,IF(P300="RESTRINGIDO(3)",3,3))))+(IF(Q300="BAJA(1)",1,IF(Q300="MEDIA(2)",2,IF(Q300="ALTA(3)",3,3))))+(IF(R300="BAJA(1)",1,IF(R300="MEDIA(2)",2,IF(R300="ALTA(3)",3,3)))) | T300: =+IF(S300<6,"BAJA",IF(S300<8,"MEDIA","ALTA")) | U300: - | V300: 45580 | W300: N/A | X300: =+IFERROR(IF(VLOOKUP(Tabla2[[#This Row],[ID]],'EVALUACION DE RIESGO'!A:A,1,FALSE)=Tabla2[[#This Row],[ID]],"SI","NO"),"NO")
A301: 3-GNE | B301: PRODUCTIVO | C301: Gestión de Negocios | D301: GNE | E301: Gestión de Marketing | F301: - | G301: Diseño y ejecución de campañas publicitarias | H301: Brief (Síntesis) de la campaña publicitaria integral. | I301: Resumen conciso de la campaña publicitaria, incluyendo los objetivos, el público objetivo, los mensajes clave y los canales de comunicación. | J301: Jefe de Marketing | K301: Jefe de Marketing | L301: UBICACIÓN DIGITAL-EQUIPO DEL RESPONSABLE | M301: DISCOS DUROS, SERVIDORES, DISCOS O MEDIOS PORTÁTILES, CINTAS O MEDIOS DE VIDEO Y AUDIO, ETC. | N301: PRIMARIOS | O301: DOCUMENTOS TÉCNICOS | P301: USO INTERNO(2) | Q301: BAJA(1) | R301: BAJA(1) | S301: =+(IF(P301="PUBLICA(1)",1,IF(P301="USO INTERNO(2)",2,IF(P301="RESTRINGIDO(3)",3,3))))+(IF(Q301="BAJA(1)",1,IF(Q301="MEDIA(2)",2,IF(Q301="ALTA(3)",3,3))))+(IF(R301="BAJA(1)",1,IF(R301="MEDIA(2)",2,IF(R301="ALTA(3)",3,3)))) | T301: =+IF(S301<6,"BAJA",IF(S301<8,"MEDIA","ALTA")) | U301: - | V301: 45580 | W301: N/A | X301: =+IFERROR(IF(VLOOKUP(Tabla2[[#This Row],[ID]],'EVALUACION DE RIESGO'!A:A,1,FALSE)=Tabla2[[#This Row],[ID]],"SI","NO"),"NO")
A302: 4-GNE | B302: PRODUCTIVO | C302: Gestión de Negocios | D302: GNE | E302: Gestión de Marketing | F302: - | G302: Diseño y ejecución de campañas publicitarias | H302: Campaña publicitaria integral o específica | I302: Actividad promocional que puede ser general (integral) o centrada en un producto o servicio específico, con estrategias y tácticas detalladas. | J302: Jefe de Marketing | K302: Jefe de Marketing | L302: UBICACIÓN DIGITAL-EQUIPO DEL RESPONSABLE | M302: DISCOS DUROS, SERVIDORES, DISCOS O MEDIOS PORTÁTILES, CINTAS O MEDIOS DE VIDEO Y AUDIO, ETC. | N302: PRIMARIOS | O302: DOCUMENTOS TÉCNICOS | P302: USO INTERNO(2) | Q302: BAJA(1) | R302: BAJA(1) | S302: =+(IF(P302="PUBLICA(1)",1,IF(P302="USO INTERNO(2)",2,IF(P302="RESTRINGIDO(3)",3,3))))+(IF(Q302="BAJA(1)",1,IF(Q302="MEDIA(2)",2,IF(Q302="ALTA(3)",3,3))))+(IF(R302="BAJA(1)",1,IF(R302="MEDIA(2)",2,IF(R302="ALTA(3)",3,3)))) | T302: =+IF(S302<6,"BAJA",IF(S302<8,"MEDIA","ALTA")) | U302: - | V302: 45580 | W302: N/A | X302: =+IFERROR(IF(VLOOKUP(Tabla2[[#This Row],[ID]],'EVALUACION DE RIESGO'!A:A,1,FALSE)=Tabla2[[#This Row],[ID]],"SI","NO"),"NO")
A303: 5-GNE | B303: PRODUCTIVO | C303: Gestión de Negocios | D303: GNE | E303: Gestión de Marketing | F303: - | G303: Diseño y ejecución de campañas publicitarias | H303: Certificaciones de Pautaje. | I303: Documentos que certifican el tiempo, el espacio o los medios utilizados para la difusión de una campaña publicitaria. | J303: Jefe de Marketing | K303: Jefe de Marketing | L303: UBICACIÓN DIGITAL-EQUIPO DEL RESPONSABLE | M303: DISCOS DUROS, SERVIDORES, DISCOS O MEDIOS PORTÁTILES, CINTAS O MEDIOS DE VIDEO Y AUDIO, ETC. | N303: PRIMARIOS | O303: DOCUMENTOS TÉCNICOS | P303: USO INTERNO(2) | Q303: MEDIA(2) | R303: BAJA(1) | S303: =+(IF(P303="PUBLICA(1)",1,IF(P303="USO INTERNO(2)",2,IF(P303="RESTRINGIDO(3)",3,3))))+(IF(Q303="BAJA(1)",1,IF(Q303="MEDIA(2)",2,IF(Q303="ALTA(3)",3,3))))+(IF(R303="BAJA(1)",1,IF(R303="MEDIA(2)",2,IF(R303="ALTA(3)",3,3)))) | T303: =+IF(S303<6,"BAJA",IF(S303<8,"MEDIA","ALTA")) | U303: - | V303: 45580 | W303: N/A | X303: =+IFERROR(IF(VLOOKUP(Tabla2[[#This Row],[ID]],'EVALUACION DE RIESGO'!A:A,1,FALSE)=Tabla2[[#This Row],[ID]],"SI","NO"),"NO")
A304: 6-GNE | B304: PRODUCTIVO | C304: Gestión de Negocios | D304: GNE | E304: Gestión de Marketing | F304: - | G304: Diseño y ejecución de campañas publicitarias | H304: Análisis de resultados de campañas publicitarias. | I304: Evaluación del impacto y el rendimiento de las campañas de marketing y publicidad, con indicadores clave de rendimiento (KPI). | J304: Jefe de Marketing | K304: Jefe de Marketing | L304: UBICACIÓN DIGITAL-EQUIPO DEL RESPONSABLE | M304: DISCOS DUROS, SERVIDORES, DISCOS O MEDIOS PORTÁTILES, CINTAS O MEDIOS DE VIDEO Y AUDIO, ETC. | N304: PRIMARIOS | O304: DOCUMENTOS TÉCNICOS | P304: USO INTERNO(2) | Q304: MEDIA(2) | R304: MEDIA(2) | S304: =+(IF(P304="PUBLICA(1)",1,IF(P304="USO INTERNO(2)",2,IF(P304="RESTRINGIDO(3)",3,3))))+(IF(Q304="BAJA(1)",1,IF(Q304="MEDIA(2)",2,IF(Q304="ALTA(3)",3,3))))+(IF(R304="BAJA(1)",1,IF(R304="MEDIA(2)",2,IF(R304="ALTA(3)",3,3)))) | T304: =+IF(S304<6,"BAJA",IF(S304<8,"MEDIA","ALTA")) | U304: - | V304: 45580 | W304: N/A | X304: =+IFERROR(IF(VLOOKUP(Tabla2[[#This Row],[ID]],'EVALUACION DE RIESGO'!A:A,1,FALSE)=Tabla2[[#This Row],[ID]],"SI","NO"),"NO")
A305: 7-GNE | B305: PRODUCTIVO | C305: Gestión de Negocios | D305: GNE | E305: Gestión de Marketing | F305: - | G305: Diseño y ejecución de campañas publicitarias | H305: Matriz de revisión de la publicidad. | I305: Herramienta que permite hacer un seguimiento y revisión de los distintos elementos de la campaña publicitaria, para asegurar la alineación con los objetivos. | J305: Jefe de Marketing | K305: Jefe de Marketing | L305: UBICACIÓN DIGITAL-EQUIPO DEL RESPONSABLE | M305: DISCOS DUROS, SERVIDORES, DISCOS O MEDIOS PORTÁTILES, CINTAS O MEDIOS DE VIDEO Y AUDIO, ETC. | N305: PRIMARIOS | O305: DOCUMENTOS TÉCNICOS | P305: USO INTERNO(2) | Q305: BAJA(1) | R305: BAJA(1) | S305: =+(IF(P305="PUBLICA(1)",1,IF(P305="USO INTERNO(2)",2,IF(P305="RESTRINGIDO(3)",3,3))))+(IF(Q305="BAJA(1)",1,IF(Q305="MEDIA(2)",2,IF(Q305="ALTA(3)",3,3))))+(IF(R305="BAJA(1)",1,IF(R305="MEDIA(2)",2,IF(R305="ALTA(3)",3,3)))) | T305: =+IF(S305<6,"BAJA",IF(S305<8,"MEDIA","ALTA")) | U305: - | V305: 45580 | W305: N/A | X305: =+IFERROR(IF(VLOOKUP(Tabla2[[#This Row],[ID]],'EVALUACION DE RIESGO'!A:A,1,FALSE)=Tabla2[[#This Row],[ID]],"SI","NO"),"NO")
A306: 8-GNE | B306: PRODUCTIVO | C306: Gestión de Negocios | D306: GNE | E306: Gestión de Marketing | F306: - | G306: Diseño y elaboración de promocionales y merchandising | H306: Acta entrega de material promocional a oficinas. | I306: documento que certifica la entrega formal del material de marketing a las oficinas para su distribución. | J306: Jefe de Marketing | K306: Jefe de Marketing | L306: UBICACIÓN DIGITAL-EQUIPO DEL RESPONSABLE | M306: DISCOS DUROS, SERVIDORES, DISCOS O MEDIOS PORTÁTILES, CINTAS O MEDIOS DE VIDEO Y AUDIO, ETC. | N306: PRIMARIOS | O306: DOCUMENTOS TÉCNICOS | P306: USO INTERNO(2) | Q306: MEDIA(2) | R306: MEDIA(2) | S306: =+(IF(P306="PUBLICA(1)",1,IF(P306="USO INTERNO(2)",2,IF(P306="RESTRINGIDO(3)",3,3))))+(IF(Q306="BAJA(1)",1,IF(Q306="MEDIA(2)",2,IF(Q306="ALTA(3)",3,3))))+(IF(R306="BAJA(1)",1,IF(R306="MEDIA(2)",2,IF(R306="ALTA(3)",3,3)))) | T306: =+IF(S306<6,"BAJA",IF(S306<8,"MEDIA","ALTA")) | U306: - | V306: 45580 | W306: N/A | X306: =+IFERROR(IF(VLOOKUP(Tabla2[[#This Row],[ID]],'EVALUACION DE RIESGO'!A:A,1,FALSE)=Tabla2[[#This Row],[ID]],"SI","NO"),"NO")
A307: 9-GNE | B307: PRODUCTIVO | C307: Gestión de Negocios | D307: GNE | E307: Gestión de Marketing | F307: - | G307: Diseño y elaboración de promocionales y merchandising | H307: Registro de entrega de promocionales. | I307: Base de datos o listado que lleva el control de la entrega de materiales promocionales, como folletos, flyers y otros productos. | J307: Jefe de Marketing | K307: Jefe de Marketing | L307: UBICACIÓN DIGITAL-EQUIPO DEL RESPONSABLE | M307: DISCOS DUROS, SERVIDORES, DISCOS O MEDIOS PORTÁTILES, CINTAS O MEDIOS DE VIDEO Y AUDIO, ETC. | N307: PRIMARIOS | O307: DOCUMENTOS TÉCNICOS | P307: USO INTERNO(2) | Q307: MEDIA(2) | R307: MEDIA(2) | S307: =+(IF(P307="PUBLICA(1)",1,IF(P307="USO INTERNO(2)",2,IF(P307="RESTRINGIDO(3)",3,3))))+(IF(Q307="BAJA(1)",1,IF(Q307="MEDIA(2)",2,IF(Q307="ALTA(3)",3,3))))+(IF(R307="BAJA(1)",1,IF(R307="MEDIA(2)",2,IF(R307="ALTA(3)",3,3)))) | T307: =+IF(S307<6,"BAJA",IF(S307<8,"MEDIA","ALTA")) | U307: - | V307: 45580 | W307: N/A | X307: =+IFERROR(IF(VLOOKUP(Tabla2[[#This Row],[ID]],'EVALUACION DE RIESGO'!A:A,1,FALSE)=Tabla2[[#This Row],[ID]],"SI","NO"),"NO")
... A782: 79-GTI | B782: APOYO | C782: Gestión de Tecnología de la Información | D782: GTI | E782: Gestión de Seguridad Informática | F782: - | G782: Gestión de respaldos | H782: Veeam Backup | I782: Servidor de copias de seguridad 192.168.100.233 | J782: GERENTE DE TI | K782: ADMINISTRADOR DE SEGURIDAD INFORMÁTICA | L782: UBICACIÓN FISICA-SUCURSAL IBARRA | M782: DISCOS DUROS, SERVIDORES, DISCOS O MEDIOS PORTÁTILES, CINTAS O MEDIOS DE VIDEO Y AUDIO, ETC. | N782: APOYO | O782: HARDWARE | P782: USO INTERNO(2) | Q782: MEDIA(2) | R782: MEDIA(2) | S782: =+(IF(P782="PUBLICA(1)",1,IF(P782="USO INTERNO(2)",2,IF(P782="RESTRINGIDO(3)",3,3))))+(IF(Q782="BAJA(1)",1,IF(Q782="MEDIA(2)",2,IF(Q782="ALTA(3)",3,3))))+(IF(R782="BAJA(1)",1,IF(R782="MEDIA(2)",2,IF(R782="ALTA(3)",3,3)))) | T782: =+IF(S782<6,"BAJA",IF(S782<8,"MEDIA","ALTA")) | U782: - | V782: 43815 | W782: N/A | X782: =+IFERROR(IF(VLOOKUP(Tabla2[[#This Row],[ID]],'EVALUACION DE RIESGO'!A:A,1,FALSE)=Tabla2[[#This Row],[ID]],"SI","NO"),"NO")
A783: 80-GTI | B783: APOYO | C783: Gestión de Tecnología de la Información | D783: GTI | E783: Gestión de Seguridad Informática | F783: - | G783: N/A | H783: Administrador de Seguridad Informática | I783: Funcionarios con el cargo de Administrador de Seguridad Informática | J783: N/A | K783: N/A | L783: N/A | M783: N/A | N783: APOYO | O783: RECURSO HUMANO | P783: USO INTERNO(2) | Q783: ALTA(3) | R783: ALTA(3) | S783: =+(IF(P783="PUBLICA(1)",1,IF(P783="USO INTERNO(2)",2,IF(P783="RESTRINGIDO(3)",3,3))))+(IF(Q783="BAJA(1)",1,IF(Q783="MEDIA(2)",2,IF(Q783="ALTA(3)",3,3))))+(IF(R783="BAJA(1)",1,IF(R783="MEDIA(2)",2,IF(R783="ALTA(3)",3,3)))) | T783: =+IF(S783<6,"BAJA",IF(S783<8,"MEDIA","ALTA")) | U783: - | V783: N/A | W783: N/A | X783: =+IFERROR(IF(VLOOKUP(Tabla2[[#This Row],[ID]],'EVALUACION DE RIESGO'!A:A,1,FALSE)=Tabla2[[#This Row],[ID]],"SI","NO"),"NO")
A784: 81-GTI | B784: APOYO | C784: Gestión de Tecnología de la Información | D784: GTI | E784: Gestión de Seguridad Informática | F784: - | G784: N/A | H784: Administrador de Base de Datos | I784: Funcionarios con el cargo de Administrador de Base de Datos | J784: N/A | K784: N/A | L784: N/A | M784: N/A | N784: APOYO | O784: RECURSO HUMANO | P784: USO INTERNO(2) | Q784: ALTA(3) | R784: ALTA(3) | S784: =+(IF(P784="PUBLICA(1)",1,IF(P784="USO INTERNO(2)",2,IF(P784="RESTRINGIDO(3)",3,3))))+(IF(Q784="BAJA(1)",1,IF(Q784="MEDIA(2)",2,IF(Q784="ALTA(3)",3,3))))+(IF(R784="BAJA(1)",1,IF(R784="MEDIA(2)",2,IF(R784="ALTA(3)",3,3)))) | T784: =+IF(S784<6,"BAJA",IF(S784<8,"MEDIA","ALTA")) | U784: - | V784: 43815 | W784: N/A | X784: =+IFERROR(IF(VLOOKUP(Tabla2[[#This Row],[ID]],'EVALUACION DE RIESGO'!A:A,1,FALSE)=Tabla2[[#This Row],[ID]],"SI","NO"),"NO")
A785: 82-GTI | B785: APOYO | C785: Gestión de Tecnología de la Información | D785: GTI | E785: Gestión de las Operaciones de TI | F785: - | G785: Administración de la Capacidad y Desempeño de la infraestructura de TI | H785: Pandora FMS | I785: Herramienta de monitoreo de los recursos tecnológicos instalado en el equipo 192.18.20.117 - Servidor PANDORA FMS Enterprise 7.0NG 760 | J785: GERENTE DE TI | K785: ADMINISTRADOR DE COMUNICACIÓN E INFRESTRUCTURA | L785: UBICACIÓN FISICA-MATRIZ ATUNTAQUI | M785: DOCUMENTO DE ARCHIVO-FÍSICO | N785: APOYO | O785: SOFTWARE | P785: USO INTERNO(2) | Q785: BAJA(1) | R785: ALTA(3) | S785: =+(IF(P785="PUBLICA(1)",1,IF(P785="USO INTERNO(2)",2,IF(P785="RESTRINGIDO(3)",3,3))))+(IF(Q785="BAJA(1)",1,IF(Q785="MEDIA(2)",2,IF(Q785="ALTA(3)",3,3))))+(IF(R785="BAJA(1)",1,IF(R785="MEDIA(2)",2,IF(R785="ALTA(3)",3,3)))) | T785: =+IF(S785<6,"BAJA",IF(S785<8,"MEDIA","ALTA")) | U785: - | V785: 43815 | W785: N/A | X785: =+IFERROR(IF(VLOOKUP(Tabla2[[#This Row],[ID]],'EVALUACION DE RIESGO'!A:A,1,FALSE)=Tabla2[[#This Row],[ID]],"SI","NO"),"NO")
A786: 83-GTI | B786: APOYO | C786: Gestión de Tecnología de la Información | D786: GTI | E786: Gestión de las Operaciones de TI | F786: - | G786: Administración de servidores | H786: Isabel / pbx-atuntaqui | I786: Servidor de telefonía IP / 192.168.20.200 | J786: GERENTE DE TI | K786: ADMINISTRADOR DE COMUNICACIÓN E INFRESTRUCTURA | L786: UBICACIÓN FISICA-MATRIZ ATUNTAQUI | M786: DISCOS DUROS, SERVIDORES, DISCOS O MEDIOS PORTÁTILES, CINTAS O MEDIOS DE VIDEO Y AUDIO, ETC. | N786: APOYO | O786: HARDWARE | P786: USO INTERNO(2) | Q786: BAJA(1) | R786: ALTA(3) | S786: =+(IF(P786="PUBLICA(1)",1,IF(P786="USO INTERNO(2)",2,IF(P786="RESTRINGIDO(3)",3,3))))+(IF(Q786="BAJA(1)",1,IF(Q786="MEDIA(2)",2,IF(Q786="ALTA(3)",3,3))))+(IF(R786="BAJA(1)",1,IF(R786="MEDIA(2)",2,IF(R786="ALTA(3)",3,3)))) | T786: =+IF(S786<6,"BAJA",IF(S786<8,"MEDIA","ALTA")) | U786: - | V786: 43815 | W786: N/A | X786: =+IFERROR(IF(VLOOKUP(Tabla2[[#This Row],[ID]],'EVALUACION DE RIESGO'!A:A,1,FALSE)=Tabla2[[#This Row],[ID]],"SI","NO"),"NO")
A787: 84-GTI | B787: APOYO | C787: Gestión de Tecnología de la Información | D787: GTI | E787: Gestión de las Operaciones de TI | F787: - | G787: Administración de servidores | H787: Isabel / pbx-ibarra | I787: Servidor de telefonía IP / 192.168.100.200 | J787: GERENTE DE TI | K787: ADMINISTRADOR DE COMUNICACIÓN E INFRESTRUCTURA | L787: UBICACIÓN FISICA-MATRIZ ATUNTAQUI | M787: DISCOS DUROS, SERVIDORES, DISCOS O MEDIOS PORTÁTILES, CINTAS O MEDIOS DE VIDEO Y AUDIO, ETC. | N787: APOYO | O787: HARDWARE | P787: USO INTERNO(2) | Q787: BAJA(1) | R787: ALTA(3) | S787: =+(IF(P787="PUBLICA(1)",1,IF(P787="USO INTERNO(2)",2,IF(P787="RESTRINGIDO(3)",3,3))))+(IF(Q787="BAJA(1)",1,IF(Q787="MEDIA(2)",2,IF(Q787="ALTA(3)",3,3))))+(IF(R787="BAJA(1)",1,IF(R787="MEDIA(2)",2,IF(R787="ALTA(3)",3,3)))) | T787: =+IF(S787<6,"BAJA",IF(S787<8,"MEDIA","ALTA")) | U787: - | V787: 43815 | W787: N/A | X787: =+IFERROR(IF(VLOOKUP(Tabla2[[#This Row],[ID]],'EVALUACION DE RIESGO'!A:A,1,FALSE)=Tabla2[[#This Row],[ID]],"SI","NO"),"NO")
A788: 85-GTI | B788: APOYO | C788: Gestión de Tecnología de la Información | D788: GTI | E788: Gestión de las Operaciones de TI | F788: - | G788: Administración de la capacidad y desempeño de la infraestructura de TI | H788: Ruteador CISCO 1900 Series (02) | I788: Ruteador para enlaces de comunicación / 192.168.100.253 | J788: GERENTE DE TI | K788: ADMINISTRADOR DE COMUNICACIÓN E INFRESTRUCTURA | L788: UBICACIÓN FISICA-SUCURSAL IBARRA | M788: DISCOS DUROS, SERVIDORES, DISCOS O MEDIOS PORTÁTILES, CINTAS O MEDIOS DE VIDEO Y AUDIO, ETC. | N788: APOYO | O788: REDES | P788: RESTRINGIDO(3) | Q788: ALTA(3) | R788: ALTA(3) | S788: =+(IF(P788="PUBLICA(1)",1,IF(P788="USO INTERNO(2)",2,IF(P788="RESTRINGIDO(3)",3,3))))+(IF(Q788="BAJA(1)",1,IF(Q788="MEDIA(2)",2,IF(Q788="ALTA(3)",3,3))))+(IF(R788="BAJA(1)",1,IF(R788="MEDIA(2)",2,IF(R788="ALTA(3)",3,3)))) | T788: =+IF(S788<6,"BAJA",IF(S788<8,"MEDIA","ALTA")) | U788: - | V788: 43815 | W788: N/A | X788: =+IFERROR(IF(VLOOKUP(Tabla2[[#This Row],[ID]],'EVALUACION DE RIESGO'!A:A,1,FALSE)=Tabla2[[#This Row],[ID]],"SI","NO"),"NO")
A789: 86-GTI | B789: APOYO | C789: Gestión de Tecnología de la Información | D789: GTI | E789: Gestión de las Operaciones de TI | F789: - | G789: Administración de la capacidad y desempeño de la infraestructura de TI | H789: Ruteador CISCO 1900 Series (03) | I789: Ruteador para enlaces de comunicación / 192.168.40.253 | J789: GERENTE DE TI | K789: ADMINISTRADOR DE COMUNICACIÓN E INFRESTRUCTURA | L789: UBICACIÓN FISICA-SUCURSAL OTAVALO | M789: DISCOS DUROS, SERVIDORES, DISCOS O MEDIOS PORTÁTILES, CINTAS O MEDIOS DE VIDEO Y AUDIO, ETC. | N789: APOYO | O789: REDES | P789: RESTRINGIDO(3) | Q789: ALTA(3) | R789: ALTA(3) | S789: =+(IF(P789="PUBLICA(1)",1,IF(P789="USO INTERNO(2)",2,IF(P789="RESTRINGIDO(3)",3,3))))+(IF(Q789="BAJA(1)",1,IF(Q789="MEDIA(2)",2,IF(Q789="ALTA(3)",3,3))))+(IF(R789="BAJA(1)",1,IF(R789="MEDIA(2)",2,IF(R789="ALTA(3)",3,3)))) | T789: =+IF(S789<6,"BAJA",IF(S789<8,"MEDIA","ALTA")) | U789: - | V789: 43815 | W789: N/A | X789: =+IFERROR(IF(VLOOKUP(Tabla2[[#This Row],[ID]],'EVALUACION DE RIESGO'!A:A,1,FALSE)=Tabla2[[#This Row],[ID]],"SI","NO"),"NO")
A790: 87-GTI | B790: APOYO | C790: Gestión de Tecnología de la Información | D790: GTI | E790: Gestión de las Operaciones de TI | F790: - | G790: Administración de la capacidad y desempeño de la infraestructura de TI | H790: Ruteador CISCO 1900 Series (04) | I790: Ruteador para enlaces de comunicación / 192.168.50.253 | J790: GERENTE DE TI | K790: ADMINISTRADOR DE COMUNICACIÓN E INFRESTRUCTURA | L790: UBICACIÓN FISICA-AGENCIA PIMAMPIRO | M790: DISCOS DUROS, SERVIDORES, DISCOS O MEDIOS PORTÁTILES, CINTAS O MEDIOS DE VIDEO Y AUDIO, ETC. | N790: APOYO | O790: REDES | P790: RESTRINGIDO(3) | Q790: ALTA(3) | R790: ALTA(3) | S790: =+(IF(P790="PUBLICA(1)",1,IF(P790="USO INTERNO(2)",2,IF(P790="RESTRINGIDO(3)",3,3))))+(IF(Q790="BAJA(1)",1,IF(Q790="MEDIA(2)",2,IF(Q790="ALTA(3)",3,3))))+(IF(R790="BAJA(1)",1,IF(R790="MEDIA(2)",2,IF(R790="ALTA(3)",3,3)))) | T790: =+IF(S790<6,"BAJA",IF(S790<8,"MEDIA","ALTA")) | U790: - | V790: 43815 | W790: N/A | X790: =+IFERROR(IF(VLOOKUP(Tabla2[[#This Row],[ID]],'EVALUACION DE RIESGO'!A:A,1,FALSE)=Tabla2[[#This Row],[ID]],"SI","NO"),"NO")
A791: 88-GTI | B791: APOYO | C791: Gestión de Tecnología de la Información | D791: GTI | E791: Gestión de las Operaciones de TI | F791: - | G791: Administración de seguridad en equipos y servidores de aplicación | H791: ATUNPRODU | I791: Servidor que contiene el servidor BDD Oracle / SERVIDOR APARK 192.168.10.72 | J791: GERENTE DE TI | K791: ADMINISTRADOR DE BASE DE DATOS | L791: UBICACIÓN FISICA-SUCURSAL IBARRA | M791: DISCOS DUROS, SERVIDORES, DISCOS O MEDIOS PORTÁTILES, CINTAS O MEDIOS DE VIDEO Y AUDIO, ETC. | N791: APOYO | O791: HARDWARE | P791: RESTRINGIDO(3) | Q791: ALTA(3) | R791: ALTA(3) | S791: =+(IF(P791="PUBLICA(1)",1,IF(P791="USO INTERNO(2)",2,IF(P791="RESTRINGIDO(3)",3,3))))+(IF(Q791="BAJA(1)",1,IF(Q791="MEDIA(2)",2,IF(Q791="ALTA(3)",3,3))))+(IF(R791="BAJA(1)",1,IF(R791="MEDIA(2)",2,IF(R791="ALTA(3)",3,3)))) | T791: =+IF(S791<6,"BAJA",IF(S791<8,"MEDIA","ALTA")) | U791: - | V791: 43815 | W791: N/A | X791: =+IFERROR(IF(VLOOKUP(Tabla2[[#This Row],[ID]],'EVALUACION DE RIESGO'!A:A,1,FALSE)=Tabla2[[#This Row],[ID]],"SI","NO"),"NO")
A792: 89-GTI | B792: APOYO | C792: Gestión de Tecnología de la Información | D792: GTI | E792: Gestión de las Operaciones de TI | F792: - | G792: Administración de la capacidad y desempeño de la infraestructura de TI | H792: Ruteador CISCO 880 Series (05) | I792: Ruteador para enlaces de comunicación / 192.168.60.253 | J792: GERENTE DE TI | K792: ADMINISTRADOR DE COMUNICACIÓN E INFRESTRUCTURA | L792: UBICACIÓN FISICA-AGENCIA COTACACHI | M792: DISCOS DUROS, SERVIDORES, DISCOS O MEDIOS PORTÁTILES, CINTAS O MEDIOS DE VIDEO Y AUDIO, ETC. | N792: APOYO | O792: REDES | P792: RESTRINGIDO(3) | Q792: ALTA(3) | R792: ALTA(3) | S792: =+(IF(P792="PUBLICA(1)",1,IF(P792="USO INTERNO(2)",2,IF(P792="RESTRINGIDO(3)",3,3))))+(IF(Q792="BAJA(1)",1,IF(Q792="MEDIA(2)",2,IF(Q792="ALTA(3)",3,3))))+(IF(R792="BAJA(1)",1,IF(R792="MEDIA(2)",2,IF(R792="ALTA(3)",3,3)))) | T792: =+IF(S792<6,"BAJA",IF(S792<8,"MEDIA","ALTA")) | U792: - | V792: 43815 | W792: N/A | X792: =+IFERROR(IF(VLOOKUP(Tabla2[[#This Row],[ID]],'EVALUACION DE RIESGO'!A:A,1,FALSE)=Tabla2[[#This Row],[ID]],"SI","NO"),"NO")
A793: 90-GTI | B793: APOYO | C793: Gestión de Tecnología de la Información | D793: GTI | E793: Gestión de las Operaciones de TI | F793: - | G793: Administración de la capacidad y desempeño de la infraestructura de TI | H793: Ruteador CISCO 1800 Series (06) | I793: Ruteador para enlaces de comunicación / 192.168.31.253 | J793: GERENTE DE TI | K793: ADMINISTRADOR DE COMUNICACIÓN E INFRESTRUCTURA | L793: UBICACIÓN FISICA-AGENCIA IBARRA | M793: DISCOS DUROS, SERVIDORES, DISCOS O MEDIOS PORTÁTILES, CINTAS O MEDIOS DE VIDEO Y AUDIO, ETC. | N793: APOYO | O793: REDES | P793: RESTRINGIDO(3) | Q793: ALTA(3) | R793: ALTA(3) | S793: =+(IF(P793="PUBLICA(1)",1,IF(P793="USO INTERNO(2)",2,IF(P793="RESTRINGIDO(3)",3,3))))+(IF(Q793="BAJA(1)",1,IF(Q793="MEDIA(2)",2,IF(Q793="ALTA(3)",3,3))))+(IF(R793="BAJA(1)",1,IF(R793="MEDIA(2)",2,IF(R793="ALTA(3)",3,3)))) | T793: =+IF(S793<6,"BAJA",IF(S793<8,"MEDIA","ALTA")) | U793: - | V793: 43815 | W793: N/A | X793: =+IFERROR(IF(VLOOKUP(Tabla2[[#This Row],[ID]],'EVALUACION DE RIESGO'!A:A,1,FALSE)=Tabla2[[#This Row],[ID]],"SI","NO"),"NO")
A794: 91-GTI | B794: APOYO | C794: Gestión de Tecnología de la Información | D794: GTI | E794: Gestión de las Operaciones de TI | F794: - | G794: Administración de la capacidad y desempeño de la infraestructura de TI | H794: Ruteador CISCO 1800 Series (07) | I794: Ruteador para enlaces de comunicación / 192.168.80.253 | J794: GERENTE DE TI | K794: ADMINISTRADOR DE COMUNICACIÓN E INFRESTRUCTURA | L794: UBICACIÓN FISICA-AGENCIA EL EJIDO | M794: DISCOS DUROS, SERVIDORES, DISCOS O MEDIOS PORTÁTILES, CINTAS O MEDIOS DE VIDEO Y AUDIO, ETC. | N794: APOYO | O794: REDES | P794: RESTRINGIDO(3) | Q794: ALTA(3) | R794: ALTA(3) | S794: =+(IF(P794="PUBLICA(1)",1,IF(P794="USO INTERNO(2)",2,IF(P794="RESTRINGIDO(3)",3,3))))+(IF(Q794="BAJA(1)",1,IF(Q794="MEDIA(2)",2,IF(Q794="ALTA(3)",3,3))))+(IF(R794="BAJA(1)",1,IF(R794="MEDIA(2)",2,IF(R794="ALTA(3)",3,3)))) | T794: =+IF(S794<6,"BAJA",IF(S794<8,"MEDIA","ALTA")) | U794: - | V794: 43815 | W794: N/A | X794: =+IFERROR(IF(VLOOKUP(Tabla2[[#This Row],[ID]],'EVALUACION DE RIESGO'!A:A,1,FALSE)=Tabla2[[#This Row],[ID]],"SI","NO"),"NO")
A795: 92-GTI | B795: APOYO | C795: Gestión de Tecnología de la Información | D795: GTI | E795: Gestión de las Operaciones de TI | F795: - | G795: Administración de la capacidad y desempeño de la infraestructura de TI | H795: Ruteador CISCO 1800 Series (09) | I795: Ruteador para enlaces de comunicación / 192.168.82.253 | J795: GERENTE DE TI | K795: ADMINISTRADOR DE COMUNICACIÓN E INFRESTRUCTURA | L795: UBICACIÓN FISICA-AGENCIA CARAPUNGO | M795: DISCOS DUROS, SERVIDORES, DISCOS O MEDIOS PORTÁTILES, CINTAS O MEDIOS DE VIDEO Y AUDIO, ETC. | N795: APOYO | O795: REDES | P795: RESTRINGIDO(3) | Q795: ALTA(3) | R795: ALTA(3) | S795: =+(IF(P795="PUBLICA(1)",1,IF(P795="USO INTERNO(2)",2,IF(P795="RESTRINGIDO(3)",3,3))))+(IF(Q795="BAJA(1)",1,IF(Q795="MEDIA(2)",2,IF(Q795="ALTA(3)",3,3))))+(IF(R795="BAJA(1)",1,IF(R795="MEDIA(2)",2,IF(R795="ALTA(3)",3,3)))) | T795: =+IF(S795<6,"BAJA",IF(S795<8,"MEDIA","ALTA")) | U795: - | V795: 43815 | W795: N/A | X795: =+IFERROR(IF(VLOOKUP(Tabla2[[#This Row],[ID]],'EVALUACION DE RIESGO'!A:A,1,FALSE)=Tabla2[[#This Row],[ID]],"SI","NO"),"NO")
... A822: 119-GTI | B822: APOYO | C822: Gestión de Tecnología de la Información | D822: GTI | E822: Gestión de las Operaciones de TI | F822: - | G822: N/A | H822: Administrador de Comunicación e Infrestructura | I822: Funcionarios con el cargo de Administrador de Comunicación e Infraestructura - Consolas Operador Oracle VM - Web Service SERVIPAGOS | J822: N/A | K822: N/A | L822: N/A | M822: N/A | N822: APOYO | O822: RECURSO HUMANO | P822: USO INTERNO(2) | Q822: ALTA(3) | R822: ALTA(3) | S822: =+(IF(P822="PUBLICA(1)",1,IF(P822="USO INTERNO(2)",2,IF(P822="RESTRINGIDO(3)",3,3))))+(IF(Q822="BAJA(1)",1,IF(Q822="MEDIA(2)",2,IF(Q822="ALTA(3)",3,3))))+(IF(R822="BAJA(1)",1,IF(R822="MEDIA(2)",2,IF(R822="ALTA(3)",3,3)))) | T822: =+IF(S822<6,"BAJA",IF(S822<8,"MEDIA","ALTA")) | U822: - | V822: 43815 | W822: N/A | X822: =+IFERROR(IF(VLOOKUP(Tabla2[[#This Row],[ID]],'EVALUACION DE RIESGO'!A:A,1,FALSE)=Tabla2[[#This Row],[ID]],"SI","NO"),"NO")
A823: 120-GTI | B823: APOYO | C823: Gestión de Tecnología de la Información | D823: GTI | E823: Gestión de las Operaciones de TI | F823: - | G823: N/A | H823: Administrador de Base de Datos | I823: Funcionarios con el cargo de Administrador de Base de Datos | J823: N/A | K823: N/A | L823: N/A | M823: N/A | N823: APOYO | O823: RECURSO HUMANO | P823: USO INTERNO(2) | Q823: ALTA(3) | R823: ALTA(3) | S823: =+(IF(P823="PUBLICA(1)",1,IF(P823="USO INTERNO(2)",2,IF(P823="RESTRINGIDO(3)",3,3))))+(IF(Q823="BAJA(1)",1,IF(Q823="MEDIA(2)",2,IF(Q823="ALTA(3)",3,3))))+(IF(R823="BAJA(1)",1,IF(R823="MEDIA(2)",2,IF(R823="ALTA(3)",3,3)))) | T823: =+IF(S823<6,"BAJA",IF(S823<8,"MEDIA","ALTA")) | U823: - | V823: N/A | W823: N/A | X823: =+IFERROR(IF(VLOOKUP(Tabla2[[#This Row],[ID]],'EVALUACION DE RIESGO'!A:A,1,FALSE)=Tabla2[[#This Row],[ID]],"SI","NO"),"NO")
A824: 1-GES | B824: ESTRATÉGICO | C824: Gestión Estratégica | D824: GES | E824: Planificación Estratégica | F824: - | G824: Preparación para la construcción de la Planificación Estratégica | H824: Cronograma de trabajo | I824: Análisis de la situación actual | J824: JEFE DE PLANIFICACIÓN Y PROCESOS | K824: JEFE DE PLANIFICACIÓN Y PROCESOS | L824: UBICACIÓN DIGITAL-EQUIPO DEL CUSTODIO | M824: DOCUMENTO DE ARCHIVO-ELECTRÓNICO | N824: PRIMARIOS | O824: DOCUMENTOS TÉCNICOS | P824: PUBLICA(1) | Q824: BAJA(1) | R824: BAJA(1) | S824: =+(IF(P824="PUBLICA(1)",1,IF(P824="USO INTERNO(2)",2,IF(P824="RESTRINGIDO(3)",3,3))))+(IF(Q824="BAJA(1)",1,IF(Q824="MEDIA(2)",2,IF(Q824="ALTA(3)",3,3))))+(IF(R824="BAJA(1)",1,IF(R824="MEDIA(2)",2,IF(R824="ALTA(3)",3,3)))) | T824: =+IF(S824<6,"BAJA",IF(S824<8,"MEDIA","ALTA")) | U824: - | V824: 45681 | W824: N/A | X824: =+IFERROR(IF(VLOOKUP(Tabla2[[#This Row],[ID]],'EVALUACION DE RIESGO'!A:A,1,FALSE)=Tabla2[[#This Row],[ID]],"SI","NO"),"NO")
A825: 2-GES | B825: ESTRATÉGICO | C825: Gestión Estratégica | D825: GES | E825: Planificación Estratégica | F825: - | G825: Preparación para la construcción de la Planificación Estratégica | H825: Solicitud de contratación de asesor externo | I825: TDR para la contratación de bienes y servicios menores | J825: JEFE DE PLANIFICACIÓN Y PROCESOS | K825: JEFE DE PLANIFICACIÓN Y PROCESOS | L825: UBICACIÓN DIGITAL-EQUIPO DEL CUSTODIO | M825: DOCUMENTO DE ARCHIVO-ELECTRÓNICO | N825: PRIMARIOS | O825: DOCUMENTOS TÉCNICOS | P825: PUBLICA(1) | Q825: BAJA(1) | R825: BAJA(1) | S825: =+(IF(P825="PUBLICA(1)",1,IF(P825="USO INTERNO(2)",2,IF(P825="RESTRINGIDO(3)",3,3))))+(IF(Q825="BAJA(1)",1,IF(Q825="MEDIA(2)",2,IF(Q825="ALTA(3)",3,3))))+(IF(R825="BAJA(1)",1,IF(R825="MEDIA(2)",2,IF(R825="ALTA(3)",3,3)))) | T825: =+IF(S825<6,"BAJA",IF(S825<8,"MEDIA","ALTA")) | U825: - | V825: 45681 | W825: N/A | X825: =+IFERROR(IF(VLOOKUP(Tabla2[[#This Row],[ID]],'EVALUACION DE RIESGO'!A:A,1,FALSE)=Tabla2[[#This Row],[ID]],"SI","NO"),"NO")
A826: 3-GES | B826: ESTRATÉGICO | C826: Gestión Estratégica | D826: GES | E826: Planificación Estratégica | F826: - | G826: Preparación para la construcción de la Planificación Estratégica | H826: Email de solicitud de insumos | I826: Solicitud de requerimientos | J826: JEFE DE PLANIFICACIÓN Y PROCESOS | K826: JEFE DE PLANIFICACIÓN Y PROCESOS | L826: UBICACIÓN DIGITAL-EQUIPO DEL CUSTODIO | M826: SISTEMA DE MENSAJERÍA ELECTRÓNICA | N826: APOYO | O826: SERVICIOS | P826: PUBLICA(1) | Q826: BAJA(1) | R826: BAJA(1) | S826: =+(IF(P826="PUBLICA(1)",1,IF(P826="USO INTERNO(2)",2,IF(P826="RESTRINGIDO(3)",3,3))))+(IF(Q826="BAJA(1)",1,IF(Q826="MEDIA(2)",2,IF(Q826="ALTA(3)",3,3))))+(IF(R826="BAJA(1)",1,IF(R826="MEDIA(2)",2,IF(R826="ALTA(3)",3,3)))) | T826: =+IF(S826<6,"BAJA",IF(S826<8,"MEDIA","ALTA")) | U826: - | V826: 45681 | W826: N/A | X826: =+IFERROR(IF(VLOOKUP(Tabla2[[#This Row],[ID]],'EVALUACION DE RIESGO'!A:A,1,FALSE)=Tabla2[[#This Row],[ID]],"SI","NO"),"NO")
A827: 4-GES | B827: ESTRATÉGICO | C827: Gestión Estratégica | D827: GES | E827: Planificación Estratégica | F827: - | G827: Análisis de la situación actual | H827: Cronograma de trabajo | I827: Lista de actividades para la construción del plan | J827: JEFE DE PLANIFICACIÓN Y PROCESOS | K827: JEFE DE PLANIFICACIÓN Y PROCESOS | L827: UBICACIÓN DIGITAL-EQUIPO DEL CUSTODIO | M827: DOCUMENTO DE ARCHIVO-ELECTRÓNICO | N827: PRIMARIOS | O827: DOCUMENTOS TÉCNICOS | P827: PUBLICA(1) | Q827: BAJA(1) | R827: BAJA(1) | S827: =+(IF(P827="PUBLICA(1)",1,IF(P827="USO INTERNO(2)",2,IF(P827="RESTRINGIDO(3)",3,3))))+(IF(Q827="BAJA(1)",1,IF(Q827="MEDIA(2)",2,IF(Q827="ALTA(3)",3,3))))+(IF(R827="BAJA(1)",1,IF(R827="MEDIA(2)",2,IF(R827="ALTA(3)",3,3)))) | T827: =+IF(S827<6,"BAJA",IF(S827<8,"MEDIA","ALTA")) | U827: - | V827: 45681 | W827: N/A | X827: =+IFERROR(IF(VLOOKUP(Tabla2[[#This Row],[ID]],'EVALUACION DE RIESGO'!A:A,1,FALSE)=Tabla2[[#This Row],[ID]],"SI","NO"),"NO")
A828: 5-GES | B828: ESTRATÉGICO | C828: Gestión Estratégica | D828: GES | E828: Planificación Estratégica | F828: - | G828: Análisis de la situación actual | H828: Email de solicitud de insumos | I828: Solicitud de requerimientos | J828: JEFE DE PLANIFICACIÓN Y PROCESOS | K828: JEFE DE PLANIFICACIÓN Y PROCESOS | L828: UBICACIÓN DIGITAL-EQUIPO DEL CUSTODIO | M828: DOCUMENTO DE ARCHIVO-ELECTRÓNICO | N828: PRIMARIOS | O828: DOCUMENTOS TÉCNICOS | P828: PUBLICA(1) | Q828: BAJA(1) | R828: BAJA(1) | S828: =+(IF(P828="PUBLICA(1)",1,IF(P828="USO INTERNO(2)",2,IF(P828="RESTRINGIDO(3)",3,3))))+(IF(Q828="BAJA(1)",1,IF(Q828="MEDIA(2)",2,IF(Q828="ALTA(3)",3,3))))+(IF(R828="BAJA(1)",1,IF(R828="MEDIA(2)",2,IF(R828="ALTA(3)",3,3)))) | T828: =+IF(S828<6,"BAJA",IF(S828<8,"MEDIA","ALTA")) | U828: - | V828: 45681 | W828: N/A | X828: =+IFERROR(IF(VLOOKUP(Tabla2[[#This Row],[ID]],'EVALUACION DE RIESGO'!A:A,1,FALSE)=Tabla2[[#This Row],[ID]],"SI","NO"),"NO")
A829: 6-GES | B829: ESTRATÉGICO | C829: Gestión Estratégica | D829: GES | E829: Planificación Estratégica | F829: - | G829: Análisis de la situación actual | H829: Estudios de mercado y de competencia | I829: Estudio para analizar la factibilidad de aperturas de oficina o lanzamiento de servicios | J829: GERENTE DE NEGOCIOS | K829: JEFE DE PLANIFICACIÓN Y PROCESOS | L829: UBICACIÓN DIGITAL-EQUIPO DEL CUSTODIO | M829: DOCUMENTO DE ARCHIVO-ELECTRÓNICO | N829: PRIMARIOS | O829: DOCUMENTOS TÉCNICOS | P829: USO INTERNO(2) | Q829: MEDIA(2) | R829: MEDIA(2) | S829: =+(IF(P829="PUBLICA(1)",1,IF(P829="USO INTERNO(2)",2,IF(P829="RESTRINGIDO(3)",3,3))))+(IF(Q829="BAJA(1)",1,IF(Q829="MEDIA(2)",2,IF(Q829="ALTA(3)",3,3))))+(IF(R829="BAJA(1)",1,IF(R829="MEDIA(2)",2,IF(R829="ALTA(3)",3,3)))) | T829: =+IF(S829<6,"BAJA",IF(S829<8,"MEDIA","ALTA")) | U829: - | V829: 45681 | W829: N/A | X829: =+IFERROR(IF(VLOOKUP(Tabla2[[#This Row],[ID]],'EVALUACION DE RIESGO'!A:A,1,FALSE)=Tabla2[[#This Row],[ID]],"SI","NO"),"NO")
A830: 7-GES | B830: ESTRATÉGICO | C830: Gestión Estratégica | D830: GES | E830: Planificación Estratégica | F830: - | G830: Análisis de la situación actual | H830: Estudios de clima laboral | I830: Documento de satisfacción de los empleados en el lugar de trabajo | J830: GERENTE DE TALENTO HUMANO | K830: JEFE DE PLANIFICACIÓN Y PROCESOS | L830: UBICACIÓN DIGITAL-EQUIPO DEL CUSTODIO | M830: DOCUMENTO DE ARCHIVO-ELECTRÓNICO | N830: PRIMARIOS | O830: DOCUMENTOS TÉCNICOS | P830: PUBLICA(1) | Q830: BAJA(1) | R830: BAJA(1) | S830: =+(IF(P830="PUBLICA(1)",1,IF(P830="USO INTERNO(2)",2,IF(P830="RESTRINGIDO(3)",3,3))))+(IF(Q830="BAJA(1)",1,IF(Q830="MEDIA(2)",2,IF(Q830="ALTA(3)",3,3))))+(IF(R830="BAJA(1)",1,IF(R830="MEDIA(2)",2,IF(R830="ALTA(3)",3,3)))) | T830: =+IF(S830<6,"BAJA",IF(S830<8,"MEDIA","ALTA")) | U830: - | V830: 45681 | W830: N/A | X830: =+IFERROR(IF(VLOOKUP(Tabla2[[#This Row],[ID]],'EVALUACION DE RIESGO'!A:A,1,FALSE)=Tabla2[[#This Row],[ID]],"SI","NO"),"NO")
A831: 8-GES | B831: ESTRATÉGICO | C831: Gestión Estratégica | D831: GES | E831: Planificación Estratégica | F831: - | G831: Análisis de la situación actual | H831: Estudios de satisfacción al cliente | I831: Documento de satisfacción de los clientes | J831: JEFE DE ATENCIÓN AL CLIENTE | K831: JEFE DE PLANIFICACIÓN Y PROCESOS | L831: UBICACIÓN DIGITAL-EQUIPO DEL CUSTODIO | M831: DOCUMENTO DE ARCHIVO-ELECTRÓNICO | N831: PRIMARIOS | O831: DOCUMENTOS TÉCNICOS | P831: USO INTERNO(2) | Q831: BAJA(1) | R831: BAJA(1) | S831: =+(IF(P831="PUBLICA(1)",1,IF(P831="USO INTERNO(2)",2,IF(P831="RESTRINGIDO(3)",3,3))))+(IF(Q831="BAJA(1)",1,IF(Q831="MEDIA(2)",2,IF(Q831="ALTA(3)",3,3))))+(IF(R831="BAJA(1)",1,IF(R831="MEDIA(2)",2,IF(R831="ALTA(3)",3,3)))) | T831: =+IF(S831<6,"BAJA",IF(S831<8,"MEDIA","ALTA")) | U831: - | V831: 45681 | W831: N/A | X831: =+IFERROR(IF(VLOOKUP(Tabla2[[#This Row],[ID]],'EVALUACION DE RIESGO'!A:A,1,FALSE)=Tabla2[[#This Row],[ID]],"SI","NO"),"NO")
A832: 9-GES | B832: ESTRATÉGICO | C832: Gestión Estratégica | D832: GES | E832: Planificación Estratégica | F832: - | G832: Análisis de la situación actual | H832: Análisis de Macrotendencias | I832: Pautas para saber las tendencias mundiales, referente a la tecnologia que pueden impactar a la coac | J832: JEFE DE PLANIFICACIÓN Y PROCESOS | K832: JEFE DE PLANIFICACIÓN Y PROCESOS | L832: UBICACIÓN DIGITAL-EQUIPO DEL CUSTODIO | M832: DOCUMENTO DE ARCHIVO-ELECTRÓNICO | N832: PRIMARIOS | O832: DOCUMENTOS TÉCNICOS | P832: PUBLICA(1) | Q832: BAJA(1) | R832: BAJA(1) | S832: =+(IF(P832="PUBLICA(1)",1,IF(P832="USO INTERNO(2)",2,IF(P832="RESTRINGIDO(3)",3,3))))+(IF(Q832="BAJA(1)",1,IF(Q832="MEDIA(2)",2,IF(Q832="ALTA(3)",3,3))))+(IF(R832="BAJA(1)",1,IF(R832="MEDIA(2)",2,IF(R832="ALTA(3)",3,3)))) | T832: =+IF(S832<6,"BAJA",IF(S832<8,"MEDIA","ALTA")) | U832: - | V832: 45681 | W832: N/A | X832: =+IFERROR(IF(VLOOKUP(Tabla2[[#This Row],[ID]],'EVALUACION DE RIESGO'!A:A,1,FALSE)=Tabla2[[#This Row],[ID]],"SI","NO"),"NO")
A833: 10-GES | B833: ESTRATÉGICO | C833: Gestión Estratégica | D833: GES | E833: Planificación Estratégica | F833: - | G833: Análisis de la situación actual | H833: Análisis financiero nacional, del segmento y de la Cooperativa | I833: Documento interno con datos externos con indicadores de la competencia | J833: GERENTE FINANCIERO | K833: JEFE DE PLANIFICACIÓN Y PROCESOS | L833: UBICACIÓN DIGITAL-EQUIPO DEL CUSTODIO | M833: DOCUMENTO DE ARCHIVO-ELECTRÓNICO | N833: PRIMARIOS | O833: DOCUMENTOS TÉCNICOS | P833: PUBLICA(1) | Q833: BAJA(1) | R833: BAJA(1) | S833: =+(IF(P833="PUBLICA(1)",1,IF(P833="USO INTERNO(2)",2,IF(P833="RESTRINGIDO(3)",3,3))))+(IF(Q833="BAJA(1)",1,IF(Q833="MEDIA(2)",2,IF(Q833="ALTA(3)",3,3))))+(IF(R833="BAJA(1)",1,IF(R833="MEDIA(2)",2,IF(R833="ALTA(3)",3,3)))) | T833: =+IF(S833<6,"BAJA",IF(S833<8,"MEDIA","ALTA")) | U833: - | V833: 45681 | W833: N/A | X833: =+IFERROR(IF(VLOOKUP(Tabla2[[#This Row],[ID]],'EVALUACION DE RIESGO'!A:A,1,FALSE)=Tabla2[[#This Row],[ID]],"SI","NO"),"NO")
A834: 11-GES | B834: ESTRATÉGICO | C834: Gestión Estratégica | D834: GES | E834: Planificación Estratégica | F834: - | G834: Análisis de la situación actual | H834: Resultados alcanzados en el Plan Estratégico que fenece | I834: Evaluación del plan estratégico | J834: JEFE DE PLANIFICACIÓN Y PROCESOS | K834: JEFE DE PLANIFICACIÓN Y PROCESOS | L834: UBICACIÓN DIGITAL-EQUIPO DEL CUSTODIO | M834: DOCUMENTO DE ARCHIVO-ELECTRÓNICO | N834: PRIMARIOS | O834: DOCUMENTOS TÉCNICOS | P834: PUBLICA(1) | Q834: BAJA(1) | R834: BAJA(1) | S834: =+(IF(P834="PUBLICA(1)",1,IF(P834="USO INTERNO(2)",2,IF(P834="RESTRINGIDO(3)",3,3))))+(IF(Q834="BAJA(1)",1,IF(Q834="MEDIA(2)",2,IF(Q834="ALTA(3)",3,3))))+(IF(R834="BAJA(1)",1,IF(R834="MEDIA(2)",2,IF(R834="ALTA(3)",3,3)))) | T834: =+IF(S834<6,"BAJA",IF(S834<8,"MEDIA","ALTA")) | U834: - | V834: 45681 | W834: N/A | X834: =+IFERROR(IF(VLOOKUP(Tabla2[[#This Row],[ID]],'EVALUACION DE RIESGO'!A:A,1,FALSE)=Tabla2[[#This Row],[ID]],"SI","NO"),"NO")
A835: 12-GES | B835: ESTRATÉGICO | C835: Gestión Estratégica | D835: GES | E835: Planificación Estratégica | F835: - | G835: Análisis de la situación actual | H835: Necesidades de los Stakeholders | I835: Matriz de necesidades de los grupos de interes | J835: GERENTE DE TALENTO HUMANO | K835: JEFE DE PLANIFICACIÓN Y PROCESOS | L835: UBICACIÓN DIGITAL-EQUIPO DEL CUSTODIO | M835: DOCUMENTO DE ARCHIVO-ELECTRÓNICO | N835: PRIMARIOS | O835: DOCUMENTOS TÉCNICOS | P835: PUBLICA(1) | Q835: BAJA(1) | R835: BAJA(1) | S835: =+(IF(P835="PUBLICA(1)",1,IF(P835="USO INTERNO(2)",2,IF(P835="RESTRINGIDO(3)",3,3))))+(IF(Q835="BAJA(1)",1,IF(Q835="MEDIA(2)",2,IF(Q835="ALTA(3)",3,3))))+(IF(R835="BAJA(1)",1,IF(R835="MEDIA(2)",2,IF(R835="ALTA(3)",3,3)))) | T835: =+IF(S835<6,"BAJA",IF(S835<8,"MEDIA","ALTA")) | U835: - | V835: 45681 | W835: N/A | X835: =+IFERROR(IF(VLOOKUP(Tabla2[[#This Row],[ID]],'EVALUACION DE RIESGO'!A:A,1,FALSE)=Tabla2[[#This Row],[ID]],"SI","NO"),"NO")
... A1406: 66-GSO | B1406: APOYO | C1406: Gestión de Seguridad Organizacional | D1406: GSO | E1406: Gestión de Seguridad de la Información | F1406: - | G1406: N/A | H1406: Oficial de Seguridad de la Información | I1406: N/A | J1406: Oficial de Seguridad de la Información | K1406: N/A | L1406: N/A | M1406: N/A | N1406: APOYO | O1406: RECURSO HUMANO | P1406: USO INTERNO(2) | Q1406: MEDIA(2) | R1406: MEDIA(2) | S1406: =+(IF(P1406="PUBLICA(1)",1,IF(P1406="USO INTERNO(2)",2,IF(P1406="RESTRINGIDO(3)",3,3))))+(IF(Q1406="BAJA(1)",1,IF(Q1406="MEDIA(2)",2,IF(Q1406="ALTA(3)",3,3))))+(IF(R1406="BAJA(1)",1,IF(R1406="MEDIA(2)",2,IF(R1406="ALTA(3)",3,3)))) | T1406: =+IF(S1406<6,"BAJA",IF(S1406<8,"MEDIA","ALTA")) | U1406: - | V1406: 45712 | W1406: N/A | X1406: =+IFERROR(IF(VLOOKUP(Tabla2[[#This Row],[ID]],'EVALUACION DE RIESGO'!A:A,1,FALSE)=Tabla2[[#This Row],[ID]],"SI","NO"),"NO")

Sheet INTERVALOS
A1: PROBABILIDAD
A2: Descripción | B2: Nivel | C2: Porcentaje de ocurrencia del evento | D2: Frecuencia
A3: Muy Baja | B3: 1 | C3: 0,00% al 4,64% | D3: Ocurre una vez al año
A4: Baja | B4: 2 | C4: 4,65% al 7,60% | D4: Ocurre una vez al mes
A5: Media | B5: 3 | C5: 7.61% al 28,26% | D5: Ocurre una vez a la semana
A6: Alta | B6: 4 | C6: 28,27% al 40,70% | D6: Ocurre una vez al día
A7: Muy Alta | B7: 5 | C7: 40,71% al 100% | D7: Ocurre varias veces al día.
A9: IMPACTO/DEGRADACIÓN
A10: Descripcion | B10: Nivel
A11: Insignificante | B11: 1
A12: Bajo | B12: 2
A13: Medio | B13: 3
A14: Alto | B14: 4
A15: Severo | B15: 5
A17: NIVEL DE RIESGO DE SEGURIDAD = IMPACTO * PROBABILIDAD
A18: PROBABILIDAD | B18: IMPACTO
B19: Insignificante | C19: Bajo | D19: Medio | E19: Alto | F19: Severo | H19: NIVEL DE RIESGO
A20: Muy Alta | B20: 5 | C20: 10 | D20: 15 | E20: 20 | F20: 25 | H20: Crítico | I20: 17-25
A21: Alta | B21: 4 | C21: 8 | D21: 12 | E21: 16 | F21: 20 | H21: Alto | I21: 10-16
A22: Media | B22: 3 | C22: 6 | D22: 9 | E22: 12 | F22: 15 | H22: Medio | I22: 5-9
A23: Baja | B23: 2 | C23: 4 | D23: 6 | E23: 8 | F23: 10 | H23: Bajo | I23: 1-4
A24: Muy Baja | B24: 1 | C24: 2 | D24: 3 | E24: 4 | F24: 5

Sheet EVALUACION DE RIESGO
A2: ACTIVO | B2: NOMBRE | C2: DESCRIPCION | D2: TIPO DE ACTIVO MAGGERIT | E2: EVENTO DE AMENAZA | F2: CID | G2: CONFIDENCIALIDAD | H2: INTEGRIDAD | I2: DISPONIBILIDAD | J2: PROBABILIDAD | K2: IMPACTO | L2: RIESGO INHERENTE | M2: DETERMINACION RIESGO ACUMULADO O INHERENTE | N2: CONTROLES EXISTENTES | O2: TIPO DE PROTECCION | P2: MADUREZ DEL CONTROL | Q2: VALOR DE EFICACIA | R2: VULNERABILIDADES | S2: PROBABILIDAD RESIDUAL | T2: IMPACTO RESIDUAL | U2: RIESGO RESIDUAL | V2: DETERMINACION RIESGO RESIDUAL | W2: APETITO DE RIESGO | X2: REQUIERE TRATAMIENTO NORMATIVA SEPS 002-2022 | Y2: PLAN DE ACCION | Z2: DESCIPCION PLAN DE ACCIÓN
A3: 16-GTI | B3: Respaldo de información | C3: Respaldo de Base de Datos (diario) | D3: [Media] Soportes de información | E3: [E.2] Errores del administrador | F3: =+VLOOKUP(E3,'CATALOGO AMENAZA'!$B$2:$D$46,3,FALSE) | G3: X | H3: X | I3: X | J3: 2 | K3: 4 | L3: =+J3*K3 | M3: =+IF(L3<5,"BAJO",IF(L3<10,"MEDIO",IF(L3<17,"ALTO","CRITICO"))) | N3: Procedimientos operativos documentados | O3: PREVENTIVO | P3: Control Implementado sin evidencia de efectividad (Inefectivo prueba) | Q3: 0.3 | R3: Dependencia del administrador (error humano) | S3: =+IF(O3="PREVENTIVO",J3*(1-Q3),IF(O3="ADMINISTRACION",J3*(1-Q3),IF(O3="ELIMINACION",J3*(1-Q3),J3))) | T3: =+IF(O3="DETECTIVO",K3*(1-Q3),IF(O3="RECUPERACION",K3*(1-Q3),K3)) | U3: =+S3*T3 | V3: =+IF(U3<5,"BAJO",IF(U3<10,"MEDIO",IF(U3<17,"ALTO","CRITICO"))) | W3: MITIGAR | X3: - | Y3: - | Z3: -
A4: 16-GTI | B4: Respaldo de información | C4: Respaldo de Base de Datos (diario) | D4: [Media] Soportes de información | E4: [E.18] Destrucción de información | F4: =+VLOOKUP(E4,'CATALOGO AMENAZA'!$B$2:$D$46,3,FALSE) | I4: X | J4: 2 | K4: 4 | L4: =+J4*K4 | M4: =+IF(L4<5,"BAJO",IF(L4<10,"MEDIO",IF(L4<17,"ALTO","CRITICO"))) | N4: Respaldo digital de información | O4: PREVENTIVO | P4: Control Implementado sin evidencia de efectividad (Inefectivo prueba) | Q4: 0.3 | R4: Almacenamiento manual en medio extraible | S4: =+IF(O4="PREVENTIVO",J4*(1-Q4),IF(O4="ADMINISTRACION",J4*(1-Q4),IF(O4="ELIMINACION",J4*(1-Q4),J4))) | T4: =+IF(O4="DETECTIVO",K4*(1-Q4),IF(O4="RECUPERACION",K4*(1-Q4),K4)) | U4: =+S4*T4 | V4: =+IF(U4<5,"BAJO",IF(U4<10,"MEDIO",IF(U4<17,"ALTO","CRITICO"))) | W4: MITIGAR | X4: - | Y4: - | Z4: -
A5: 16-GTI | B5: Respaldo de información | C5: Respaldo de Base de Datos (diario) | D5: [Media] Soportes de información | E5: [N.1] Fuego | F5: =+VLOOKUP(E5,'CATALOGO AMENAZA'!$B$2:$D$46,3,FALSE) | I5: X | J5: 1 | K5: 4 | L5: =+J5*K5 | M5: =+IF(L5<5,"BAJO",IF(L5<10,"MEDIO",IF(L5<17,"ALTO","CRITICO"))) | N5: Sistema contra incendios | O5: PREVENTIVO | P5: Control Implementado sin evidencia de efectividad (Inefectivo prueba) | Q5: 0.3 | R5: - | S5: =+IF(O5="PREVENTIVO",J5*(1-Q5),IF(O5="ADMINISTRACION",J5*(1-Q5),IF(O5="ELIMINACION",J5*(1-Q5),J5))) | T5: =+IF(O5="DETECTIVO",K5*(1-Q5),IF(O5="RECUPERACION",K5*(1-Q5),K5)) | U5: =+S5*T5 | V5: =+IF(U5<5,"BAJO",IF(U5<10,"MEDIO",IF(U5<17,"ALTO","CRITICO"))) | W5: ACEPTABLE | X5: - | Y5: - | Z5: -
A6: 16-GTI | B6: Respaldo de información | C6: Respaldo de Base de Datos (diario) | D6: [Media] Soportes de información | E6: [E.19] Fugas de información | F6: =+VLOOKUP(E6,'CATALOGO AMENAZA'!$B$2:$D$46,3,FALSE) | G6: X | J6: 2 | K6: 4 | L6: =+J6*K6 | M6: =+IF(L6<5,"BAJO",IF(L6<10,"MEDIO",IF(L6<17,"ALTO","CRITICO"))) | N6: Politicas de manejo de información | O6: PREVENTIVO | P6: Control Implementado sin evidencia de efectividad (Inefectivo prueba) | Q6: 0.3 | R6: Dispositivos no encriptados | S6: =+IF(O6="PREVENTIVO",J6*(1-Q6),IF(O6="ADMINISTRACION",J6*(1-Q6),IF(O6="ELIMINACION",J6*(1-Q6),J6))) | T6: =+IF(O6="DETECTIVO",K6*(1-Q6),IF(O6="RECUPERACION",K6*(1-Q6),K6)) | U6: =+S6*T6 | V6: =+IF(U6<5,"BAJO",IF(U6<10,"MEDIO",IF(U6<17,"ALTO","CRITICO"))) | W6: MITIGAR | X6: - | Y6: - | Z6: -
A7: 21-GTI | B7: Registro control de respaldos | C7: Matriz de registro de respaldos realizados por fechas, tipo de respaldo y responsable | D7: [D] Datos / Información / datos de configuración | E7: [E.2] Errores del administrador | F7: =+VLOOKUP(E7,'CATALOGO AMENAZA'!$B$2:$D$46,3,FALSE) | G7: X | H7: X | I7: X | J7: 1 | K7: 2 | L7: =+J7*K7 | M7: =+IF(L7<5,"BAJO",IF(L7<10,"MEDIO",IF(L7<17,"ALTO","CRITICO"))) | N7: Procedimientos operativos documentados | O7: PREVENTIVO | P7: Control Implementado sin evidencia de efectividad (Inefectivo prueba) | Q7: 0.3 | R7: Dependencia del administrador (error humano) | S7: =+IF(O7="PREVENTIVO",J7*(1-Q7),IF(O7="ADMINISTRACION",J7*(1-Q7),IF(O7="ELIMINACION",J7*(1-Q7),J7))) | T7: =+IF(O7="DETECTIVO",K7*(1-Q7),IF(O7="RECUPERACION",K7*(1-Q7),K7)) | U7: =+S7*T7 | V7: =+IF(U7<5,"BAJO",IF(U7<10,"MEDIO",IF(U7<17,"ALTO","CRITICO"))) | W7: ACEPTABLE | X7: - | Y7: - | Z7: -
A8: 63-GTI | B8: Home Banking | C8: Aplicación Banca Virtual | D8: [SW] Software - Aplicaciones informáticas | E8: [A.11] Acceso no autorizado | F8: =+VLOOKUP(E8,'CATALOGO AMENAZA'!$B$2:$D$46,3,FALSE) | G8: X | H8: X | J8: 4 | K8: 5 | L8: =+J8*K8 | M8: =+IF(L8<5,"BAJO",IF(L8<10,"MEDIO",IF(L8<17,"ALTO","CRITICO"))) | N8: Control de accesos | O8: PREVENTIVO | P8: Control Implementado sin evidencia de efectividad (Inefectivo prueba) | Q8: 0.3 | R8: Usuarios sin monitoreo | S8: =+IF(O8="PREVENTIVO",J8*(1-Q8),IF(O8="ADMINISTRACION",J8*(1-Q8),IF(O8="ELIMINACION",J8*(1-Q8),J8))) | T8: =+IF(O8="DETECTIVO",K8*(1-Q8),IF(O8="RECUPERACION",K8*(1-Q8),K8)) | U8: =+S8*T8 | V8: =+IF(U8<5,"BAJO",IF(U8<10,"MEDIO",IF(U8<17,"ALTO","CRITICO"))) | W8: MITIGAR | X8: REQUIERE TRATAMIENTO | Y8: PA-SI-001 | Z8: Identificar herramientas que permitan realizar un análisis de LOGS
A9: 63-GTI | B9: Home Banking | C9: Aplicación Banca Virtual | D9: [SW] Software - Aplicaciones informáticas | E9: [A.5] Suplantación de la identidad del usuario | F9: =+VLOOKUP(E9,'CATALOGO AMENAZA'!$B$2:$D$46,3,FALSE) | G9: X | H9: X | J9: 4 | K9: 5 | L9: =+J9*K9 | M9: =+IF(L9<5,"BAJO",IF(L9<10,"MEDIO",IF(L9<17,"ALTO","CRITICO"))) | N9: Doble autenticación | O9: ELIMINACION | P9: Control Implementado sin evidencia de efectividad (Inefectivo prueba) | Q9: 0.8 | R9: - | S9: =+IF(O9="PREVENTIVO",J9*(1-Q9),IF(O9="ADMINISTRACION",J9*(1-Q9),IF(O9="ELIMINACION",J9*(1-Q9),J9))) | T9: =+IF(O9="DETECTIVO",K9*(1-Q9),IF(O9="RECUPERACION",K9*(1-Q9),K9)) | U9: =+S9*T9 | V9: =+IF(U9<5,"BAJO",IF(U9<10,"MEDIO",IF(U9<17,"ALTO","CRITICO"))) | W9: ACEPTABLE | X9: - | Y9: - | Z9: -
A10: 63-GTI | B10: Home Banking | C10: Aplicación Banca Virtual | D10: [SW] Software - Aplicaciones informáticas | E10: [A.6] Abuso de privilegios de acceso | F10: =+VLOOKUP(E10,'CATALOGO AMENAZA'!$B$2:$D$46,3,FALSE) | G10: X | H10: X | I10: X | J10: 2 | K10: 4 | L10: =+J10*K10 | M10: =+IF(L10<5,"BAJO",IF(L10<10,"MEDIO",IF(L10<17,"ALTO","CRITICO"))) | N10: Registro de logs | O10: DETECTIVO | P10: Control Implementado sin evidencia de efectividad (Inefectivo prueba) | Q10: 0.3 | R10: Falta de revisión de perfiles de acceso | S10: =+IF(O10="PREVENTIVO",J10*(1-Q10),IF(O10="ADMINISTRACION",J10*(1-Q10),IF(O10="ELIMINACION",J10*(1-Q10),J10))) | T10: =+IF(O10="DETECTIVO",K10*(1-Q10),IF(O10="RECUPERACION",K10*(1-Q10),K10)) | U10: =+S10*T10 | V10: =+IF(U10<5,"BAJO",IF(U10<10,"MEDIO",IF(U10<17,"ALTO","CRITICO"))) | W10: MITIGAR | X10: - | Y10: - | Z10: -
A11: 63-GTI | B11: Home Banking | C11: Aplicación Banca Virtual | D11: [SW] Software - Aplicaciones informáticas | E11: [E.20] Vulnerabilidades de los programas (software) | F11: =+VLOOKUP(E11,'CATALOGO AMENAZA'!$B$2:$D$46,3,FALSE) | G11: X | H11: X | I11: X | J11: 4 | K11: 4 | L11: =+J11*K11 | M11: =+IF(L11<5,"BAJO",IF(L11<10,"MEDIO",IF(L11<17,"ALTO","CRITICO"))) | N11: Gestión de vulnerabilidades | O11: PREVENTIVO | P11: Control Implementado sin evidencia de efectividad (Inefectivo prueba) | Q11: 0.4 | R11: Recursos tecnológicos insuficientes para remediación | S11: =+IF(O11="PREVENTIVO",J11*(1-Q11),IF(O11="ADMINISTRACION",J11*(1-Q11),IF(O11="ELIMINACION",J11*(1-Q11),J11))) | T11: =+IF(O11="DETECTIVO",K11*(1-Q11),IF(O11="RECUPERACION",K11*(1-Q11),K11)) | U11: =+S11*T11 | V11: =+IF(U11<5,"BAJO",IF(U11<10,"MEDIO",IF(U11<17,"ALTO","CRITICO"))) | W11: MITIGAR | X11: - | Y11: - | Z11: -
A12: 63-GTI | B12: Home Banking | C12: Aplicación Banca Virtual | D12: [SW] Software - Aplicaciones informáticas | E12: [E.21] Errores de mantenimiento / actualización de programas (software) | F12: =+VLOOKUP(E12,'CATALOGO AMENAZA'!$B$2:$D$46,3,FALSE) | H12: X | I12: X | J12: 3 | K12: 4 | L12: =+J12*K12 | M12: =+IF(L12<5,"BAJO",IF(L12<10,"MEDIO",IF(L12<17,"ALTO","CRITICO"))) | N12: Gestión de vulnerabilidades | O12: PREVENTIVO | P12: Control Implementado sin evidencia de efectividad (Inefectivo prueba) | Q12: 0.4 | R12: Recursos tecnológicos insuficientes para remediación | S12: =+IF(O12="PREVENTIVO",J12*(1-Q12),IF(O12="ADMINISTRACION",J12*(1-Q12),IF(O12="ELIMINACION",J12*(1-Q12),J12))) | T12: =+IF(O12="DETECTIVO",K12*(1-Q12),IF(O12="RECUPERACION",K12*(1-Q12),K12)) | U12: =+S12*T12 | V12: =+IF(U12<5,"BAJO",IF(U12<10,"MEDIO",IF(U12<17,"ALTO","CRITICO"))) | W12: MITIGAR | X12: - | Y12: - | Z12: -
A13: 64-GTI | B13: Cooperativa Virtual | C13: Servidor que aloja la Banca Electronica 192.168.23.11 | D13: [HW] Equipamiento informático (hardware) | E13: [E.2] Errores del administrador | F13: =+VLOOKUP(E13,'CATALOGO AMENAZA'!$B$2:$D$46,3,FALSE) | G13: X | H13: X | I13: X | J13: 2 | K13: 4 | L13: =+J13*K13 | M13: =+IF(L13<5,"BAJO",IF(L13<10,"MEDIO",IF(L13<17,"ALTO","CRITICO"))) | N13: Control de cambios en los sistemas Verificación posterior (informe) | O13: ADMINISTRACION | P13: Control Implementado sin evidencia de efectividad (Inefectivo prueba) | Q13: 0.3 | R13: No existe procedimiento formal de gestión de cambios | S13: =+IF(O13="PREVENTIVO",J13*(1-Q13),IF(O13="ADMINISTRACION",J13*(1-Q13),IF(O13="ELIMINACION",J13*(1-Q13),J13))) | T13: =+IF(O13="DETECTIVO",K13*(1-Q13),IF(O13="RECUPERACION",K13*(1-Q13),K13)) | U13: =+S13*T13 | V13: =+IF(U13<5,"BAJO",IF(U13<10,"MEDIO",IF(U13<17,"ALTO","CRITICO"))) | W13: MITIGAR | X13: - | Y13: - | Z13: -
A14: 64-GTI | B14: Cooperativa Virtual | C14: Servidor que aloja la Banca Electronica 192.168.23.11 | D14: [HW] Equipamiento informático (hardware) | E14: [E.24] Caída del sistema por agotamiento de recursos | F14: =+VLOOKUP(E14,'CATALOGO AMENAZA'!$B$2:$D$46,3,FALSE) | I14: X | J14: 4 | K14: 4 | L14: =+J14*K14 | M14: =+IF(L14<5,"BAJO",IF(L14<10,"MEDIO",IF(L14<17,"ALTO","CRITICO"))) | N14: Monitoreo de Servidores presenta en el procedimiento operativo Administración de Servidores en el Manua de Gestión de las Operaciones de TI | O14: PREVENTIVO | P14: Control Implementado sin evidencia de efectividad (Inefectivo prueba) | Q14: 0.4 | R14: Falta de alertas automáticas | S14: =+IF(O14="PREVENTIVO",J14*(1-Q14),IF(O14="ADMINISTRACION",J14*(1-Q14),IF(O14="ELIMINACION",J14*(1-Q14),J14))) | T14: =+IF(O14="DETECTIVO",K14*(1-Q14),IF(O14="RECUPERACION",K14*(1-Q14),K14)) | U14: =+S14*T14 | V14: =+IF(U14<5,"BAJO",IF(U14<10,"MEDIO",IF(U14<17,"ALTO","CRITICO"))) | W14: MITIGAR | X14: - | Y14: - | Z14: -
A15: 64-GTI | B15: Cooperativa Virtual | C15: Servidor que aloja la Banca Electronica 192.168.23.11 | D15: [HW] Equipamiento informático (hardware) | E15: [A.11] Acceso no autorizado | F15: =+VLOOKUP(E15,'CATALOGO AMENAZA'!$B$2:$D$46,3,FALSE) | G15: X | H15: X | J15: 3 | K15: 4 | L15: =+J15*K15 | M15: =+IF(L15<5,"BAJO",IF(L15<10,"MEDIO",IF(L15<17,"ALTO","CRITICO"))) | N15: Control de accesos / VPN | O15: PREVENTIVO | P15: Control Implementado sin evidencia de efectividad (Inefectivo prueba) | Q15: 0.3 | R15: Contreaseñas de VPN no expiran | S15: =+IF(O15="PREVENTIVO",J15*(1-Q15),IF(O15="ADMINISTRACION",J15*(1-Q15),IF(O15="ELIMINACION",J15*(1-Q15),J15))) | T15: =+IF(O15="DETECTIVO",K15*(1-Q15),IF(O15="RECUPERACION",K15*(1-Q15),K15)) | U15: =+S15*T15 | V15: =+IF(U15<5,"BAJO",IF(U15<10,"MEDIO",IF(U15<17,"ALTO","CRITICO"))) | W15: MITIGAR | X15: - | Y15: - | Z15: -
A16: 64-GTI | B16: Cooperativa Virtual | C16: Servidor que aloja la Banca Electronica 192.168.23.11 | D16: [HW] Equipamiento informático (hardware) | E16: [A.23] Manipulación de los equipos | F16: =+VLOOKUP(E16,'CATALOGO AMENAZA'!$B$2:$D$46,3,FALSE) | G16: X | I16: X | J16: 3 | K16: 4 | L16: =+J16*K16 | M16: =+IF(L16<5,"BAJO",IF(L16<10,"MEDIO",IF(L16<17,"ALTO","CRITICO"))) | N16: Control de accesos | O16: PREVENTIVO | P16: Control Implementado sin evidencia de efectividad (Inefectivo prueba) | Q16: 0.3 | R16: Usuarios genéricos | S16: =+IF(O16="PREVENTIVO",J16*(1-Q16),IF(O16="ADMINISTRACION",J16*(1-Q16),IF(O16="ELIMINACION",J16*(1-Q16),J16))) | T16: =+IF(O16="DETECTIVO",K16*(1-Q16),IF(O16="RECUPERACION",K16*(1-Q16),K16)) | U16: =+S16*T16 | V16: =+IF(U16<5,"BAJO",IF(U16<10,"MEDIO",IF(U16<17,"ALTO","CRITICO"))) | W16: MITIGAR | X16: - | Y16: - | Z16: -
A17: 64-GTI | B17: Cooperativa Virtual | C17: Servidor que aloja la Banca Electronica 192.168.23.11 | D17: [HW] Equipamiento informático (hardware) | E17: [A.24] Denegación de servicio | F17: =+VLOOKUP(E17,'CATALOGO AMENAZA'!$B$2:$D$46,3,FALSE) | I17: X | J17: 4 | K17: 5 | L17: =+J17*K17 | M17: =+IF(L17<5,"BAJO",IF(L17<10,"MEDIO",IF(L17<17,"ALTO","CRITICO"))) | N17: Configuración segura de firewall | O17: PREVENTIVO | P17: Control Implementado sin evidencia de efectividad (Inefectivo prueba) | Q17: 0.3 | R17: Evidencia de validación de las configuraciones | S17: =+IF(O17="PREVENTIVO",J17*(1-Q17),IF(O17="ADMINISTRACION",J17*(1-Q17),IF(O17="ELIMINACION",J17*(1-Q17),J17))) | T17: =+IF(O17="DETECTIVO",K17*(1-Q17),IF(O17="RECUPERACION",K17*(1-Q17),K17)) | U17: =+S17*T17 | V17: =+IF(U17<5,"BAJO",IF(U17<10,"MEDIO",IF(U17<17,"ALTO","CRITICO"))) | W17: MITIGAR | X17: REQUIERE TRATAMIENTO | Y17: PA-SI-002 | Z17: Fortalecer mecanismos de protección contra ataques DoS/DDoS
A18: 64-GTI | B18: Cooperativa Virtual | C18: Servidor que aloja la Banca Electronica 192.168.23.11 | D18: [HW] Equipamiento informático (hardware) | E18: [E.23] Errores de mantenimiento / actualización de equipos (hardware) | F18: =+VLOOKUP(E18,'CATALOGO AMENAZA'!$B$2:$D$46,3,FALSE) | I18: X | J18: 3 | K18: 4 | L18: =+J18*K18 | M18: =+IF(L18<5,"BAJO",IF(L18<10,"MEDIO",IF(L18<17,"ALTO","CRITICO"))) | N18: Gestión de vulnerabilidades | O18: PREVENTIVO | P18: Control Implementado sin evidencia de efectividad (Inefectivo prueba) | Q18: 0.4 | R18: Recursos tecnológicos insuficientes para remediación | S18: =+IF(O18="PREVENTIVO",J18*(1-Q18),IF(O18="ADMINISTRACION",J18*(1-Q18),IF(O18="ELIMINACION",J18*(1-Q18),J18))) | T18: =+IF(O18="DETECTIVO",K18*(1-Q18),IF(O18="RECUPERACION",K18*(1-Q18),K18)) | U18: =+S18*T18 | V18: =+IF(U18<5,"BAJO",IF(U18<10,"MEDIO",IF(U18<17,"ALTO","CRITICO"))) | W18: MITIGAR | X18: - | Y18: - | Z18: -
A19: 65-GTI | B19: Sendmail | C19: Administracion Contenidos y Correo electrónico | D19: [S] Servicios | E19: [A.11] Acceso no autorizado | F19: =+VLOOKUP(E19,'CATALOGO AMENAZA'!$B$2:$D$46,3,FALSE) | G19: X | H19: X | J19: 2 | K19: 3 | L19: =+J19*K19 | M19: =+IF(L19<5,"BAJO",IF(L19<10,"MEDIO",IF(L19<17,"ALTO","CRITICO"))) | N19: Control de accesos | O19: PREVENTIVO | P19: Control Implementado sin evidencia de efectividad (Inefectivo prueba) | Q19: 0.3 | R19: Usuarios genéricos | S19: =+IF(O19="PREVENTIVO",J19*(1-Q19),IF(O19="ADMINISTRACION",J19*(1-Q19),IF(O19="ELIMINACION",J19*(1-Q19),J19))) | T19: =+IF(O19="DETECTIVO",K19*(1-Q19),IF(O19="RECUPERACION",K19*(1-Q19),K19)) | U19: =+S19*T19 | V19: =+IF(U19<5,"BAJO",IF(U19<10,"MEDIO",IF(U19<17,"ALTO","CRITICO"))) | W19: ACEPTABLE | X19: - | Y19: - | Z19: -
A20: 65-GTI | B20: Sendmail | C20: Administracion Contenidos y Correo electrónico | D20: [S] Servicios | E20: [A.5] Suplantación de la identidad del usuario | F20: =+VLOOKUP(E20,'CATALOGO AMENAZA'!$B$2:$D$46,3,FALSE) | G20: X | H20: X | J20: 2 | K20: 3 | L20: =+J20*K20 | M20: =+IF(L20<5,"BAJO",IF(L20<10,"MEDIO",IF(L20<17,"ALTO","CRITICO"))) | N20: Politicas de contraseñas robustas | O20: PREVENTIVO | P20: Control Implementado sin evidencia de efectividad (Inefectivo prueba) | Q20: 0.3 | R20: Usuarios genéricos / claves compartidas y almacenadas en navegadores | S20: =+IF(O20="PREVENTIVO",J20*(1-Q20),IF(O20="ADMINISTRACION",J20*(1-Q20),IF(O20="ELIMINACION",J20*(1-Q20),J20))) | T20: =+IF(O20="DETECTIVO",K20*(1-Q20),IF(O20="RECUPERACION",K20*(1-Q20),K20)) | U20: =+S20*T20 | V20: =+IF(U20<5,"BAJO",IF(U20<10,"MEDIO",IF(U20<17,"ALTO","CRITICO"))) | W20: ACEPTABLE | X20: - | Y20: - | Z20: -
A21: 65-GTI | B21: Sendmail | C21: Administracion Contenidos y Correo electrónico | D21: [S] Servicios | E21: [A.19] Divulgación de información | F21: =+VLOOKUP(E21,'CATALOGO AMENAZA'!$B$2:$D$46,3,FALSE) | G21: X | J21: 2 | K21: 3 | L21: =+J21*K21 | M21: =+IF(L21<5,"BAJO",IF(L21<10,"MEDIO",IF(L21<17,"ALTO","CRITICO"))) | N21: Validación de destinatarios | O21: PREVENTIVO | P21: Control Implementado sin evidencia de efectividad (Inefectivo prueba) | Q21: 0.3 | R21: Politicas sin restricción para jefaturas | S21: =+IF(O21="PREVENTIVO",J21*(1-Q21),IF(O21="ADMINISTRACION",J21*(1-Q21),IF(O21="ELIMINACION",J21*(1-Q21),J21))) | T21: =+IF(O21="DETECTIVO",K21*(1-Q21),IF(O21="RECUPERACION",K21*(1-Q21),K21)) | U21: =+S21*T21 | V21: =+IF(U21<5,"BAJO",IF(U21<10,"MEDIO",IF(U21<17,"ALTO","CRITICO"))) | W21: ACEPTABLE | X21: - | Y21: - | Z21: -
A22: 65-GTI | B22: Sendmail | C22: Administracion Contenidos y Correo electrónico | D22: [S] Servicios | E22: [A.24] Denegación de servicio | F22: =+VLOOKUP(E22,'CATALOGO AMENAZA'!$B$2:$D$46,3,FALSE) | I22: X | J22: 3 | K22: 4 | L22: =+J22*K22 | M22: =+IF(L22<5,"BAJO",IF(L22<10,"MEDIO",IF(L22<17,"ALTO","CRITICO"))) | N22: Software Antispam Fortimail | O22: PREVENTIVO | P22: Control Implementado sin evidencia de efectividad (Inefectivo prueba) | Q22: 0.3 | R22: No se realiza pruebas de carga | S22: =+IF(O22="PREVENTIVO",J22*(1-Q22),IF(O22="ADMINISTRACION",J22*(1-Q22),IF(O22="ELIMINACION",J22*(1-Q22),J22))) | T22: =+IF(O22="DETECTIVO",K22*(1-Q22),IF(O22="RECUPERACION",K22*(1-Q22),K22)) | U22: =+S22*T22 | V22: =+IF(U22<5,"BAJO",IF(U22<10,"MEDIO",IF(U22<17,"ALTO","CRITICO"))) | W22: MITIGAR | X22: - | Y22: - | Z22: -
A23: 65-GTI | B23: Sendmail | C23: Administracion Contenidos y Correo electrónico | D23: [S] Servicios | E23: [E.24] Caída del sistema por agotamiento de recursos | F23: =+VLOOKUP(E23,'CATALOGO AMENAZA'!$B$2:$D$46,3,FALSE) | I23: X | J23: 2 | K23: 3 | L23: =+J23*K23 | M23: =+IF(L23<5,"BAJO",IF(L23<10,"MEDIO",IF(L23<17,"ALTO","CRITICO"))) | N23: Monitoreo de Servidores presenta en el procedimiento operativo Administración de Servidores en el Manua de Gestión de las Operaciones de TI | O23: PREVENTIVO | P23: Control Implementado sin evidencia de efectividad (Inefectivo prueba) | Q23: 0.4 | R23: Falta de alertas automáticas | S23: =+IF(O23="PREVENTIVO",J23*(1-Q23),IF(O23="ADMINISTRACION",J23*(1-Q23),IF(O23="ELIMINACION",J23*(1-Q23),J23))) | T23: =+IF(O23="DETECTIVO",K23*(1-Q23),IF(O23="RECUPERACION",K23*(1-Q23),K23)) | U23: =+S23*T23 | V23: =+IF(U23<5,"BAJO",IF(U23<10,"MEDIO",IF(U23<17,"ALTO","CRITICO"))) | W23: ACEPTABLE | X23: - | Y23: - | Z23: -
A24: 66-GTI | B24: correo electronico | C24: Servidor web administracion correo electronico 192.168.23.2 | D24: [S] Servicios | E24: [A.11] Acceso no autorizado | F24: =+VLOOKUP(E24,'CATALOGO AMENAZA'!$B$2:$D$46,3,FALSE) | G24: X | H24: X | J24: 3 | K24: 3 | L24: =+J24*K24 | M24: =+IF(L24<5,"BAJO",IF(L24<10,"MEDIO",IF(L24<17,"ALTO","CRITICO"))) | N24: Control de accesos | O24: PREVENTIVO | P24: Control Implementado sin evidencia de efectividad (Inefectivo prueba) | Q24: 0.3 | R24: Usuarios genéricos | S24: =+IF(O24="PREVENTIVO",J24*(1-Q24),IF(O24="ADMINISTRACION",J24*(1-Q24),IF(O24="ELIMINACION",J24*(1-Q24),J24))) | T24: =+IF(O24="DETECTIVO",K24*(1-Q24),IF(O24="RECUPERACION",K24*(1-Q24),K24)) | U24: =+S24*T24 | V24: =+IF(U24<5,"BAJO",IF(U24<10,"MEDIO",IF(U24<17,"ALTO","CRITICO"))) | W24: MITIGAR | X24: - | Y24: - | Z24: -
A25: 66-GTI | B25: correo electronico | C25: Servidor web administracion correo electronico 192.168.23.2 | D25: [S] Servicios | E25: [A.5] Suplantación de la identidad del usuario | F25: =+VLOOKUP(E25,'CATALOGO AMENAZA'!$B$2:$D$46,3,FALSE) | G25: X | H25: X | J25: 3 | K25: 3 | L25: =+J25*K25 | M25: =+IF(L25<5,"BAJO",IF(L25<10,"MEDIO",IF(L25<17,"ALTO","CRITICO"))) | N25: Politicas de contraseñas robustas | O25: PREVENTIVO | P25: Control Implementado sin evidencia de efectividad (Inefectivo prueba) | Q25: 0.3 | R25: Usuarios genéricos / claves compartidas y almacenadas en navegadores | S25: =+IF(O25="PREVENTIVO",J25*(1-Q25),IF(O25="ADMINISTRACION",J25*(1-Q25),IF(O25="ELIMINACION",J25*(1-Q25),J25))) | T25: =+IF(O25="DETECTIVO",K25*(1-Q25),IF(O25="RECUPERACION",K25*(1-Q25),K25)) | U25: =+S25*T25 | V25: =+IF(U25<5,"BAJO",IF(U25<10,"MEDIO",IF(U25<17,"ALTO","CRITICO"))) | W25: MITIGAR | X25: - | Y25: - | Z25: -
A26: 66-GTI | B26: correo electronico | C26: Servidor web administracion correo electronico 192.168.23.2 | D26: [S] Servicios | E26: [A.19] Divulgación de información | F26: =+VLOOKUP(E26,'CATALOGO AMENAZA'!$B$2:$D$46,3,FALSE) | G26: X | J26: 3 | K26: 3 | L26: =+J26*K26 | M26: =+IF(L26<5,"BAJO",IF(L26<10,"MEDIO",IF(L26<17,"ALTO","CRITICO"))) | N26: Validación de destinatarios | O26: PREVENTIVO | P26: Control Implementado sin evidencia de efectividad (Inefectivo prueba) | Q26: 0.3 | R26: Politicas sin restricción para jefaturas | S26: =+IF(O26="PREVENTIVO",J26*(1-Q26),IF(O26="ADMINISTRACION",J26*(1-Q26),IF(O26="ELIMINACION",J26*(1-Q26),J26))) | T26: =+IF(O26="DETECTIVO",K26*(1-Q26),IF(O26="RECUPERACION",K26*(1-Q26),K26)) | U26: =+S26*T26 | V26: =+IF(U26<5,"BAJO",IF(U26<10,"MEDIO",IF(U26<17,"ALTO","CRITICO"))) | W26: MITIGAR | X26: - | Y26: - | Z26: -
A27: 66-GTI | B27: correo electronico | C27: Servidor web administracion correo electronico 192.168.23.2 | D27: [S] Servicios | E27: [A.24] Denegación de servicio | F27: =+VLOOKUP(E27,'CATALOGO AMENAZA'!$B$2:$D$46,3,FALSE) | I27: X | J27: 3 | K27: 3 | L27: =+J27*K27 | M27: =+IF(L27<5,"BAJO",IF(L27<10,"MEDIO",IF(L27<17,"ALTO","CRITICO"))) | N27: Configuración segura de firewall | O27: PREVENTIVO | P27: Control Implementado sin evidencia de efectividad (Inefectivo prueba) | Q27: 0.3 | R27: Evidencia de validación de las configuraciones | S27: =+IF(O27="PREVENTIVO",J27*(1-Q27),IF(O27="ADMINISTRACION",J27*(1-Q27),IF(O27="ELIMINACION",J27*(1-Q27),J27))) | T27: =+IF(O27="DETECTIVO",K27*(1-Q27),IF(O27="RECUPERACION",K27*(1-Q27),K27)) | U27: =+S27*T27 | V27: =+IF(U27<5,"BAJO",IF(U27<10,"MEDIO",IF(U27<17,"ALTO","CRITICO"))) | W27: MITIGAR | X27: - | Y27: - | Z27: -
A28: 66-GTI | B28: correo electronico | C28: Servidor web administracion correo electronico 192.168.23.2 | D28: [S] Servicios | E28: [E.24] Caída del sistema por agotamiento de recursos | F28: =+VLOOKUP(E28,'CATALOGO AMENAZA'!$B$2:$D$46,3,FALSE) | I28: X | J28: 2 | K28: 4 | L28: =+J28*K28 | M28: =+IF(L28<5,"BAJO",IF(L28<10,"MEDIO",IF(L28<17,"ALTO","CRITICO"))) | N28: Monitoreo de Servidores presenta en el procedimiento operativo Administración de Servidores en el Manua de Gestión de las Operaciones de TI | O28: PREVENTIVO | P28: Control Implementado sin evidencia de efectividad (Inefectivo prueba) | Q28: 0.4 | R28: Falta de alertas automáticas | S28: =+IF(O28="PREVENTIVO",J28*(1-Q28),IF(O28="ADMINISTRACION",J28*(1-Q28),IF(O28="ELIMINACION",J28*(1-Q28),J28))) | T28: =+IF(O28="DETECTIVO",K28*(1-Q28),IF(O28="RECUPERACION",K28*(1-Q28),K28)) | U28: =+S28*T28 | V28: =+IF(U28<5,"BAJO",IF(U28<10,"MEDIO",IF(U28<17,"ALTO","CRITICO"))) | W28: ACEPTABLE | X28: - | Y28: - | Z28: -
A29: 67-GTI | B29: Check Point | C29: Proteccion perimetral, Analiza todas las conexiones, eventos inusuales | D29: [HW] Equipamiento informático (hardware) | E29: [A.11] Acceso no autorizado | F29: =+VLOOKUP(E29,'CATALOGO AMENAZA'!$B$2:$D$46,3,FALSE) | G29: X | H29: X | J29: 2 | K29: 4 | L29: =+J29*K29 | M29: =+IF(L29<5,"BAJO",IF(L29<10,"MEDIO",IF(L29<17,"ALTO","CRITICO"))) | N29: Control de accesos / VPN | O29: PREVENTIVO | P29: Control Implementado sin evidencia de efectividad (Inefectivo prueba) | Q29: 0.3 | R29: Contreaseñas de VPN no expiran | S29: =+IF(O29="PREVENTIVO",J29*(1-Q29),IF(O29="ADMINISTRACION",J29*(1-Q29),IF(O29="ELIMINACION",J29*(1-Q29),J29))) | T29: =+IF(O29="DETECTIVO",K29*(1-Q29),IF(O29="RECUPERACION",K29*(1-Q29),K29)) | U29: =+S29*T29 | V29: =+IF(U29<5,"BAJO",IF(U29<10,"MEDIO",IF(U29<17,"ALTO","CRITICO"))) | W29: MITIGAR | X29: - | Y29: - | Z29: -
A30: 67-GTI | B30: Check Point | C30: Proteccion perimetral, Analiza todas las conexiones, eventos inusuales | D30: [HW] Equipamiento informático (hardware) | E30: [A.23] Manipulación de los equipos | F30: =+VLOOKUP(E30,'CATALOGO AMENAZA'!$B$2:$D$46,3,FALSE) | G30: X | I30: X | J30: 2 | K30: 3 | L30: =+J30*K30 | M30: =+IF(L30<5,"BAJO",IF(L30<10,"MEDIO",IF(L30<17,"ALTO","CRITICO"))) | N30: Control de accesos | O30: PREVENTIVO | P30: Control Implementado sin evidencia de efectividad (Inefectivo prueba) | Q30: 0.3 | R30: Usuarios genéricos | S30: =+IF(O30="PREVENTIVO",J30*(1-Q30),IF(O30="ADMINISTRACION",J30*(1-Q30),IF(O30="ELIMINACION",J30*(1-Q30),J30))) | T30: =+IF(O30="DETECTIVO",K30*(1-Q30),IF(O30="RECUPERACION",K30*(1-Q30),K30)) | U30: =+S30*T30 | V30: =+IF(U30<5,"BAJO",IF(U30<10,"MEDIO",IF(U30<17,"ALTO","CRITICO"))) | W30: ACEPTABLE | X30: - | Y30: - | Z30: -
A31: 67-GTI | B31: Check Point | C31: Proteccion perimetral, Analiza todas las conexiones, eventos inusuales | D31: [HW] Equipamiento informático (hardware) | E31: [A.24] Denegación de servicio | F31: =+VLOOKUP(E31,'CATALOGO AMENAZA'!$B$2:$D$46,3,FALSE) | I31: X | J31: 3 | K31: 4 | L31: =+J31*K31 | M31: =+IF(L31<5,"BAJO",IF(L31<10,"MEDIO",IF(L31<17,"ALTO","CRITICO"))) | N31: Configuración segura de firewall | O31: PREVENTIVO | P31: Control Implementado sin evidencia de efectividad (Inefectivo prueba) | Q31: 0.3 | R31: Evidencia de validación de las configuraciones | S31: =+IF(O31="PREVENTIVO",J31*(1-Q31),IF(O31="ADMINISTRACION",J31*(1-Q31),IF(O31="ELIMINACION",J31*(1-Q31),J31))) | T31: =+IF(O31="DETECTIVO",K31*(1-Q31),IF(O31="RECUPERACION",K31*(1-Q31),K31)) | U31: =+S31*T31 | V31: =+IF(U31<5,"BAJO",IF(U31<10,"MEDIO",IF(U31<17,"ALTO","CRITICO"))) | W31: MITIGAR | X31: - | Y31: - | Z31: -
A32: 67-GTI | B32: Check Point | C32: Proteccion perimetral, Analiza todas las conexiones, eventos inusuales | D32: [HW] Equipamiento informático (hardware) | E32: [E.2] Errores del administrador | F32: =+VLOOKUP(E32,'CATALOGO AMENAZA'!$B$2:$D$46,3,FALSE) | G32: X | H32: X | I32: X | J32: 2 | K32: 4 | L32: =+J32*K32 | M32: =+IF(L32<5,"BAJO",IF(L32<10,"MEDIO",IF(L32<17,"ALTO","CRITICO"))) | N32: Control de cambios en los sistemas Verificación posterior (informe) | O32: ADMINISTRACION | P32: Control Implementado sin evidencia de efectividad (Inefectivo prueba) | Q32: 0.3 | R32: No existe procedimiento formal de gestión de cambios | S32: =+IF(O32="PREVENTIVO",J32*(1-Q32),IF(O32="ADMINISTRACION",J32*(1-Q32),IF(O32="ELIMINACION",J32*(1-Q32),J32))) | T32: =+IF(O32="DETECTIVO",K32*(1-Q32),IF(O32="RECUPERACION",K32*(1-Q32),K32)) | U32: =+S32*T32 | V32: =+IF(U32<5,"BAJO",IF(U32<10,"MEDIO",IF(U32<17,"ALTO","CRITICO"))) | W32: MITIGAR | X32: - | Y32: - | Z32: -
A33: 67-GTI | B33: Check Point | C33: Proteccion perimetral, Analiza todas las conexiones, eventos inusuales | D33: [HW] Equipamiento informático (hardware) | E33: [A.6] Abuso de privilegios de acceso | F33: =+VLOOKUP(E33,'CATALOGO AMENAZA'!$B$2:$D$46,3,FALSE) | G33: X | H33: X | I33: X | J33: 2 | K33: 3 | L33: =+J33*K33 | M33: =+IF(L33<5,"BAJO",IF(L33<10,"MEDIO",IF(L33<17,"ALTO","CRITICO"))) | N33: Registro de logs (FortiAnalyzer) | O33: DETECTIVO | P33: Control Implementado sin evidencia de efectividad (Inefectivo prueba) | Q33: 0.3 | R33: Falta de revisión de perfiles de acceso | S33: =+IF(O33="PREVENTIVO",J33*(1-Q33),IF(O33="ADMINISTRACION",J33*(1-Q33),IF(O33="ELIMINACION",J33*(1-Q33),J33))) | T33: =+IF(O33="DETECTIVO",K33*(1-Q33),IF(O33="RECUPERACION",K33*(1-Q33),K33)) | U33: =+S33*T33 | V33: =+IF(U33<5,"BAJO",IF(U33<10,"MEDIO",IF(U33<17,"ALTO","CRITICO"))) | W33: ACEPTABLE | X33: - | Y33: - | Z33: -
A34: 68-GTI | B34: FortiAnalyzer | C34: Analizador de logs | D34: [SW] Software - Aplicaciones informáticas | E34: [A.11] Acceso no autorizado | F34: =+VLOOKUP(E34,'CATALOGO AMENAZA'!$B$2:$D$46,3,FALSE) | G34: X | H34: X | J34: 2 | K34: 2 | L34: =+J34*K34 | M34: =+IF(L34<5,"BAJO",IF(L34<10,"MEDIO",IF(L34<17,"ALTO","CRITICO"))) | N34: Control de accesos | O34: PREVENTIVO | P34: Control Implementado sin evidencia de efectividad (Inefectivo prueba) | Q34: 0.3 | R34: Usuarios genéricos | S34: =+IF(O34="PREVENTIVO",J34*(1-Q34),IF(O34="ADMINISTRACION",J34*(1-Q34),IF(O34="ELIMINACION",J34*(1-Q34),J34))) | T34: =+IF(O34="DETECTIVO",K34*(1-Q34),IF(O34="RECUPERACION",K34*(1-Q34),K34)) | U34: =+S34*T34 | V34: =+IF(U34<5,"BAJO",IF(U34<10,"MEDIO",IF(U34<17,"ALTO","CRITICO"))) | W34: ACEPTABLE | X34: - | Y34: - | Z34: -
A35: 68-GTI | B35: FortiAnalyzer | C35: Analizador de logs | D35: [SW] Software - Aplicaciones informáticas | E35: [A.23] Manipulación de los equipos | F35: =+VLOOKUP(E35,'CATALOGO AMENAZA'!$B$2:$D$46,3,FALSE) | G35: X | I35: X | J35: 2 | K35: 2 | L35: =+J35*K35 | M35: =+IF(L35<5,"BAJO",IF(L35<10,"MEDIO",IF(L35<17,"ALTO","CRITICO"))) | N35: Control de accesos | O35: PREVENTIVO | P35: Control Implementado sin evidencia de efectividad (Inefectivo prueba) | Q35: 0.3 | R35: Usuarios genéricos | S35: =+IF(O35="PREVENTIVO",J35*(1-Q35),IF(O35="ADMINISTRACION",J35*(1-Q35),IF(O35="ELIMINACION",J35*(1-Q35),J35))) | T35: =+IF(O35="DETECTIVO",K35*(1-Q35),IF(O35="RECUPERACION",K35*(1-Q35),K35)) | U35: =+S35*T35 | V35: =+IF(U35<5,"BAJO",IF(U35<10,"MEDIO",IF(U35<17,"ALTO","CRITICO"))) | W35: ACEPTABLE | X35: - | Y35: - | Z35: -
A36: 68-GTI | B36: FortiAnalyzer | C36: Analizador de logs | D36: [SW] Software - Aplicaciones informáticas | E36: [A.6] Abuso de privilegios de acceso | F36: =+VLOOKUP(E36,'CATALOGO AMENAZA'!$B$2:$D$46,3,FALSE) | G36: X | H36: X | I36: X | J36: 2 | K36: 2 | L36: =+J36*K36 | M36: =+IF(L36<5,"BAJO",IF(L36<10,"MEDIO",IF(L36<17,"ALTO","CRITICO"))) | N36: Registro de logs | O36: DETECTIVO | P36: Control Implementado sin evidencia de efectividad (Inefectivo prueba) | Q36: 0.3 | R36: Falta de revisión de perfiles de acceso | S36: =+IF(O36="PREVENTIVO",J36*(1-Q36),IF(O36="ADMINISTRACION",J36*(1-Q36),IF(O36="ELIMINACION",J36*(1-Q36),J36))) | T36: =+IF(O36="DETECTIVO",K36*(1-Q36),IF(O36="RECUPERACION",K36*(1-Q36),K36)) | U36: =+S36*T36 | V36: =+IF(U36<5,"BAJO",IF(U36<10,"MEDIO",IF(U36<17,"ALTO","CRITICO"))) | W36: ACEPTABLE | X36: - | Y36: - | Z36: -
A37: 68-GTI | B37: FortiAnalyzer | C37: Analizador de logs | D37: [SW] Software - Aplicaciones informáticas | E37: [A.24] Denegación de servicio | F37: =+VLOOKUP(E37,'CATALOGO AMENAZA'!$B$2:$D$46,3,FALSE) | I37: X | J37: 2 | K37: 2 | L37: =+J37*K37 | M37: =+IF(L37<5,"BAJO",IF(L37<10,"MEDIO",IF(L37<17,"ALTO","CRITICO"))) | N37: Configuración segura de firewall | O37: PREVENTIVO | P37: Control Implementado sin evidencia de efectividad (Inefectivo prueba) | Q37: 0.3 | R37: Evidencia de validación de las configuraciones | S37: =+IF(O37="PREVENTIVO",J37*(1-Q37),IF(O37="ADMINISTRACION",J37*(1-Q37),IF(O37="ELIMINACION",J37*(1-Q37),J37))) | T37: =+IF(O37="DETECTIVO",K37*(1-Q37),IF(O37="RECUPERACION",K37*(1-Q37),K37)) | U37: =+S37*T37 | V37: =+IF(U37<5,"BAJO",IF(U37<10,"MEDIO",IF(U37<17,"ALTO","CRITICO"))) | W37: ACEPTABLE | X37: - | Y37: - | Z37: -
A38: 68-GTI | B38: FortiAnalyzer | C38: Analizador de logs | D38: [SW] Software - Aplicaciones informáticas | E38: [E.24] Caída del sistema por agotamiento de recursos | F38: =+VLOOKUP(E38,'CATALOGO AMENAZA'!$B$2:$D$46,3,FALSE) | I38: X | J38: 2 | K38: 2 | L38: =+J38*K38 | M38: =+IF(L38<5,"BAJO",IF(L38<10,"MEDIO",IF(L38<17,"ALTO","CRITICO"))) | N38: Monitoreo de Servidores presenta en el procedimiento operativo Administración de Servidores en el Manua de Gestión de las Operaciones de TI | O38: PREVENTIVO | P38: Control Implementado sin evidencia de efectividad (Inefectivo prueba) | Q38: 0.4 | R38: Falta de alertas automáticas | S38: =+IF(O38="PREVENTIVO",J38*(1-Q38),IF(O38="ADMINISTRACION",J38*(1-Q38),IF(O38="ELIMINACION",J38*(1-Q38),J38))) | T38: =+IF(O38="DETECTIVO",K38*(1-Q38),IF(O38="RECUPERACION",K38*(1-Q38),K38)) | U38: =+S38*T38 | V38: =+IF(U38<5,"BAJO",IF(U38<10,"MEDIO",IF(U38<17,"ALTO","CRITICO"))) | W38: ACEPTABLE | X38: - | Y38: - | Z38: -
A39: 68-GTI | B39: FortiAnalyzer | C39: Analizador de logs | D39: [SW] Software - Aplicaciones informáticas | E39: [E.2] Errores del administrador | F39: =+VLOOKUP(E39,'CATALOGO AMENAZA'!$B$2:$D$46,3,FALSE) | G39: X | H39: X | I39: X | J39: 2 | K39: 2 | L39: =+J39*K39 | M39: =+IF(L39<5,"BAJO",IF(L39<10,"MEDIO",IF(L39<17,"ALTO","CRITICO"))) | N39: Control de cambios en los sistemas Verificación posterior (informe) | O39: ADMINISTRACION | P39: Control Implementado sin evidencia de efectividad (Inefectivo prueba) | Q39: 0.3 | R39: No existe procedimiento formal de gestión de cambios | S39: =+IF(O39="PREVENTIVO",J39*(1-Q39),IF(O39="ADMINISTRACION",J39*(1-Q39),IF(O39="ELIMINACION",J39*(1-Q39),J39))) | T39: =+IF(O39="DETECTIVO",K39*(1-Q39),IF(O39="RECUPERACION",K39*(1-Q39),K39)) | U39: =+S39*T39 | V39: =+IF(U39<5,"BAJO",IF(U39<10,"MEDIO",IF(U39<17,"ALTO","CRITICO"))) | W39: ACEPTABLE | X39: - | Y39: - | Z39: -
A40: 69-GTI | B40: UTM Fortinet | C40: Revision y categorizacion urls y sitios peligrosos | D40: [SW] Software - Aplicaciones informáticas | E40: [A.11] Acceso no autorizado | F40: =+VLOOKUP(E40,'CATALOGO AMENAZA'!$B$2:$D$46,3,FALSE) | G40: X | H40: X | J40: 2 | K40: 4 | L40: =+J40*K40 | M40: =+IF(L40<5,"BAJO",IF(L40<10,"MEDIO",IF(L40<17,"ALTO","CRITICO"))) | N40: Control de accesos | O40: PREVENTIVO | P40: Control Implementado sin evidencia de efectividad (Inefectivo prueba) | Q40: 0.3 | R40: Usuarios genéricos | S40: =+IF(O40="PREVENTIVO",J40*(1-Q40),IF(O40="ADMINISTRACION",J40*(1-Q40),IF(O40="ELIMINACION",J40*(1-Q40),J40))) | T40: =+IF(O40="DETECTIVO",K40*(1-Q40),IF(O40="RECUPERACION",K40*(1-Q40),K40)) | U40: =+S40*T40 | V40: =+IF(U40<5,"BAJO",IF(U40<10,"MEDIO",IF(U40<17,"ALTO","CRITICO"))) | W40: MITIGAR | X40: - | Y40: - | Z40: -
A41: 69-GTI | B41: UTM Fortinet | C41: Revision y categorizacion urls y sitios peligrosos | D41: [SW] Software - Aplicaciones informáticas | E41: [A.23] Manipulación de los equipos | F41: =+VLOOKUP(E41,'CATALOGO AMENAZA'!$B$2:$D$46,3,FALSE) | G41: X | I41: X | J41: 2 | K41: 2 | L41: =+J41*K41 | M41: =+IF(L41<5,"BAJO",IF(L41<10,"MEDIO",IF(L41<17,"ALTO","CRITICO"))) | N41: Control de accesos | O41: PREVENTIVO | P41: Control Implementado sin evidencia de efectividad (Inefectivo prueba) | Q41: 0.3 | R41: Usuarios genéricos | S41: =+IF(O41="PREVENTIVO",J41*(1-Q41),IF(O41="ADMINISTRACION",J41*(1-Q41),IF(O41="ELIMINACION",J41*(1-Q41),J41))) | T41: =+IF(O41="DETECTIVO",K41*(1-Q41),IF(O41="RECUPERACION",K41*(1-Q41),K41)) | U41: =+S41*T41 | V41: =+IF(U41<5,"BAJO",IF(U41<10,"MEDIO",IF(U41<17,"ALTO","CRITICO"))) | W41: ACEPTABLE | X41: - | Y41: - | Z41: -
A42: 69-GTI | B42: UTM Fortinet | C42: Revision y categorizacion urls y sitios peligrosos | D42: [SW] Software - Aplicaciones informáticas | E42: [A.6] Abuso de privilegios de acceso | F42: =+VLOOKUP(E42,'CATALOGO AMENAZA'!$B$2:$D$46,3,FALSE) | G42: X | H42: X | I42: X | J42: 2 | K42: 2 | L42: =+J42*K42 | M42: =+IF(L42<5,"BAJO",IF(L42<10,"MEDIO",IF(L42<17,"ALTO","CRITICO"))) | N42: Registro de logs (FortiAnalyzer) | O42: DETECTIVO | P42: Control Implementado sin evidencia de efectividad (Inefectivo prueba) | Q42: 0.3 | R42: Falta de revisión de perfiles de acceso | S42: =+IF(O42="PREVENTIVO",J42*(1-Q42),IF(O42="ADMINISTRACION",J42*(1-Q42),IF(O42="ELIMINACION",J42*(1-Q42),J42))) | T42: =+IF(O42="DETECTIVO",K42*(1-Q42),IF(O42="RECUPERACION",K42*(1-Q42),K42)) | U42: =+S42*T42 | V42: =+IF(U42<5,"BAJO",IF(U42<10,"MEDIO",IF(U42<17,"ALTO","CRITICO"))) | W42: ACEPTABLE | X42: - | Y42: - | Z42: -
A43: 69-GTI | B43: UTM Fortinet | C43: Revision y categorizacion urls y sitios peligrosos | D43: [SW] Software - Aplicaciones informáticas | E43: [A.24] Denegación de servicio | F43: =+VLOOKUP(E43,'CATALOGO AMENAZA'!$B$2:$D$46,3,FALSE) | I43: X | J43: 3 | K43: 2 | L43: =+J43*K43 | M43: =+IF(L43<5,"BAJO",IF(L43<10,"MEDIO",IF(L43<17,"ALTO","CRITICO"))) | N43: Configuración segura de firewall | O43: PREVENTIVO | P43: Control Implementado sin evidencia de efectividad (Inefectivo prueba) | Q43: 0.3 | R43: Evidencia de validación de las configuraciones | S43: =+IF(O43="PREVENTIVO",J43*(1-Q43),IF(O43="ADMINISTRACION",J43*(1-Q43),IF(O43="ELIMINACION",J43*(1-Q43),J43))) | T43: =+IF(O43="DETECTIVO",K43*(1-Q43),IF(O43="RECUPERACION",K43*(1-Q43),K43)) | U43: =+S43*T43 | V43: =+IF(U43<5,"BAJO",IF(U43<10,"MEDIO",IF(U43<17,"ALTO","CRITICO"))) | W43: ACEPTABLE | X43: - | Y43: - | Z43: -
A44: 69-GTI | B44: UTM Fortinet | C44: Revision y categorizacion urls y sitios peligrosos | D44: [SW] Software - Aplicaciones informáticas | E44: [E.2] Errores del administrador | F44: =+VLOOKUP(E44,'CATALOGO AMENAZA'!$B$2:$D$46,3,FALSE) | G44: X | H44: X | I44: X | J44: 2 | K44: 3 | L44: =+J44*K44 | M44: =+IF(L44<5,"BAJO",IF(L44<10,"MEDIO",IF(L44<17,"ALTO","CRITICO"))) | N44: Control de cambios en los sistemas Verificación posterior (informe) | O44: ADMINISTRACION | P44: Control Implementado sin evidencia de efectividad (Inefectivo prueba) | Q44: 0.3 | R44: No existe procedimiento formal de gestión de cambios | S44: =+IF(O44="PREVENTIVO",J44*(1-Q44),IF(O44="ADMINISTRACION",J44*(1-Q44),IF(O44="ELIMINACION",J44*(1-Q44),J44))) | T44: =+IF(O44="DETECTIVO",K44*(1-Q44),IF(O44="RECUPERACION",K44*(1-Q44),K44)) | U44: =+S44*T44 | V44: =+IF(U44<5,"BAJO",IF(U44<10,"MEDIO",IF(U44<17,"ALTO","CRITICO"))) | W44: ACEPTABLE | X44: - | Y44: - | Z44: -
A45: 69-GTI | B45: UTM Fortinet | C45: Revision y categorizacion urls y sitios peligrosos | D45: [SW] Software - Aplicaciones informáticas | E45: [E.24] Caída del sistema por agotamiento de recursos | F45: =+VLOOKUP(E45,'CATALOGO AMENAZA'!$B$2:$D$46,3,FALSE) | I45: X | J45: 3 | K45: 3 | L45: =+J45*K45 | M45: =+IF(L45<5,"BAJO",IF(L45<10,"MEDIO",IF(L45<17,"ALTO","CRITICO"))) | N45: Monitoreo de Servidores presenta en el procedimiento operativo Administración de Servidores en el Manua de Gestión de las Operaciones de TI | O45: PREVENTIVO | P45: Control Implementado sin evidencia de efectividad (Inefectivo prueba) | Q45: 0.4 | R45: Falta de alertas automáticas | S45: =+IF(O45="PREVENTIVO",J45*(1-Q45),IF(O45="ADMINISTRACION",J45*(1-Q45),IF(O45="ELIMINACION",J45*(1-Q45),J45))) | T45: =+IF(O45="DETECTIVO",K45*(1-Q45),IF(O45="RECUPERACION",K45*(1-Q45),K45)) | U45: =+S45*T45 | V45: =+IF(U45<5,"BAJO",IF(U45<10,"MEDIO",IF(U45<17,"ALTO","CRITICO"))) | W45: MITIGAR | X45: - | Y45: - | Z45: -
A46: 70-GTI | B46: Eset Endpoint Security | C46: Herramienta de control de software malicioso | D46: [SW] Software - Aplicaciones informáticas | E46: [A.11] Acceso no autorizado | F46: =+VLOOKUP(E46,'CATALOGO AMENAZA'!$B$2:$D$46,3,FALSE) | G46: X | H46: X | J46: 1 | K46: 4 | L46: =+J46*K46 | M46: =+IF(L46<5,"BAJO",IF(L46<10,"MEDIO",IF(L46<17,"ALTO","CRITICO"))) | N46: Control de accesos | O46: PREVENTIVO | P46: Control Implementado sin evidencia de efectividad (Inefectivo prueba) | Q46: 0.3 | R46: Usuarios genéricos | S46: =+IF(O46="PREVENTIVO",J46*(1-Q46),IF(O46="ADMINISTRACION",J46*(1-Q46),IF(O46="ELIMINACION",J46*(1-Q46),J46))) | T46: =+IF(O46="DETECTIVO",K46*(1-Q46),IF(O46="RECUPERACION",K46*(1-Q46),K46)) | U46: =+S46*T46 | V46: =+IF(U46<5,"BAJO",IF(U46<10,"MEDIO",IF(U46<17,"ALTO","CRITICO"))) | W46: ACEPTABLE | X46: - | Y46: - | Z46: -
A47: 70-GTI | B47: Eset Endpoint Security | C47: Herramienta de control de software malicioso | D47: [SW] Software - Aplicaciones informáticas | E47: [A.23] Manipulación de los equipos | F47: =+VLOOKUP(E47,'CATALOGO AMENAZA'!$B$2:$D$46,3,FALSE) | G47: X | I47: X | J47: 3 | K47: 3 | L47: =+J47*K47 | M47: =+IF(L47<5,"BAJO",IF(L47<10,"MEDIO",IF(L47<17,"ALTO","CRITICO"))) | N47: Control de accesos | O47: PREVENTIVO | P47: Control Implementado sin evidencia de efectividad (Inefectivo prueba) | Q47: 0.3 | R47: Usuarios genéricos | S47: =+IF(O47="PREVENTIVO",J47*(1-Q47),IF(O47="ADMINISTRACION",J47*(1-Q47),IF(O47="ELIMINACION",J47*(1-Q47),J47))) | T47: =+IF(O47="DETECTIVO",K47*(1-Q47),IF(O47="RECUPERACION",K47*(1-Q47),K47)) | U47: =+S47*T47 | V47: =+IF(U47<5,"BAJO",IF(U47<10,"MEDIO",IF(U47<17,"ALTO","CRITICO"))) | W47: MITIGAR | X47: - | Y47: - | Z47: -
A48: 70-GTI | B48: Eset Endpoint Security | C48: Herramienta de control de software malicioso | D48: [SW] Software - Aplicaciones informáticas | E48: [A.6] Abuso de privilegios de acceso | F48: =+VLOOKUP(E48,'CATALOGO AMENAZA'!$B$2:$D$46,3,FALSE) | G48: X | H48: X | I48: X | J48: 2 | K48: 4 | L48: =+J48*K48 | M48: =+IF(L48<5,"BAJO",IF(L48<10,"MEDIO",IF(L48<17,"ALTO","CRITICO"))) | N48: Registro de logs (FortiAnalyzer) | O48: DETECTIVO | P48: Control Implementado sin evidencia de efectividad (Inefectivo prueba) | Q48: 0.3 | R48: Falta de revisión de perfiles de acceso | S48: =+IF(O48="PREVENTIVO",J48*(1-Q48),IF(O48="ADMINISTRACION",J48*(1-Q48),IF(O48="ELIMINACION",J48*(1-Q48),J48))) | T48: =+IF(O48="DETECTIVO",K48*(1-Q48),IF(O48="RECUPERACION",K48*(1-Q48),K48)) | U48: =+S48*T48 | V48: =+IF(U48<5,"BAJO",IF(U48<10,"MEDIO",IF(U48<17,"ALTO","CRITICO"))) | W48: MITIGAR | X48: - | Y48: - | Z48: -
A49: 70-GTI | B49: Eset Endpoint Security | C49: Herramienta de control de software malicioso | D49: [SW] Software - Aplicaciones informáticas | E49: [A.24] Denegación de servicio | F49: =+VLOOKUP(E49,'CATALOGO AMENAZA'!$B$2:$D$46,3,FALSE) | I49: X | J49: 3 | K49: 4 | L49: =+J49*K49 | M49: =+IF(L49<5,"BAJO",IF(L49<10,"MEDIO",IF(L49<17,"ALTO","CRITICO"))) | N49: Configuración segura de firewall | O49: PREVENTIVO | P49: Control Implementado sin evidencia de efectividad (Inefectivo prueba) | Q49: 0.3 | R49: Evidencia de validación de las configuraciones | S49: =+IF(O49="PREVENTIVO",J49*(1-Q49),IF(O49="ADMINISTRACION",J49*(1-Q49),IF(O49="ELIMINACION",J49*(1-Q49),J49))) | T49: =+IF(O49="DETECTIVO",K49*(1-Q49),IF(O49="RECUPERACION",K49*(1-Q49),K49)) | U49: =+S49*T49 | V49: =+IF(U49<5,"BAJO",IF(U49<10,"MEDIO",IF(U49<17,"ALTO","CRITICO"))) | W49: MITIGAR | X49: - | Y49: - | Z49: -
A50: 70-GTI | B50: Eset Endpoint Security | C50: Herramienta de control de software malicioso | D50: [SW] Software - Aplicaciones informáticas | E50: [E.2] Errores del administrador | F50: =+VLOOKUP(E50,'CATALOGO AMENAZA'!$B$2:$D$46,3,FALSE) | G50: X | H50: X | I50: X | J50: 2 | K50: 3 | L50: =+J50*K50 | M50: =+IF(L50<5,"BAJO",IF(L50<10,"MEDIO",IF(L50<17,"ALTO","CRITICO"))) | N50: Control de cambios en los sistemas Verificación posterior (informe) | O50: ADMINISTRACION | P50: Control Implementado sin evidencia de efectividad (Inefectivo prueba) | Q50: 0.3 | R50: No existe procedimiento formal de gestión de cambios | S50: =+IF(O50="PREVENTIVO",J50*(1-Q50),IF(O50="ADMINISTRACION",J50*(1-Q50),IF(O50="ELIMINACION",J50*(1-Q50),J50))) | T50: =+IF(O50="DETECTIVO",K50*(1-Q50),IF(O50="RECUPERACION",K50*(1-Q50),K50)) | U50: =+S50*T50 | V50: =+IF(U50<5,"BAJO",IF(U50<10,"MEDIO",IF(U50<17,"ALTO","CRITICO"))) | W50: ACEPTABLE | X50: - | Y50: - | Z50: -
A51: 70-GTI | B51: Eset Endpoint Security | C51: Herramienta de control de software malicioso | D51: [SW] Software - Aplicaciones informáticas | E51: [E.24] Caída del sistema por agotamiento de recursos | F51: =+VLOOKUP(E51,'CATALOGO AMENAZA'!$B$2:$D$46,3,FALSE) | I51: X | J51: 3 | K51: 3 | L51: =+J51*K51 | M51: =+IF(L51<5,"BAJO",IF(L51<10,"MEDIO",IF(L51<17,"ALTO","CRITICO"))) | N51: Monitoreo de Servidores presenta en el procedimiento operativo Administración de Servidores en el Manua de Gestión de las Operaciones de TI | O51: PREVENTIVO | P51: Control Implementado sin evidencia de efectividad (Inefectivo prueba) | Q51: 0.4 | R51: Falta de alertas automáticas | S51: =+IF(O51="PREVENTIVO",J51*(1-Q51),IF(O51="ADMINISTRACION",J51*(1-Q51),IF(O51="ELIMINACION",J51*(1-Q51),J51))) | T51: =+IF(O51="DETECTIVO",K51*(1-Q51),IF(O51="RECUPERACION",K51*(1-Q51),K51)) | U51: =+S51*T51 | V51: =+IF(U51<5,"BAJO",IF(U51<10,"MEDIO",IF(U51<17,"ALTO","CRITICO"))) | W51: MITIGAR | X51: - | Y51: - | Z51: -
A52: 71-GTI | B52: FortiMail | C52: Control de correo no deseado Antispam | D52: [SW] Software - Aplicaciones informáticas | E52: [A.11] Acceso no autorizado | F52: =+VLOOKUP(E52,'CATALOGO AMENAZA'!$B$2:$D$46,3,FALSE) | G52: X | H52: X | J52: 3 | K52: 4 | L52: =+J52*K52 | M52: =+IF(L52<5,"BAJO",IF(L52<10,"MEDIO",IF(L52<17,"ALTO","CRITICO"))) | N52: Control de accesos | O52: PREVENTIVO | P52: Control Implementado sin evidencia de efectividad (Inefectivo prueba) | Q52: 0.3 | R52: Usuarios genéricos | S52: =+IF(O52="PREVENTIVO",J52*(1-Q52),IF(O52="ADMINISTRACION",J52*(1-Q52),IF(O52="ELIMINACION",J52*(1-Q52),J52))) | T52: =+IF(O52="DETECTIVO",K52*(1-Q52),IF(O52="RECUPERACION",K52*(1-Q52),K52)) | U52: =+S52*T52 | V52: =+IF(U52<5,"BAJO",IF(U52<10,"MEDIO",IF(U52<17,"ALTO","CRITICO"))) | W52: MITIGAR | X52: - | Y52: - | Z52: -
A53: 71-GTI | B53: FortiMail | C53: Control de correo no deseado Antispam | D53: [SW] Software - Aplicaciones informáticas | E53: [A.23] Manipulación de los equipos | F53: =+VLOOKUP(E53,'CATALOGO AMENAZA'!$B$2:$D$46,3,FALSE) | G53: X | I53: X | J53: 1 | K53: 3 | L53: =+J53*K53 | M53: =+IF(L53<5,"BAJO",IF(L53<10,"MEDIO",IF(L53<17,"ALTO","CRITICO"))) | N53: Control de accesos | O53: PREVENTIVO | P53: Control Implementado sin evidencia de efectividad (Inefectivo prueba) | Q53: 0.3 | R53: Usuarios genéricos | S53: =+IF(O53="PREVENTIVO",J53*(1-Q53),IF(O53="ADMINISTRACION",J53*(1-Q53),IF(O53="ELIMINACION",J53*(1-Q53),J53))) | T53: =+IF(O53="DETECTIVO",K53*(1-Q53),IF(O53="RECUPERACION",K53*(1-Q53),K53)) | U53: =+S53*T53 | V53: =+IF(U53<5,"BAJO",IF(U53<10,"MEDIO",IF(U53<17,"ALTO","CRITICO"))) | W53: ACEPTABLE | X53: - | Y53: - | Z53: -
A54: 71-GTI | B54: FortiMail | C54: Control de correo no deseado Antispam | D54: [SW] Software - Aplicaciones informáticas | E54: [A.6] Abuso de privilegios de acceso | F54: =+VLOOKUP(E54,'CATALOGO AMENAZA'!$B$2:$D$46,3,FALSE) | G54: X | H54: X | I54: X | J54: 2 | K54: 3 | L54: =+J54*K54 | M54: =+IF(L54<5,"BAJO",IF(L54<10,"MEDIO",IF(L54<17,"ALTO","CRITICO"))) | N54: Registro de logs (FortiAnalyzer) | O54: DETECTIVO | P54: Control Implementado sin evidencia de efectividad (Inefectivo prueba) | Q54: 0.3 | R54: Falta de revisión de perfiles de acceso | S54: =+IF(O54="PREVENTIVO",J54*(1-Q54),IF(O54="ADMINISTRACION",J54*(1-Q54),IF(O54="ELIMINACION",J54*(1-Q54),J54))) | T54: =+IF(O54="DETECTIVO",K54*(1-Q54),IF(O54="RECUPERACION",K54*(1-Q54),K54)) | U54: =+S54*T54 | V54: =+IF(U54<5,"BAJO",IF(U54<10,"MEDIO",IF(U54<17,"ALTO","CRITICO"))) | W54: ACEPTABLE | X54: - | Y54: - | Z54: -
A55: 71-GTI | B55: FortiMail | C55: Control de correo no deseado Antispam | D55: [SW] Software - Aplicaciones informáticas | E55: [A.24] Denegación de servicio | F55: =+VLOOKUP(E55,'CATALOGO AMENAZA'!$B$2:$D$46,3,FALSE) | I55: X | J55: 3 | K55: 3 | L55: =+J55*K55 | M55: =+IF(L55<5,"BAJO",IF(L55<10,"MEDIO",IF(L55<17,"ALTO","CRITICO"))) | N55: Configuración segura de firewall | O55: PREVENTIVO | P55: Control Implementado sin evidencia de efectividad (Inefectivo prueba) | Q55: 0.3 | R55: Evidencia de validación de las configuraciones | S55: =+IF(O55="PREVENTIVO",J55*(1-Q55),IF(O55="ADMINISTRACION",J55*(1-Q55),IF(O55="ELIMINACION",J55*(1-Q55),J55))) | T55: =+IF(O55="DETECTIVO",K55*(1-Q55),IF(O55="RECUPERACION",K55*(1-Q55),K55)) | U55: =+S55*T55 | V55: =+IF(U55<5,"BAJO",IF(U55<10,"MEDIO",IF(U55<17,"ALTO","CRITICO"))) | W55: MITIGAR | X55: - | Y55: - | Z55: -
A56: 71-GTI | B56: FortiMail | C56: Control de correo no deseado Antispam | D56: [SW] Software - Aplicaciones informáticas | E56: [E.2] Errores del administrador | F56: =+VLOOKUP(E56,'CATALOGO AMENAZA'!$B$2:$D$46,3,FALSE) | G56: X | H56: X | I56: X | J56: 2 | K56: 3 | L56: =+J56*K56 | M56: =+IF(L56<5,"BAJO",IF(L56<10,"MEDIO",IF(L56<17,"ALTO","CRITICO"))) | N56: Control de cambios en los sistemas Verificación posterior (informe) | O56: ADMINISTRACION | P56: Control Implementado sin evidencia de efectividad (Inefectivo prueba) | Q56: 0.3 | R56: No existe procedimiento formal de gestión de cambios | S56: =+IF(O56="PREVENTIVO",J56*(1-Q56),IF(O56="ADMINISTRACION",J56*(1-Q56),IF(O56="ELIMINACION",J56*(1-Q56),J56))) | T56: =+IF(O56="DETECTIVO",K56*(1-Q56),IF(O56="RECUPERACION",K56*(1-Q56),K56)) | U56: =+S56*T56 | V56: =+IF(U56<5,"BAJO",IF(U56<10,"MEDIO",IF(U56<17,"ALTO","CRITICO"))) | W56: ACEPTABLE | X56: - | Y56: - | Z56: -
A57: 71-GTI | B57: FortiMail | C57: Control de correo no deseado Antispam | D57: [SW] Software - Aplicaciones informáticas | E57: [E.24] Caída del sistema por agotamiento de recursos | F57: =+VLOOKUP(E57,'CATALOGO AMENAZA'!$B$2:$D$46,3,FALSE) | I57: X | J57: 2 | K57: 4 | L57: =+J57*K57 | M57: =+IF(L57<5,"BAJO",IF(L57<10,"MEDIO",IF(L57<17,"ALTO","CRITICO"))) | N57: Monitoreo de Servidores presenta en el procedimiento operativo Administración de Servidores en el Manua de Gestión de las Operaciones de TI | O57: PREVENTIVO | P57: Control Implementado sin evidencia de efectividad (Inefectivo prueba) | Q57: 0.4 | R57: Falta de alertas automáticas | S57: =+IF(O57="PREVENTIVO",J57*(1-Q57),IF(O57="ADMINISTRACION",J57*(1-Q57),IF(O57="ELIMINACION",J57*(1-Q57),J57))) | T57: =+IF(O57="DETECTIVO",K57*(1-Q57),IF(O57="RECUPERACION",K57*(1-Q57),K57)) | U57: =+S57*T57 | V57: =+IF(U57<5,"BAJO",IF(U57<10,"MEDIO",IF(U57<17,"ALTO","CRITICO"))) | W57: ACEPTABLE | X57: - | Y57: - | Z57: -
A58: 72-GTI | B58: Informe de gestión | C58: Informe eventos de seguridad | D58: [D] Datos / Información / datos de configuración | E58: [E.19] Fugas de información | F58: =+VLOOKUP(E58,'CATALOGO AMENAZA'!$B$2:$D$46,3,FALSE) | G58: X | J58: 3 | K58: 4 | L58: =+J58*K58 | M58: =+IF(L58<5,"BAJO",IF(L58<10,"MEDIO",IF(L58<17,"ALTO","CRITICO"))) | N58: Software DLP | O58: PREVENTIVO | P58: Control Implementado sin evidencia de efectividad (Inefectivo prueba) | Q58: 0.3 | R58: Politicas sin restricción para jefaturas | S58: =+IF(O58="PREVENTIVO",J58*(1-Q58),IF(O58="ADMINISTRACION",J58*(1-Q58),IF(O58="ELIMINACION",J58*(1-Q58),J58))) | T58: =+IF(O58="DETECTIVO",K58*(1-Q58),IF(O58="RECUPERACION",K58*(1-Q58),K58)) | U58: =+S58*T58 | V58: =+IF(U58<5,"BAJO",IF(U58<10,"MEDIO",IF(U58<17,"ALTO","CRITICO"))) | W58: MITIGAR | X58: - | Y58: - | Z58: -
A59: 72-GTI | B59: Informe de gestión | C59: Informe eventos de seguridad | D59: [D] Datos / Información / datos de configuración | E59: [E.18] Destrucción de información | F59: =+VLOOKUP(E59,'CATALOGO AMENAZA'!$B$2:$D$46,3,FALSE) | I59: X | J59: 3 | K59: 3 | L59: =+J59*K59 | M59: =+IF(L59<5,"BAJO",IF(L59<10,"MEDIO",IF(L59<17,"ALTO","CRITICO"))) | N59: Respaldo digital de información | O59: PREVENTIVO | P59: Control Implementado sin evidencia de efectividad (Inefectivo prueba) | Q59: 0.3 | R59: Almacenamiento manual en medio extraible | S59: =+IF(O59="PREVENTIVO",J59*(1-Q59),IF(O59="ADMINISTRACION",J59*(1-Q59),IF(O59="ELIMINACION",J59*(1-Q59),J59))) | T59: =+IF(O59="DETECTIVO",K59*(1-Q59),IF(O59="RECUPERACION",K59*(1-Q59),K59)) | U59: =+S59*T59 | V59: =+IF(U59<5,"BAJO",IF(U59<10,"MEDIO",IF(U59<17,"ALTO","CRITICO"))) | W59: MITIGAR | X59: - | Y59: - | Z59: -
A60: 73-GTI | B60: Consola ESET | C60: Servidor control software malicioso 192.168.100.235 | D60: [HW] Equipamiento informático (hardware) | E60: [A.11] Acceso no autorizado | F60: =+VLOOKUP(E60,'CATALOGO AMENAZA'!$B$2:$D$46,3,FALSE) | G60: X | H60: X | J60: 2 | K60: 3 | L60: =+J60*K60 | M60: =+IF(L60<5,"BAJO",IF(L60<10,"MEDIO",IF(L60<17,"ALTO","CRITICO"))) | N60: Control de accesos / VPN | O60: PREVENTIVO | P60: Control Implementado sin evidencia de efectividad (Inefectivo prueba) | Q60: 0.3 | R60: Contreaseñas de VPN no expiran | S60: =+IF(O60="PREVENTIVO",J60*(1-Q60),IF(O60="ADMINISTRACION",J60*(1-Q60),IF(O60="ELIMINACION",J60*(1-Q60),J60))) | T60: =+IF(O60="DETECTIVO",K60*(1-Q60),IF(O60="RECUPERACION",K60*(1-Q60),K60)) | U60: =+S60*T60 | V60: =+IF(U60<5,"BAJO",IF(U60<10,"MEDIO",IF(U60<17,"ALTO","CRITICO"))) | W60: ACEPTABLE | X60: - | Y60: - | Z60: -
A61: 73-GTI | B61: Consola ESET | C61: Servidor control software malicioso 192.168.100.235 | D61: [HW] Equipamiento informático (hardware) | E61: [A.23] Manipulación de los equipos | F61: =+VLOOKUP(E61,'CATALOGO AMENAZA'!$B$2:$D$46,3,FALSE) | G61: X | I61: X | J61: 2 | K61: 3 | L61: =+J61*K61 | M61: =+IF(L61<5,"BAJO",IF(L61<10,"MEDIO",IF(L61<17,"ALTO","CRITICO"))) | N61: Control de accesos | O61: PREVENTIVO | P61: Control Implementado sin evidencia de efectividad (Inefectivo prueba) | Q61: 0.3 | R61: Usuarios genéricos | S61: =+IF(O61="PREVENTIVO",J61*(1-Q61),IF(O61="ADMINISTRACION",J61*(1-Q61),IF(O61="ELIMINACION",J61*(1-Q61),J61))) | T61: =+IF(O61="DETECTIVO",K61*(1-Q61),IF(O61="RECUPERACION",K61*(1-Q61),K61)) | U61: =+S61*T61 | V61: =+IF(U61<5,"BAJO",IF(U61<10,"MEDIO",IF(U61<17,"ALTO","CRITICO"))) | W61: ACEPTABLE | X61: - | Y61: - | Z61: -
A62: 73-GTI | B62: Consola ESET | C62: Servidor control software malicioso 192.168.100.235 | D62: [HW] Equipamiento informático (hardware) | E62: [A.6] Abuso de privilegios de acceso | F62: =+VLOOKUP(E62,'CATALOGO AMENAZA'!$B$2:$D$46,3,FALSE) | G62: X | H62: X | I62: X | J62: 2 | K62: 3 | L62: =+J62*K62 | M62: =+IF(L62<5,"BAJO",IF(L62<10,"MEDIO",IF(L62<17,"ALTO","CRITICO"))) | N62: Registro de logs (FortiAnalyzer) | O62: DETECTIVO | P62: Control Implementado sin evidencia de efectividad (Inefectivo prueba) | Q62: 0.3 | R62: Falta de revisión de perfiles de acceso | S62: =+IF(O62="PREVENTIVO",J62*(1-Q62),IF(O62="ADMINISTRACION",J62*(1-Q62),IF(O62="ELIMINACION",J62*(1-Q62),J62))) | T62: =+IF(O62="DETECTIVO",K62*(1-Q62),IF(O62="RECUPERACION",K62*(1-Q62),K62)) | U62: =+S62*T62 | V62: =+IF(U62<5,"BAJO",IF(U62<10,"MEDIO",IF(U62<17,"ALTO","CRITICO"))) | W62: ACEPTABLE | X62: - | Y62: - | Z62: -
A63: 73-GTI | B63: Consola ESET | C63: Servidor control software malicioso 192.168.100.235 | D63: [HW] Equipamiento informático (hardware) | E63: [A.24] Denegación de servicio | F63: =+VLOOKUP(E63,'CATALOGO AMENAZA'!$B$2:$D$46,3,FALSE) | I63: X | J63: 3 | K63: 4 | L63: =+J63*K63 | M63: =+IF(L63<5,"BAJO",IF(L63<10,"MEDIO",IF(L63<17,"ALTO","CRITICO"))) | N63: Configuración segura de firewall | O63: PREVENTIVO | P63: Control Implementado sin evidencia de efectividad (Inefectivo prueba) | Q63: 0.3 | R63: Evidencia de validación de las configuraciones | S63: =+IF(O63="PREVENTIVO",J63*(1-Q63),IF(O63="ADMINISTRACION",J63*(1-Q63),IF(O63="ELIMINACION",J63*(1-Q63),J63))) | T63: =+IF(O63="DETECTIVO",K63*(1-Q63),IF(O63="RECUPERACION",K63*(1-Q63),K63)) | U63: =+S63*T63 | V63: =+IF(U63<5,"BAJO",IF(U63<10,"MEDIO",IF(U63<17,"ALTO","CRITICO"))) | W63: MITIGAR | X63: - | Y63: - | Z63: -
A64: 73-GTI | B64: Consola ESET | C64: Servidor control software malicioso 192.168.100.235 | D64: [HW] Equipamiento informático (hardware) | E64: [E.2] Errores del administrador | F64: =+VLOOKUP(E64,'CATALOGO AMENAZA'!$B$2:$D$46,3,FALSE) | G64: X | H64: X | I64: X | J64: 2 | K64: 3 | L64: =+J64*K64 | M64: =+IF(L64<5,"BAJO",IF(L64<10,"MEDIO",IF(L64<17,"ALTO","CRITICO"))) | N64: Control de cambios en los sistemas Verificación posterior (informe) | O64: ADMINISTRACION | P64: Control Implementado sin evidencia de efectividad (Inefectivo prueba) | Q64: 0.3 | R64: No existe procedimiento formal de gestión de cambios | S64: =+IF(O64="PREVENTIVO",J64*(1-Q64),IF(O64="ADMINISTRACION",J64*(1-Q64),IF(O64="ELIMINACION",J64*(1-Q64),J64))) | T64: =+IF(O64="DETECTIVO",K64*(1-Q64),IF(O64="RECUPERACION",K64*(1-Q64),K64)) | U64: =+S64*T64 | V64: =+IF(U64<5,"BAJO",IF(U64<10,"MEDIO",IF(U64<17,"ALTO","CRITICO"))) | W64: ACEPTABLE | X64: - | Y64: - | Z64: -
A65: 73-GTI | B65: Consola ESET | C65: Servidor control software malicioso 192.168.100.235 | D65: [HW] Equipamiento informático (hardware) | E65: [E.24] Caída del sistema por agotamiento de recursos | F65: =+VLOOKUP(E65,'CATALOGO AMENAZA'!$B$2:$D$46,3,FALSE) | I65: X | J65: 2 | K65: 3 | L65: =+J65*K65 | M65: =+IF(L65<5,"BAJO",IF(L65<10,"MEDIO",IF(L65<17,"ALTO","CRITICO"))) | N65: Procedimiento de Gestión de la capacidad y desempeño de la Infraestructura | O65: PREVENTIVO | P65: Control Implementado sin evidencia de efectividad (Inefectivo prueba) | Q65: 0.3 | R65: Notificación automática de alertas | S65: =+IF(O65="PREVENTIVO",J65*(1-Q65),IF(O65="ADMINISTRACION",J65*(1-Q65),IF(O65="ELIMINACION",J65*(1-Q65),J65))) | T65: =+IF(O65="DETECTIVO",K65*(1-Q65),IF(O65="RECUPERACION",K65*(1-Q65),K65)) | U65: =+S65*T65 | V65: =+IF(U65<5,"BAJO",IF(U65<10,"MEDIO",IF(U65<17,"ALTO","CRITICO"))) | W65: ACEPTABLE | X65: - | Y65: - | Z65: -
A66: 74-GTI | B66: Consola AntiSpam | C66: Servidor prevencion correo no deseado 192.168.23.6 | D66: [HW] Equipamiento informático (hardware) | E66: [A.11] Acceso no autorizado | F66: =+VLOOKUP(E66,'CATALOGO AMENAZA'!$B$2:$D$46,3,FALSE) | G66: X | H66: X | J66: 3 | K66: 4 | L66: =+J66*K66 | M66: =+IF(L66<5,"BAJO",IF(L66<10,"MEDIO",IF(L66<17,"ALTO","CRITICO"))) | N66: Control de accesos / VPN | O66: PREVENTIVO | P66: Control Implementado sin evidencia de efectividad (Inefectivo prueba) | Q66: 0.3 | R66: Contreaseñas de VPN no expiran | S66: =+IF(O66="PREVENTIVO",J66*(1-Q66),IF(O66="ADMINISTRACION",J66*(1-Q66),IF(O66="ELIMINACION",J66*(1-Q66),J66))) | T66: =+IF(O66="DETECTIVO",K66*(1-Q66),IF(O66="RECUPERACION",K66*(1-Q66),K66)) | U66: =+S66*T66 | V66: =+IF(U66<5,"BAJO",IF(U66<10,"MEDIO",IF(U66<17,"ALTO","CRITICO"))) | W66: MITIGAR | X66: - | Y66: - | Z66: -
A67: 74-GTI | B67: Consola AntiSpam | C67: Servidor prevencion correo no deseado 192.168.23.6 | D67: [HW] Equipamiento informático (hardware) | E67: [A.23] Manipulación de los equipos | F67: =+VLOOKUP(E67,'CATALOGO AMENAZA'!$B$2:$D$46,3,FALSE) | G67: X | I67: X | J67: 3 | K67: 3 | L67: =+J67*K67 | M67: =+IF(L67<5,"BAJO",IF(L67<10,"MEDIO",IF(L67<17,"ALTO","CRITICO"))) | N67: Control de accesos | O67: PREVENTIVO | P67: Control Implementado sin evidencia de efectividad (Inefectivo prueba) | Q67: 0.3 | R67: Usuarios genéricos | S67: =+IF(O67="PREVENTIVO",J67*(1-Q67),IF(O67="ADMINISTRACION",J67*(1-Q67),IF(O67="ELIMINACION",J67*(1-Q67),J67))) | T67: =+IF(O67="DETECTIVO",K67*(1-Q67),IF(O67="RECUPERACION",K67*(1-Q67),K67)) | U67: =+S67*T67 | V67: =+IF(U67<5,"BAJO",IF(U67<10,"MEDIO",IF(U67<17,"ALTO","CRITICO"))) | W67: MITIGAR | X67: - | Y67: - | Z67: -
A68: 74-GTI | B68: Consola AntiSpam | C68: Servidor prevencion correo no deseado 192.168.23.6 | D68: [HW] Equipamiento informático (hardware) | E68: [A.6] Abuso de privilegios de acceso | F68: =+VLOOKUP(E68,'CATALOGO AMENAZA'!$B$2:$D$46,3,FALSE) | G68: X | H68: X | I68: X | J68: 2 | K68: 3 | L68: =+J68*K68 | M68: =+IF(L68<5,"BAJO",IF(L68<10,"MEDIO",IF(L68<17,"ALTO","CRITICO"))) | N68: Registro de logs (FortiAnalyzer) | O68: DETECTIVO | P68: Control Implementado sin evidencia de efectividad (Inefectivo prueba) | Q68: 0.3 | R68: Falta de revisión de perfiles de acceso | S68: =+IF(O68="PREVENTIVO",J68*(1-Q68),IF(O68="ADMINISTRACION",J68*(1-Q68),IF(O68="ELIMINACION",J68*(1-Q68),J68))) | T68: =+IF(O68="DETECTIVO",K68*(1-Q68),IF(O68="RECUPERACION",K68*(1-Q68),K68)) | U68: =+S68*T68 | V68: =+IF(U68<5,"BAJO",IF(U68<10,"MEDIO",IF(U68<17,"ALTO","CRITICO"))) | W68: ACEPTABLE | X68: - | Y68: - | Z68: -
A69: 74-GTI | B69: Consola AntiSpam | C69: Servidor prevencion correo no deseado 192.168.23.6 | D69: [HW] Equipamiento informático (hardware) | E69: [A.24] Denegación de servicio | F69: =+VLOOKUP(E69,'CATALOGO AMENAZA'!$B$2:$D$46,3,FALSE) | I69: X | J69: 3 | K69: 4 | L69: =+J69*K69 | M69: =+IF(L69<5,"BAJO",IF(L69<10,"MEDIO",IF(L69<17,"ALTO","CRITICO"))) | N69: Configuración segura de firewall | O69: PREVENTIVO | P69: Control Implementado sin evidencia de efectividad (Inefectivo prueba) | Q69: 0.3 | R69: Evidencia de validación de las configuraciones | S69: =+IF(O69="PREVENTIVO",J69*(1-Q69),IF(O69="ADMINISTRACION",J69*(1-Q69),IF(O69="ELIMINACION",J69*(1-Q69),J69))) | T69: =+IF(O69="DETECTIVO",K69*(1-Q69),IF(O69="RECUPERACION",K69*(1-Q69),K69)) | U69: =+S69*T69 | V69: =+IF(U69<5,"BAJO",IF(U69<10,"MEDIO",IF(U69<17,"ALTO","CRITICO"))) | W69: MITIGAR | X69: - | Y69: - | Z69: -
A70: 74-GTI | B70: Consola AntiSpam | C70: Servidor prevencion correo no deseado 192.168.23.6 | D70: [HW] Equipamiento informático (hardware) | E70: [E.2] Errores del administrador | F70: =+VLOOKUP(E70,'CATALOGO AMENAZA'!$B$2:$D$46,3,FALSE) | G70: X | H70: X | I70: X | J70: 2 | K70: 4 | L70: =+J70*K70 | M70: =+IF(L70<5,"BAJO",IF(L70<10,"MEDIO",IF(L70<17,"ALTO","CRITICO"))) | N70: Control de cambios en los sistemas Verificación posterior (informe) | O70: ADMINISTRACION | P70: Control Implementado sin evidencia de efectividad (Inefectivo prueba) | Q70: 0.3 | R70: No existe procedimiento formal de gestión de cambios | S70: =+IF(O70="PREVENTIVO",J70*(1-Q70),IF(O70="ADMINISTRACION",J70*(1-Q70),IF(O70="ELIMINACION",J70*(1-Q70),J70))) | T70: =+IF(O70="DETECTIVO",K70*(1-Q70),IF(O70="RECUPERACION",K70*(1-Q70),K70)) | U70: =+S70*T70 | V70: =+IF(U70<5,"BAJO",IF(U70<10,"MEDIO",IF(U70<17,"ALTO","CRITICO"))) | W70: MITIGAR | X70: - | Y70: - | Z70: -
A71: 74-GTI | B71: Consola AntiSpam | C71: Servidor prevencion correo no deseado 192.168.23.6 | D71: [HW] Equipamiento informático (hardware) | E71: [E.24] Caída del sistema por agotamiento de recursos | F71: =+VLOOKUP(E71,'CATALOGO AMENAZA'!$B$2:$D$46,3,FALSE) | I71: X | J71: 2 | K71: 3 | L71: =+J71*K71 | M71: =+IF(L71<5,"BAJO",IF(L71<10,"MEDIO",IF(L71<17,"ALTO","CRITICO"))) | N71: Procedimiento de Gestión de la capacidad y desempeño de la Infraestructura | O71: PREVENTIVO | P71: Control Implementado sin evidencia de efectividad (Inefectivo prueba) | Q71: 0.3 | R71: Notificación automática de alertas | S71: =+IF(O71="PREVENTIVO",J71*(1-Q71),IF(O71="ADMINISTRACION",J71*(1-Q71),IF(O71="ELIMINACION",J71*(1-Q71),J71))) | T71: =+IF(O71="DETECTIVO",K71*(1-Q71),IF(O71="RECUPERACION",K71*(1-Q71),K71)) | U71: =+S71*T71 | V71: =+IF(U71<5,"BAJO",IF(U71<10,"MEDIO",IF(U71<17,"ALTO","CRITICO"))) | W71: ACEPTABLE | X71: - | Y71: - | Z71: -
A72: 75-GTI | B72: Consola Firewall | C72: Consola de administracion firewall 192.168.21.2 | D72: [HW] Equipamiento informático (hardware) | E72: [A.11] Acceso no autorizado | F72: =+VLOOKUP(E72,'CATALOGO AMENAZA'!$B$2:$D$46,3,FALSE) | G72: X | H72: X | J72: 3 | K72: 4 | L72: =+J72*K72 | M72: =+IF(L72<5,"BAJO",IF(L72<10,"MEDIO",IF(L72<17,"ALTO","CRITICO"))) | N72: Control de accesos / VPN | O72: PREVENTIVO | P72: Control Implementado sin evidencia de efectividad (Inefectivo prueba) | Q72: 0.3 | R72: Contreaseñas de VPN no expiran | S72: =+IF(O72="PREVENTIVO",J72*(1-Q72),IF(O72="ADMINISTRACION",J72*(1-Q72),IF(O72="ELIMINACION",J72*(1-Q72),J72))) | T72: =+IF(O72="DETECTIVO",K72*(1-Q72),IF(O72="RECUPERACION",K72*(1-Q72),K72)) | U72: =+S72*T72 | V72: =+IF(U72<5,"BAJO",IF(U72<10,"MEDIO",IF(U72<17,"ALTO","CRITICO"))) | W72: MITIGAR | X72: - | Y72: - | Z72: -
A73: 75-GTI | B73: Consola Firewall | C73: Consola de administracion firewall 192.168.21.2 | D73: [HW] Equipamiento informático (hardware) | E73: [A.23] Manipulación de los equipos | F73: =+VLOOKUP(E73,'CATALOGO AMENAZA'!$B$2:$D$46,3,FALSE) | G73: X | I73: X | J73: 2 | K73: 4 | L73: =+J73*K73 | M73: =+IF(L73<5,"BAJO",IF(L73<10,"MEDIO",IF(L73<17,"ALTO","CRITICO"))) | N73: Control de accesos | O73: PREVENTIVO | P73: Control Implementado sin evidencia de efectividad (Inefectivo prueba) | Q73: 0.3 | R73: Usuarios genéricos | S73: =+IF(O73="PREVENTIVO",J73*(1-Q73),IF(O73="ADMINISTRACION",J73*(1-Q73),IF(O73="ELIMINACION",J73*(1-Q73),J73))) | T73: =+IF(O73="DETECTIVO",K73*(1-Q73),IF(O73="RECUPERACION",K73*(1-Q73),K73)) | U73: =+S73*T73 | V73: =+IF(U73<5,"BAJO",IF(U73<10,"MEDIO",IF(U73<17,"ALTO","CRITICO"))) | W73: MITIGAR | X73: - | Y73: - | Z73: -
A74: 75-GTI | B74: Consola Firewall | C74: Consola de administracion firewall 192.168.21.2 | D74: [HW] Equipamiento informático (hardware) | E74: [A.6] Abuso de privilegios de acceso | F74: =+VLOOKUP(E74,'CATALOGO AMENAZA'!$B$2:$D$46,3,FALSE) | G74: X | H74: X | I74: X | J74: 2 | K74: 4 | L74: =+J74*K74 | M74: =+IF(L74<5,"BAJO",IF(L74<10,"MEDIO",IF(L74<17,"ALTO","CRITICO"))) | N74: Registro de logs (FortiAnalyzer) | O74: DETECTIVO | P74: Control Implementado sin evidencia de efectividad (Inefectivo prueba) | Q74: 0.3 | R74: Falta de revisión de perfiles de acceso | S74: =+IF(O74="PREVENTIVO",J74*(1-Q74),IF(O74="ADMINISTRACION",J74*(1-Q74),IF(O74="ELIMINACION",J74*(1-Q74),J74))) | T74: =+IF(O74="DETECTIVO",K74*(1-Q74),IF(O74="RECUPERACION",K74*(1-Q74),K74)) | U74: =+S74*T74 | V74: =+IF(U74<5,"BAJO",IF(U74<10,"MEDIO",IF(U74<17,"ALTO","CRITICO"))) | W74: MITIGAR | X74: - | Y74: - | Z74: -
A75: 75-GTI | B75: Consola Firewall | C75: Consola de administracion firewall 192.168.21.2 | D75: [HW] Equipamiento informático (hardware) | E75: [A.24] Denegación de servicio | F75: =+VLOOKUP(E75,'CATALOGO AMENAZA'!$B$2:$D$46,3,FALSE) | I75: X | J75: 3 | K75: 5 | L75: =+J75*K75 | M75: =+IF(L75<5,"BAJO",IF(L75<10,"MEDIO",IF(L75<17,"ALTO","CRITICO"))) | N75: Configuración segura de firewall | O75: PREVENTIVO | P75: Control Implementado sin evidencia de efectividad (Inefectivo prueba) | Q75: 0.3 | R75: Evidencia de validación de las configuraciones | S75: =+IF(O75="PREVENTIVO",J75*(1-Q75),IF(O75="ADMINISTRACION",J75*(1-Q75),IF(O75="ELIMINACION",J75*(1-Q75),J75))) | T75: =+IF(O75="DETECTIVO",K75*(1-Q75),IF(O75="RECUPERACION",K75*(1-Q75),K75)) | U75: =+S75*T75 | V75: =+IF(U75<5,"BAJO",IF(U75<10,"MEDIO",IF(U75<17,"ALTO","CRITICO"))) | W75: MITIGAR | X75: REQUIERE TRATAMIENTO | Y75: PA-SI-003 | Z75: Determinar accesos restringidos para la consola administrativa
A76: 75-GTI | B76: Consola Firewall | C76: Consola de administracion firewall 192.168.21.2 | D76: [HW] Equipamiento informático (hardware) | E76: [E.2] Errores del administrador | F76: =+VLOOKUP(E76,'CATALOGO AMENAZA'!$B$2:$D$46,3,FALSE) | G76: X | H76: X | I76: X | J76: 2 | K76: 4 | L76: =+J76*K76 | M76: =+IF(L76<5,"BAJO",IF(L76<10,"MEDIO",IF(L76<17,"ALTO","CRITICO"))) | N76: Control de cambios en los sistemas Verificación posterior (informe) | O76: ADMINISTRACION | P76: Control Implementado sin evidencia de efectividad (Inefectivo prueba) | Q76: 0.3 | R76: No existe procedimiento formal de gestión de cambios | S76: =+IF(O76="PREVENTIVO",J76*(1-Q76),IF(O76="ADMINISTRACION",J76*(1-Q76),IF(O76="ELIMINACION",J76*(1-Q76),J76))) | T76: =+IF(O76="DETECTIVO",K76*(1-Q76),IF(O76="RECUPERACION",K76*(1-Q76),K76)) | U76: =+S76*T76 | V76: =+IF(U76<5,"BAJO",IF(U76<10,"MEDIO",IF(U76<17,"ALTO","CRITICO"))) | W76: MITIGAR | X76: - | Y76: - | Z76: -
A77: 75-GTI | B77: Consola Firewall | C77: Consola de administracion firewall 192.168.21.2 | D77: [HW] Equipamiento informático (hardware) | E77: [E.24] Caída del sistema por agotamiento de recursos | F77: =+VLOOKUP(E77,'CATALOGO AMENAZA'!$B$2:$D$46,3,FALSE) | I77: X | J77: 2 | K77: 3 | L77: =+J77*K77 | M77: =+IF(L77<5,"BAJO",IF(L77<10,"MEDIO",IF(L77<17,"ALTO","CRITICO"))) | N77: Procedimiento de Gestión de la capacidad y desempeño de la Infraestructura | O77: PREVENTIVO | P77: Control Implementado sin evidencia de efectividad (Inefectivo prueba) | Q77: 0.3 | R77: Notificación automática de alertas | S77: =+IF(O77="PREVENTIVO",J77*(1-Q77),IF(O77="ADMINISTRACION",J77*(1-Q77),IF(O77="ELIMINACION",J77*(1-Q77),J77))) | T77: =+IF(O77="DETECTIVO",K77*(1-Q77),IF(O77="RECUPERACION",K77*(1-Q77),K77)) | U77: =+S77*T77 | V77: =+IF(U77<5,"BAJO",IF(U77<10,"MEDIO",IF(U77<17,"ALTO","CRITICO"))) | W77: ACEPTABLE | X77: - | Y77: - | Z77: -
A78: 77-GTI | B78: Consola FortiAnalizer | C78: Analizador de logs 192.168.100.232 | D78: [HW] Equipamiento informático (hardware) | E78: [A.11] Acceso no autorizado | F78: =+VLOOKUP(E78,'CATALOGO AMENAZA'!$B$2:$D$46,3,FALSE) | G78: X | H78: X | J78: 2 | K78: 3 | L78: =+J78*K78 | M78: =+IF(L78<5,"BAJO",IF(L78<10,"MEDIO",IF(L78<17,"ALTO","CRITICO"))) | N78: Control de accesos / VPN | O78: PREVENTIVO | P78: Control Implementado sin evidencia de efectividad (Inefectivo prueba) | Q78: 0.3 | R78: Contreaseñas de VPN no expiran | S78: =+IF(O78="PREVENTIVO",J78*(1-Q78),IF(O78="ADMINISTRACION",J78*(1-Q78),IF(O78="ELIMINACION",J78*(1-Q78),J78))) | T78: =+IF(O78="DETECTIVO",K78*(1-Q78),IF(O78="RECUPERACION",K78*(1-Q78),K78)) | U78: =+S78*T78 | V78: =+IF(U78<5,"BAJO",IF(U78<10,"MEDIO",IF(U78<17,"ALTO","CRITICO"))) | W78: ACEPTABLE | X78: - | Y78: - | Z78: -
A79: 77-GTI | B79: Consola FortiAnalizer | C79: Analizador de logs 192.168.100.232 | D79: [HW] Equipamiento informático (hardware) | E79: [A.23] Manipulación de los equipos | F79: =+VLOOKUP(E79,'CATALOGO AMENAZA'!$B$2:$D$46,3,FALSE) | G79: X | I79: X | J79: 2 | K79: 3 | L79: =+J79*K79 | M79: =+IF(L79<5,"BAJO",IF(L79<10,"MEDIO",IF(L79<17,"ALTO","CRITICO"))) | N79: Control de accesos | O79: PREVENTIVO | P79: Control Implementado sin evidencia de efectividad (Inefectivo prueba) | Q79: 0.3 | R79: Usuarios genéricos | S79: =+IF(O79="PREVENTIVO",J79*(1-Q79),IF(O79="ADMINISTRACION",J79*(1-Q79),IF(O79="ELIMINACION",J79*(1-Q79),J79))) | T79: =+IF(O79="DETECTIVO",K79*(1-Q79),IF(O79="RECUPERACION",K79*(1-Q79),K79)) | U79: =+S79*T79 | V79: =+IF(U79<5,"BAJO",IF(U79<10,"MEDIO",IF(U79<17,"ALTO","CRITICO"))) | W79: ACEPTABLE | X79: - | Y79: - | Z79: -
A80: 77-GTI | B80: Consola FortiAnalizer | C80: Analizador de logs 192.168.100.232 | D80: [HW] Equipamiento informático (hardware) | E80: [A.6] Abuso de privilegios de acceso | F80: =+VLOOKUP(E80,'CATALOGO AMENAZA'!$B$2:$D$46,3,FALSE) | G80: X | H80: X | I80: X | J80: 2 | K80: 3 | L80: =+J80*K80 | M80: =+IF(L80<5,"BAJO",IF(L80<10,"MEDIO",IF(L80<17,"ALTO","CRITICO"))) | N80: Registro de logs (FortiAnalyzer) | O80: DETECTIVO | P80: Control Implementado sin evidencia de efectividad (Inefectivo prueba) | Q80: 0.3 | R80: Falta de revisión de perfiles de acceso | S80: =+IF(O80="PREVENTIVO",J80*(1-Q80),IF(O80="ADMINISTRACION",J80*(1-Q80),IF(O80="ELIMINACION",J80*(1-Q80),J80))) | T80: =+IF(O80="DETECTIVO",K80*(1-Q80),IF(O80="RECUPERACION",K80*(1-Q80),K80)) | U80: =+S80*T80 | V80: =+IF(U80<5,"BAJO",IF(U80<10,"MEDIO",IF(U80<17,"ALTO","CRITICO"))) | W80: ACEPTABLE | X80: - | Y80: - | Z80: -
A81: 77-GTI | B81: Consola FortiAnalizer | C81: Analizador de logs 192.168.100.232 | D81: [HW] Equipamiento informático (hardware) | E81: [A.24] Denegación de servicio | F81: =+VLOOKUP(E81,'CATALOGO AMENAZA'!$B$2:$D$46,3,FALSE) | I81: X | J81: 3 | K81: 3 | L81: =+J81*K81 | M81: =+IF(L81<5,"BAJO",IF(L81<10,"MEDIO",IF(L81<17,"ALTO","CRITICO"))) | N81: Configuración segura de firewall | O81: PREVENTIVO | P81: Control Implementado sin evidencia de efectividad (Inefectivo prueba) | Q81: 0.3 | R81: Evidencia de validación de las configuraciones | S81: =+IF(O81="PREVENTIVO",J81*(1-Q81),IF(O81="ADMINISTRACION",J81*(1-Q81),IF(O81="ELIMINACION",J81*(1-Q81),J81))) | T81: =+IF(O81="DETECTIVO",K81*(1-Q81),IF(O81="RECUPERACION",K81*(1-Q81),K81)) | U81: =+S81*T81 | V81: =+IF(U81<5,"BAJO",IF(U81<10,"MEDIO",IF(U81<17,"ALTO","CRITICO"))) | W81: MITIGAR | X81: - | Y81: - | Z81: -
A82: 77-GTI | B82: Consola FortiAnalizer | C82: Analizador de logs 192.168.100.232 | D82: [HW] Equipamiento informático (hardware) | E82: [E.2] Errores del administrador | F82: =+VLOOKUP(E82,'CATALOGO AMENAZA'!$B$2:$D$46,3,FALSE) | G82: X | H82: X | I82: X | J82: 2 | K82: 3 | L82: =+J82*K82 | M82: =+IF(L82<5,"BAJO",IF(L82<10,"MEDIO",IF(L82<17,"ALTO","CRITICO"))) | N82: Control de cambios en los sistemas Verificación posterior (informe) | O82: ADMINISTRACION | P82: Control Implementado sin evidencia de efectividad (Inefectivo prueba) | Q82: 0.3 | R82: No existe procedimiento formal de gestión de cambios | S82: =+IF(O82="PREVENTIVO",J82*(1-Q82),IF(O82="ADMINISTRACION",J82*(1-Q82),IF(O82="ELIMINACION",J82*(1-Q82),J82))) | T82: =+IF(O82="DETECTIVO",K82*(1-Q82),IF(O82="RECUPERACION",K82*(1-Q82),K82)) | U82: =+S82*T82 | V82: =+IF(U82<5,"BAJO",IF(U82<10,"MEDIO",IF(U82<17,"ALTO","CRITICO"))) | W82: ACEPTABLE | X82: - | Y82: - | Z82: -
A83: 77-GTI | B83: Consola FortiAnalizer | C83: Analizador de logs 192.168.100.232 | D83: [HW] Equipamiento informático (hardware) | E83: [E.24] Caída del sistema por agotamiento de recursos | F83: =+VLOOKUP(E83,'CATALOGO AMENAZA'!$B$2:$D$46,3,FALSE) | I83: X | J83: 3 | K83: 3 | L83: =+J83*K83 | M83: =+IF(L83<5,"BAJO",IF(L83<10,"MEDIO",IF(L83<17,"ALTO","CRITICO"))) | N83: Procedimiento de Gestión de la capacidad y desempeño de la Infraestructura | O83: PREVENTIVO | P83: Control Implementado sin evidencia de efectividad (Inefectivo prueba) | Q83: 0.3 | R83: Notificación automática de alertas | S83: =+IF(O83="PREVENTIVO",J83*(1-Q83),IF(O83="ADMINISTRACION",J83*(1-Q83),IF(O83="ELIMINACION",J83*(1-Q83),J83))) | T83: =+IF(O83="DETECTIVO",K83*(1-Q83),IF(O83="RECUPERACION",K83*(1-Q83),K83)) | U83: =+S83*T83 | V83: =+IF(U83<5,"BAJO",IF(U83<10,"MEDIO",IF(U83<17,"ALTO","CRITICO"))) | W83: MITIGAR | X83: - | Y83: - | Z83: -
A84: 78-GTI | B84: FortiGate | C84: Consola de administracion 192.168.100.238 | D84: [HW] Equipamiento informático (hardware) | E84: [A.11] Acceso no autorizado | F84: =+VLOOKUP(E84,'CATALOGO AMENAZA'!$B$2:$D$46,3,FALSE) | G84: X | H84: X | J84: 3 | K84: 4 | L84: =+J84*K84 | M84: =+IF(L84<5,"BAJO",IF(L84<10,"MEDIO",IF(L84<17,"ALTO","CRITICO"))) | N84: Control de accesos / VPN | O84: PREVENTIVO | P84: Control Implementado sin evidencia de efectividad (Inefectivo prueba) | Q84: 0.3 | R84: Contreaseñas de VPN no expiran | S84: =+IF(O84="PREVENTIVO",J84*(1-Q84),IF(O84="ADMINISTRACION",J84*(1-Q84),IF(O84="ELIMINACION",J84*(1-Q84),J84))) | T84: =+IF(O84="DETECTIVO",K84*(1-Q84),IF(O84="RECUPERACION",K84*(1-Q84),K84)) | U84: =+S84*T84 | V84: =+IF(U84<5,"BAJO",IF(U84<10,"MEDIO",IF(U84<17,"ALTO","CRITICO"))) | W84: MITIGAR | X84: - | Y84: - | Z84: -
A85: 78-GTI | B85: FortiGate | C85: Consola de administracion 192.168.100.238 | D85: [HW] Equipamiento informático (hardware) | E85: [A.23] Manipulación de los equipos | F85: =+VLOOKUP(E85,'CATALOGO AMENAZA'!$B$2:$D$46,3,FALSE) | G85: X | I85: X | J85: 2 | K85: 3 | L85: =+J85*K85 | M85: =+IF(L85<5,"BAJO",IF(L85<10,"MEDIO",IF(L85<17,"ALTO","CRITICO"))) | N85: Control de accesos | O85: PREVENTIVO | P85: Control Implementado sin evidencia de efectividad (Inefectivo prueba) | Q85: 0.3 | R85: Usuarios genéricos | S85: =+IF(O85="PREVENTIVO",J85*(1-Q85),IF(O85="ADMINISTRACION",J85*(1-Q85),IF(O85="ELIMINACION",J85*(1-Q85),J85))) | T85: =+IF(O85="DETECTIVO",K85*(1-Q85),IF(O85="RECUPERACION",K85*(1-Q85),K85)) | U85: =+S85*T85 | V85: =+IF(U85<5,"BAJO",IF(U85<10,"MEDIO",IF(U85<17,"ALTO","CRITICO"))) | W85: ACEPTABLE | X85: - | Y85: - | Z85: -
A86: 78-GTI | B86: FortiGate | C86: Consola de administracion 192.168.100.238 | D86: [HW] Equipamiento informático (hardware) | E86: [A.6] Abuso de privilegios de acceso | F86: =+VLOOKUP(E86,'CATALOGO AMENAZA'!$B$2:$D$46,3,FALSE) | G86: X | H86: X | I86: X | J86: 2 | K86: 4 | L86: =+J86*K86 | M86: =+IF(L86<5,"BAJO",IF(L86<10,"MEDIO",IF(L86<17,"ALTO","CRITICO"))) | N86: Registro de logs (FortiAnalyzer) | O86: DETECTIVO | P86: Control Implementado sin evidencia de efectividad (Inefectivo prueba) | Q86: 0.3 | R86: Falta de revisión de perfiles de acceso | S86: =+IF(O86="PREVENTIVO",J86*(1-Q86),IF(O86="ADMINISTRACION",J86*(1-Q86),IF(O86="ELIMINACION",J86*(1-Q86),J86))) | T86: =+IF(O86="DETECTIVO",K86*(1-Q86),IF(O86="RECUPERACION",K86*(1-Q86),K86)) | U86: =+S86*T86 | V86: =+IF(U86<5,"BAJO",IF(U86<10,"MEDIO",IF(U86<17,"ALTO","CRITICO"))) | W86: MITIGAR | X86: - | Y86: - | Z86: -
A87: 78-GTI | B87: FortiGate | C87: Consola de administracion 192.168.100.238 | D87: [HW] Equipamiento informático (hardware) | E87: [A.24] Denegación de servicio | F87: =+VLOOKUP(E87,'CATALOGO AMENAZA'!$B$2:$D$46,3,FALSE) | I87: X | J87: 3 | K87: 4 | L87: =+J87*K87 | M87: =+IF(L87<5,"BAJO",IF(L87<10,"MEDIO",IF(L87<17,"ALTO","CRITICO"))) | N87: Configuración segura de firewall | O87: PREVENTIVO | P87: Control Implementado sin evidencia de efectividad (Inefectivo prueba) | Q87: 0.3 | R87: Evidencia de validación de las configuraciones | S87: =+IF(O87="PREVENTIVO",J87*(1-Q87),IF(O87="ADMINISTRACION",J87*(1-Q87),IF(O87="ELIMINACION",J87*(1-Q87),J87))) | T87: =+IF(O87="DETECTIVO",K87*(1-Q87),IF(O87="RECUPERACION",K87*(1-Q87),K87)) | U87: =+S87*T87 | V87: =+IF(U87<5,"BAJO",IF(U87<10,"MEDIO",IF(U87<17,"ALTO","CRITICO"))) | W87: MITIGAR | X87: - | Y87: - | Z87: -
A88: 78-GTI | B88: FortiGate | C88: Consola de administracion 192.168.100.238 | D88: [HW] Equipamiento informático (hardware) | E88: [E.2] Errores del administrador | F88: =+VLOOKUP(E88,'CATALOGO AMENAZA'!$B$2:$D$46,3,FALSE) | G88: X | H88: X | I88: X | J88: 2 | K88: 3 | L88: =+J88*K88 | M88: =+IF(L88<5,"BAJO",IF(L88<10,"MEDIO",IF(L88<17,"ALTO","CRITICO"))) | N88: Control de cambios en los sistemas Verificación posterior (informe) | O88: ADMINISTRACION | P88: Control Implementado sin evidencia de efectividad (Inefectivo prueba) | Q88: 0.3 | R88: No existe procedimiento formal de gestión de cambios | S88: =+IF(O88="PREVENTIVO",J88*(1-Q88),IF(O88="ADMINISTRACION",J88*(1-Q88),IF(O88="ELIMINACION",J88*(1-Q88),J88))) | T88: =+IF(O88="DETECTIVO",K88*(1-Q88),IF(O88="RECUPERACION",K88*(1-Q88),K88)) | U88: =+S88*T88 | V88: =+IF(U88<5,"BAJO",IF(U88<10,"MEDIO",IF(U88<17,"ALTO","CRITICO"))) | W88: ACEPTABLE | X88: - | Y88: - | Z88: -
A89: 78-GTI | B89: FortiGate | C89: Consola de administracion 192.168.100.238 | D89: [HW] Equipamiento informático (hardware) | E89: [E.24] Caída del sistema por agotamiento de recursos | F89: =+VLOOKUP(E89,'CATALOGO AMENAZA'!$B$2:$D$46,3,FALSE) | I89: X | J89: 2 | K89: 4 | L89: =+J89*K89 | M89: =+IF(L89<5,"BAJO",IF(L89<10,"MEDIO",IF(L89<17,"ALTO","CRITICO"))) | N89: Procedimiento de Gestión de la capacidad y desempeño de la Infraestructura | O89: PREVENTIVO | P89: Control Implementado sin evidencia de efectividad (Inefectivo prueba) | Q89: 0.3 | R89: Notificación automática de alertas | S89: =+IF(O89="PREVENTIVO",J89*(1-Q89),IF(O89="ADMINISTRACION",J89*(1-Q89),IF(O89="ELIMINACION",J89*(1-Q89),J89))) | T89: =+IF(O89="DETECTIVO",K89*(1-Q89),IF(O89="RECUPERACION",K89*(1-Q89),K89)) | U89: =+S89*T89 | V89: =+IF(U89<5,"BAJO",IF(U89<10,"MEDIO",IF(U89<17,"ALTO","CRITICO"))) | W89: MITIGAR | X89: - | Y89: - | Z89: -
A90: 80-GTI | B90: Administrador de Seguridad Informática | C90: Funcionarios con el cargo de Administrador de Seguridad Informática | D90: [P] Personal | E90: [E.28] Indisponibilidad del personal | F90: =+VLOOKUP(E90,'CATALOGO AMENAZA'!$B$2:$D$46,3,FALSE) | I90: X | J90: 2 | K90: 3 | L90: =+J90*K90 | M90: =+IF(L90<5,"BAJO",IF(L90<10,"MEDIO",IF(L90<17,"ALTO","CRITICO"))) | N90: Plan de continuidad documentado | O90: RECUPERACION | P90: Control Implementado sin evidencia de efectividad (Inefectivo prueba) | Q90: 0.3 | R90: Dependencia de personal clave | S90: =+IF(O90="PREVENTIVO",J90*(1-Q90),IF(O90="ADMINISTRACION",J90*(1-Q90),IF(O90="ELIMINACION",J90*(1-Q90),J90))) | T90: =+IF(O90="DETECTIVO",K90*(1-Q90),IF(O90="RECUPERACION",K90*(1-Q90),K90)) | U90: =+S90*T90 | V90: =+IF(U90<5,"BAJO",IF(U90<10,"MEDIO",IF(U90<17,"ALTO","CRITICO"))) | W90: ACEPTABLE | X90: - | Y90: - | Z90: -
A91: 81-GTI | B91: Administrador de Base de Datos | C91: Funcionarios con el cargo de Administrador de Base de Datos | D91: [P] Personal | E91: [E.28] Indisponibilidad del personal | F91: =+VLOOKUP(E91,'CATALOGO AMENAZA'!$B$2:$D$46,3,FALSE) | I91: X | J91: 2 | K91: 3 | L91: =+J91*K91 | M91: =+IF(L91<5,"BAJO",IF(L91<10,"MEDIO",IF(L91<17,"ALTO","CRITICO"))) | N91: Plan de continuidad documentado | O91: RECUPERACION | P91: Control Implementado sin evidencia de efectividad (Inefectivo prueba) | Q91: 0.3 | R91: Dependencia de personal clave | S91: =+IF(O91="PREVENTIVO",J91*(1-Q91),IF(O91="ADMINISTRACION",J91*(1-Q91),IF(O91="ELIMINACION",J91*(1-Q91),J91))) | T91: =+IF(O91="DETECTIVO",K91*(1-Q91),IF(O91="RECUPERACION",K91*(1-Q91),K91)) | U91: =+S91*T91 | V91: =+IF(U91<5,"BAJO",IF(U91<10,"MEDIO",IF(U91<17,"ALTO","CRITICO"))) | W91: ACEPTABLE | X91: - | Y91: - | Z91: -
A92: 85-GTI | B92: Ruteador CISCO 1900 Series (02) | C92: Ruteador para enlaces de comunicación / 192.168.100.253 | D92: [HW] Equipamiento informático (hardware) | E92: [E.2] Errores del administrador | F92: =+VLOOKUP(E92,'CATALOGO AMENAZA'!$B$2:$D$46,3,FALSE) | G92: X | H92: X | I92: X | J92: 2 | K92: 3 | L92: =+J92*K92 | M92: =+IF(L92<5,"BAJO",IF(L92<10,"MEDIO",IF(L92<17,"ALTO","CRITICO"))) | N92: Control de cambios en los sistemas Verificación posterior (informe) | O92: ADMINISTRACION | P92: Control Implementado sin evidencia de efectividad (Inefectivo prueba) | Q92: 0.3 | R92: No existe procedimiento formal de gestión de cambios | S92: =+IF(O92="PREVENTIVO",J92*(1-Q92),IF(O92="ADMINISTRACION",J92*(1-Q92),IF(O92="ELIMINACION",J92*(1-Q92),J92))) | T92: =+IF(O92="DETECTIVO",K92*(1-Q92),IF(O92="RECUPERACION",K92*(1-Q92),K92)) | U92: =+S92*T92 | V92: =+IF(U92<5,"BAJO",IF(U92<10,"MEDIO",IF(U92<17,"ALTO","CRITICO"))) | W92: ACEPTABLE | X92: - | Y92: - | Z92: -
A93: 85-GTI | B93: Ruteador CISCO 1900 Series (02) | C93: Ruteador para enlaces de comunicación / 192.168.100.253 | D93: [HW] Equipamiento informático (hardware) | E93: [A.11] Acceso no autorizado | F93: =+VLOOKUP(E93,'CATALOGO AMENAZA'!$B$2:$D$46,3,FALSE) | G93: X | H93: X | J93: 3 | K93: 4 | L93: =+J93*K93 | M93: =+IF(L93<5,"BAJO",IF(L93<10,"MEDIO",IF(L93<17,"ALTO","CRITICO"))) | N93: Control de accesos / VPN | O93: PREVENTIVO | P93: Control Implementado sin evidencia de efectividad (Inefectivo prueba) | Q93: 0.3 | R93: Contreaseñas de VPN no expiran | S93: =+IF(O93="PREVENTIVO",J93*(1-Q93),IF(O93="ADMINISTRACION",J93*(1-Q93),IF(O93="ELIMINACION",J93*(1-Q93),J93))) | T93: =+IF(O93="DETECTIVO",K93*(1-Q93),IF(O93="RECUPERACION",K93*(1-Q93),K93)) | U93: =+S93*T93 | V93: =+IF(U93<5,"BAJO",IF(U93<10,"MEDIO",IF(U93<17,"ALTO","CRITICO"))) | W93: MITIGAR | X93: - | Y93: - | Z93: -
A94: 85-GTI | B94: Ruteador CISCO 1900 Series (02) | C94: Ruteador para enlaces de comunicación / 192.168.100.253 | D94: [HW] Equipamiento informático (hardware) | E94: [A.6] Abuso de privilegios de acceso | F94: =+VLOOKUP(E94,'CATALOGO AMENAZA'!$B$2:$D$46,3,FALSE) | G94: X | H94: X | I94: X | J94: 2 | K94: 4 | L94: =+J94*K94 | M94: =+IF(L94<5,"BAJO",IF(L94<10,"MEDIO",IF(L94<17,"ALTO","CRITICO"))) | N94: Registro de logs | O94: DETECTIVO | P94: Control Implementado sin evidencia de efectividad (Inefectivo prueba) | Q94: 0.3 | R94: Falta de revisión de perfiles de acceso | S94: =+IF(O94="PREVENTIVO",J94*(1-Q94),IF(O94="ADMINISTRACION",J94*(1-Q94),IF(O94="ELIMINACION",J94*(1-Q94),J94))) | T94: =+IF(O94="DETECTIVO",K94*(1-Q94),IF(O94="RECUPERACION",K94*(1-Q94),K94)) | U94: =+S94*T94 | V94: =+IF(U94<5,"BAJO",IF(U94<10,"MEDIO",IF(U94<17,"ALTO","CRITICO"))) | W94: MITIGAR | X94: - | Y94: - | Z94: -
A95: 85-GTI | B95: Ruteador CISCO 1900 Series (02) | C95: Ruteador para enlaces de comunicación / 192.168.100.253 | D95: [HW] Equipamiento informático (hardware) | E95: [E.23] Errores de mantenimiento / actualización de equipos (hardware) | F95: =+VLOOKUP(E95,'CATALOGO AMENAZA'!$B$2:$D$46,3,FALSE) | I95: X | J95: 3 | K95: 4 | L95: =+J95*K95 | M95: =+IF(L95<5,"BAJO",IF(L95<10,"MEDIO",IF(L95<17,"ALTO","CRITICO"))) | N95: Gestión de vulnerabilidades | O95: PREVENTIVO | P95: Control Implementado sin evidencia de efectividad (Inefectivo prueba) | Q95: 0.4 | R95: Recursos tecnológicos insuficientes para remediación | S95: =+IF(O95="PREVENTIVO",J95*(1-Q95),IF(O95="ADMINISTRACION",J95*(1-Q95),IF(O95="ELIMINACION",J95*(1-Q95),J95))) | T95: =+IF(O95="DETECTIVO",K95*(1-Q95),IF(O95="RECUPERACION",K95*(1-Q95),K95)) | U95: =+S95*T95 | V95: =+IF(U95<5,"BAJO",IF(U95<10,"MEDIO",IF(U95<17,"ALTO","CRITICO"))) | W95: MITIGAR | X95: - | Y95: - | Z95: -
A96: 86-GTI | B96: Ruteador CISCO 1900 Series (03) | C96: Ruteador para enlaces de comunicación / 192.168.40.253 | D96: [HW] Equipamiento informático (hardware) | E96: [E.2] Errores del administrador | F96: =+VLOOKUP(E96,'CATALOGO AMENAZA'!$B$2:$D$46,3,FALSE) | G96: X | H96: X | I96: X | J96: 2 | K96: 3 | L96: =+J96*K96 | M96: =+IF(L96<5,"BAJO",IF(L96<10,"MEDIO",IF(L96<17,"ALTO","CRITICO"))) | N96: Control de cambios en los sistemas Verificación posterior (informe) | O96: ADMINISTRACION | P96: Control Implementado sin evidencia de efectividad (Inefectivo prueba) | Q96: 0.3 | R96: No existe procedimiento formal de gestión de cambios | S96: =+IF(O96="PREVENTIVO",J96*(1-Q96),IF(O96="ADMINISTRACION",J96*(1-Q96),IF(O96="ELIMINACION",J96*(1-Q96),J96))) | T96: =+IF(O96="DETECTIVO",K96*(1-Q96),IF(O96="RECUPERACION",K96*(1-Q96),K96)) | U96: =+S96*T96 | V96: =+IF(U96<5,"BAJO",IF(U96<10,"MEDIO",IF(U96<17,"ALTO","CRITICO"))) | W96: ACEPTABLE | X96: - | Y96: - | Z96: -
A97: 86-GTI | B97: Ruteador CISCO 1900 Series (03) | C97: Ruteador para enlaces de comunicación / 192.168.40.253 | D97: [HW] Equipamiento informático (hardware) | E97: [A.11] Acceso no autorizado | F97: =+VLOOKUP(E97,'CATALOGO AMENAZA'!$B$2:$D$46,3,FALSE) | G97: X | H97: X | J97: 2 | K97: 4 | L97: =+J97*K97 | M97: =+IF(L97<5,"BAJO",IF(L97<10,"MEDIO",IF(L97<17,"ALTO","CRITICO"))) | N97: Control de accesos / VPN | O97: PREVENTIVO | P97: Control Implementado sin evidencia de efectividad (Inefectivo prueba) | Q97: 0.3 | R97: Contreaseñas de VPN no expiran | S97: =+IF(O97="PREVENTIVO",J97*(1-Q97),IF(O97="ADMINISTRACION",J97*(1-Q97),IF(O97="ELIMINACION",J97*(1-Q97),J97))) | T97: =+IF(O97="DETECTIVO",K97*(1-Q97),IF(O97="RECUPERACION",K97*(1-Q97),K97)) | U97: =+S97*T97 | V97: =+IF(U97<5,"BAJO",IF(U97<10,"MEDIO",IF(U97<17,"ALTO","CRITICO"))) | W97: MITIGAR | X97: - | Y97: - | Z97: -
A98: 86-GTI | B98: Ruteador CISCO 1900 Series (03) | C98: Ruteador para enlaces de comunicación / 192.168.40.253 | D98: [HW] Equipamiento informático (hardware) | E98: [A.6] Abuso de privilegios de acceso | F98: =+VLOOKUP(E98,'CATALOGO AMENAZA'!$B$2:$D$46,3,FALSE) | G98: X | H98: X | I98: X | J98: 2 | K98: 4 | L98: =+J98*K98 | M98: =+IF(L98<5,"BAJO",IF(L98<10,"MEDIO",IF(L98<17,"ALTO","CRITICO"))) | N98: Registro de logs | O98: DETECTIVO | P98: Control Implementado sin evidencia de efectividad (Inefectivo prueba) | Q98: 0.3 | R98: Falta de revisión de perfiles de acceso | S98: =+IF(O98="PREVENTIVO",J98*(1-Q98),IF(O98="ADMINISTRACION",J98*(1-Q98),IF(O98="ELIMINACION",J98*(1-Q98),J98))) | T98: =+IF(O98="DETECTIVO",K98*(1-Q98),IF(O98="RECUPERACION",K98*(1-Q98),K98)) | U98: =+S98*T98 | V98: =+IF(U98<5,"BAJO",IF(U98<10,"MEDIO",IF(U98<17,"ALTO","CRITICO"))) | W98: MITIGAR | X98: - | Y98: - | Z98: -
A99: 86-GTI | B99: Ruteador CISCO 1900 Series (03) | C99: Ruteador para enlaces de comunicación / 192.168.40.253 | D99: [HW] Equipamiento informático (hardware) | E99: [E.23] Errores de mantenimiento / actualización de equipos (hardware) | F99: =+VLOOKUP(E99,'CATALOGO AMENAZA'!$B$2:$D$46,3,FALSE) | I99: X | J99: 3 | K99: 3 | L99: =+J99*K99 | M99: =+IF(L99<5,"BAJO",IF(L99<10,"MEDIO",IF(L99<17,"ALTO","CRITICO"))) | N99: Gestión de vulnerabilidades | O99: PREVENTIVO | P99: Control Implementado sin evidencia de efectividad (Inefectivo prueba) | Q99: 0.4 | R99: Recursos tecnológicos insuficientes para remediación | S99: =+IF(O99="PREVENTIVO",J99*(1-Q99),IF(O99="ADMINISTRACION",J99*(1-Q99),IF(O99="ELIMINACION",J99*(1-Q99),J99))) | T99: =+IF(O99="DETECTIVO",K99*(1-Q99),IF(O99="RECUPERACION",K99*(1-Q99),K99)) | U99: =+S99*T99 | V99: =+IF(U99<5,"BAJO",IF(U99<10,"MEDIO",IF(U99<17,"ALTO","CRITICO"))) | W99: MITIGAR | X99: - | Y99: - | Z99: -
A100: 87-GTI | B100: Ruteador CISCO 1900 Series (04) | C100: Ruteador para enlaces de comunicación / 192.168.50.253 | D100: [HW] Equipamiento informático (hardware) | E100: [E.2] Errores del administrador | F100: =+VLOOKUP(E100,'CATALOGO AMENAZA'!$B$2:$D$46,3,FALSE) | G100: X | H100: X | I100: X | J100: 2 | K100: 3 | L100: =+J100*K100 | M100: =+IF(L100<5,"BAJO",IF(L100<10,"MEDIO",IF(L100<17,"ALTO","CRITICO"))) | N100: Control de cambios en los sistemas Verificación posterior (informe) | O100: ADMINISTRACION | P100: Control Implementado sin evidencia de efectividad (Inefectivo prueba) | Q100: 0.3 | R100: No existe procedimiento formal de gestión de cambios | S100: =+IF(O100="PREVENTIVO",J100*(1-Q100),IF(O100="ADMINISTRACION",J100*(1-Q100),IF(O100="ELIMINACION",J100*(1-Q100),J100))) | T100: =+IF(O100="DETECTIVO",K100*(1-Q100),IF(O100="RECUPERACION",K100*(1-Q100),K100)) | U100: =+S100*T100 | V100: =+IF(U100<5,"BAJO",IF(U100<10,"MEDIO",IF(U100<17,"ALTO","CRITICO"))) | W100: ACEPTABLE | X100: - | Y100: - | Z100: -
A101: 87-GTI | B101: Ruteador CISCO 1900 Series (04) | C101: Ruteador para enlaces de comunicación / 192.168.50.253 | D101: [HW] Equipamiento informático (hardware) | E101: [A.11] Acceso no autorizado | F101: =+VLOOKUP(E101,'CATALOGO AMENAZA'!$B$2:$D$46,3,FALSE) | G101: X | H101: X | J101: 2 | K101: 4 | L101: =+J101*K101 | M101: =+IF(L101<5,"BAJO",IF(L101<10,"MEDIO",IF(L101<17,"ALTO","CRITICO"))) | N101: Control de accesos / VPN | O101: PREVENTIVO | P101: Control Implementado sin evidencia de efectividad (Inefectivo prueba) | Q101: 0.3 | R101: Contreaseñas de VPN no expiran | S101: =+IF(O101="PREVENTIVO",J101*(1-Q101),IF(O101="ADMINISTRACION",J101*(1-Q101),IF(O101="ELIMINACION",J101*(1-Q101),J101))) | T101: =+IF(O101="DETECTIVO",K101*(1-Q101),IF(O101="RECUPERACION",K101*(1-Q101),K101)) | U101: =+S101*T101 | V101: =+IF(U101<5,"BAJO",IF(U101<10,"MEDIO",IF(U101<17,"ALTO","CRITICO"))) | W101: MITIGAR | X101: - | Y101: - | Z101: -
...

Sheet PLANES DE ACCION
A1: PLAN DE ACCION | B1: DESCIPCION PLAN DE ACCIÓN | C1: RESPONSABLE | D1: PLAZO
A2: PA-SI-001 | B2: Identificar una herramienta que permitan realizar un análisis de LOGS | C2: JEFE DE SEGURIDAD DE LA INFORMACION | D2: 8 MESES
A3: PA-SI-002 | B3: Fortalecer mecanismos de protección contra ataques DoS/DDoS | C3: JEFE DE SEGURIDAD DE LA INFORMACION | D3: 3 MESES
A4: PA-SI-003 | B4: Determinar accesos restringidos para la consola administrativa | C4: JEFE DE SEGURIDAD DE LA INFORMACION | D4: 3 MESES
A5: PA-SI-004 | B5: Aplicar política de expiración de contraseñas VPN. | C5: JEFE DE SEGURIDAD DE LA INFORMACION | D5: 6 MESES
A6: PA-SI-005 | B6: Fortalecer el monitoreo proactivo de recursos (CPU, RAM, almacenamiento). | C6: JEFE DE SEGURIDAD DE LA INFORMACION | D6: 6 MESES
A7: PA-SI-006 | B7: Fortalecer las políticas de prevención de fuga de información (DLP) para mejorar la protección de datos sensibles. | C7: JEFE DE SEGURIDAD DE LA INFORMACION | D7: 8 MESES

Sheet INDICADORES
A1: Etiquetas de fila | B1: Cuenta de CRITICIDAD
A2: ALTA | B2: 68
A3: BAJA | B3: 639
A4: MEDIA | B4: 697
A5: Total general | B5: 1404
A9: EVENTO DE AMENAZA | B9: (Todas)
A11: TIPO DE ACTIVO MAGGERIT | B11: Cuenta de EVENTO DE AMENAZA
A12: [D] Datos / Información / datos de configuración | B12: 59
A13: [HW] Equipamiento informático (hardware) | B13: 103
A14: [Media] Soportes de información | B14: 4
A15: [P] Personal | B15: 4
A16: [S] Servicios | B16: 10
A17: [SW] Software - Aplicaciones informáticas | B17: 29
A18: Total general | B18: 209
A22: Cuenta de EVENTO DE AMENAZA | B22: Etiquetas de columna
A23: NIVELES DE RIESGO HINNERENTE | B23: ALTO | C23: BAJO | D23: CRITICO | E23: MEDIO | F23: Total general
A24: [D] Datos / Información / datos de configuración | B24: 7 | C24: 11 | E24: 41 | F24: 59
A25: [HW] Equipamiento informático (hardware) | B25: 21 | C25: 3 | D25: 1 | E25: 78 | F25: 103
A26: [Media] Soportes de información | C26: 1 | E26: 3 | F26: 4
A27: [P] Personal | E27: 4 | F27: 4
A28: [S] Servicios | B28: 1 | E28: 9 | F28: 10
A29: [SW] Software - Aplicaciones informáticas | B29: 4 | C29: 10 | D29: 2 | E29: 13 | F29: 29
A30: Total general | B30: 33 | C30: 25 | D30: 3 | E30: 148 | F30: 209
A32: NIVELES DE RIESGO HINNERENTE | B32: Cuenta de DETERMINACION RIESGO ACUMULADO O INHERENTE
A33: ALTO | B33: 33
A34: BAJO | B34: 25
A35: CRITICO | B35: 3
A36: MEDIO | B36: 148
A37: Total general | B37: 209
A42: Cuenta de EVENTO DE AMENAZA | B42: Etiquetas de columna
A43: NIVELES DE RIESGO RESIDUAL | B43: ALTO | C43: BAJO | D43: MEDIO | E43: Total general
A44: [D] Datos / Información / datos de configuración | B44: 1 | C44: 34 | D44: 24 | E44: 59
A45: [HW] Equipamiento informático (hardware) | B45: 7 | C45: 28 | D45: 68 | E45: 103
A46: [Media] Soportes de información | C46: 1 | D46: 3 | E46: 4
A47: [P] Personal | C47: 4 | E47: 4
A48: [S] Servicios | C48: 5 | D48: 5 | E48: 10
A49: [SW] Software - Aplicaciones informáticas | B49: 1 | C49: 17 | D49: 11 | E49: 29
A50: Total general | B50: 9 | C50: 89 | D50: 111 | E50: 209
A52: NIVELES DE RIESGO HINNERENTE | B52: Cuenta de DETERMINACION RIESGO RESIDUAL
A53: ALTO | B53: 9
A54: BAJO | B54: 89
A55: MEDIO | B55: 111
A56: Total general | B56: 209
A60: Efectividad de los controles | B60: Número de controles
A61: 0.3 | B61: 186
A62: Control Implementado sin evidencia de efectividad (Inefectivo prueba) | B62: 186
A63: 0.4 | B63: 20
A64: Control Implementado sin evidencia de efectividad (Inefectivo prueba) | B64: 20
A65: 0.8 | B65: 3
A66: Control implementado formalizado y probado | B66: 2
A67: Control Implementado sin evidencia de efectividad (Inefectivo prueba) | B67: 1
A68: Total general | B68: 209

Sheet CATALOGO VULNERABILIDADES
A2: Código | B2: Descripción
A3: V1 | B3: Implementación ineficaz de políticas de seguridad de la información
A4: V2 | B4: Documentos y archivos sin cifrar
A5: V3 | B5: Componentes vulnerables y fuera de soporte
A6: V4 | B6: Diseño inseguro del sistema
A7: V5 | B7: Fallos criptográficos
A8: V6 | B8: Ausencia de componentes de respaldo
A9: V7 | B9: Configuración incorrecta de software o hardware
A10: V8 | B10: Falta de prácticas de seguridad de la información
A11: V9 | B11: Software no actualizado con parches de seguridad
A12: V10 | B12: Controles de acceso mal implementados
A13: V11 | B13: Uso de contraseñas débiles o compartidas
... A52: V50 | B52: Dependiencia de un solo usuario/empleado administrador

Sheet CATALOGO AMENAZA
E1: TIPOS DE ACTIVOS
A2: TIPOS DE AMENAZA | B2: AMENAZA | C2: DESCRIPCION | D2: DIMENSIONES | E2: [D] Datos / Información / datos de configuración | F2: [K] Claves criptográficas | G2: [S] Servicios | H2: [SW] Software - Aplicaciones informáticas | I2: [HW] Equipamiento informático (hardware) | J2: [COM] Redes de comunicaciones | K2: [Media] Soportes de información | L2: [AUX] equipamiento auxiliar | M2: [L] Instalaciones | N2: [P] Personal
A3: [N] Desastres naturales | B3: [N.1] Fuego | C3: incendios: posibilidad de que el fuego acabe con recursos del sistema. | D3: [D] disponibilidad | I3: X | K3: X | L3: X | M3: X
A4: [N] Desastres naturales | B4: [N.2] Daños por agua | C4: inundaciones: posibilidad de que el agua acabe con recursos del sistema. | D4: [D] disponibilidad | I4: X | K4: X | L4: X | M4: X
A5: [N] Desastres naturales | B5: [N.*] Desastres naturales | C5: otros incidentes que se producen sin intervención humana: rayo, tormenta eléctrica, terremoto, ciclones, avalancha, corrimiento de tierras, ... Se excluyen desastres específicos tales como incendios (ver [N.1]) e inundaciones (ver [N.2]). Se excluye al personal por cuanto se ha previsto una amenaza específica [E.31] para cubrir la indisponibilidad involuntaria del personal sin entrar en sus causas. | D5: [D] disponibilidad | I5: X | K5: X | L5: X | M5: X
A6: [E] Errores y fallos no intencionados | B6: [E.1] Errores de los usuarios | C6: equivocaciones de las personas cuando usan los servicios, datos, etc. | D6: [I] integridad [C] confidencialidad [D] disponibilidad | E6: X | F6: X | G6: X | H6: X | K6: X
A7: [E] Errores y fallos no intencionados | B7: [E.2] Errores del administrador | C7: equivocaciones de personas con responsabilidades de instalación y operación | D7: [I] integridad [C] confidencialidad [D] disponibilidad | E7: X | F7: X | G7: X | H7: X | I7: X | J7: X | K7: X
A8: [E] Errores y fallos no intencionados | B8: [E.3] Errores de monitorización (log) | C8: inadecuado registro de actividades: falta de registros, registros incompletos, registros incorrectamente fechados, registros incorrectamente atribuidos, … | D8: [I] integridad (trazabilidad) | E8: X
A9: [E] Errores y fallos no intencionados | B9: [E.4] Errores de configuración | C9: introducción de datos de configuración erróneos. Prácticamente todos los activos dependen de su configuración y ésta de la diligencia del administrador: privilegios de acceso, flujos de actividades, registro de actividad, encaminamiento, etc. | D9: [I] integridad | E9: X
A10: [E] Errores y fallos no intencionados | B10: [E.7] Deficiencias en la organización | C10: cuando no está claro quién tiene que hacer exactamente qué y cuándo, incluyendo tomar medidas sobre los activos o informar a la jerarquía de gestión. Acciones descoordinadas, errores por omisión, etc. | D10: [D] disponibilidad | N10: X
A11: [E] Errores y fallos no intencionados | B11: [E.8] Difusión de software dañino | C11: propagación inocente de virus, espías (spyware), gusanos, troyanos, bombas lógicas, etc. | D11: [I] integridad [C] confidencialidad [D] disponibilidad | H11: X
A12: [E] Errores y fallos no intencionados | B12: [E.9] Errores de [re-]encaminamiento | C12: envío de información a través de un sistema o una red usando, accidentalmente, una ruta incorrecta que lleve la información a donde o por donde no es debido; puede tratarse de mensajes entre personas, entre procesos o entre unos y otros. Es particularmente destacable el caso de que el error de encaminamiento suponga un error de entrega, acabando la información en manos de quien no se espera. | D12: [C] confidencialidad | G12: X | H12: X | J12: X
A13: [E] Errores y fallos no intencionados | B13: [E.10] Errores de secuencia | C13: alteración accidental del orden de los mensajes transmitidos. | D13: [I] integridad | G13: X | H13: X | J13: X
A14: [E] Errores y fallos no intencionados | B14: [E.15] Alteración accidental de la información | C14: alteración accidental de la información. Esta amenaza sólo se identifica sobre datos en general, pues cuando la información está en algún soporte informático, hay amenazas específicas. | D14: [I] integridad | E14: X | F14: X | G14: X | H14: X | J14: X | K14: X | M14: X
A15: [E] Errores y fallos no intencionados | B15: [E.18] Destrucción de información | C15: pérdida accidental de información. Esta amenaza sólo se identifica sobre datos en general, pues cuando la información está en algún soporte informático, hay amenazas específicas. | D15: [D] disponibilidad | E15: X | F15: X | G15: X | H15: X | J15: X | K15: X | M15: X
A16: [E] Errores y fallos no intencionados | B16: [E.19] Fugas de información | C16: revelación por indiscreción. Incontinencia verbal, medios electrónicos, soporte papel, etc. | D16: [C] confidencialidad | E16: X | F16: X | G16: X | H16: X | J16: X | K16: X | M16: X | N16: X
A17: [E] Errores y fallos no intencionados | B17: [E.20] Vulnerabilidades de los programas (software) | C17: defectos en el código que dan pie a una operación defectuosa sin intención por parte del usuario pero con consecuencias sobre la integridad de los datos o la capacidad misma de operar. | D17: [I] integridad [C] confidencialidad [D] disponibilidad | H17: X
A18: [E] Errores y fallos no intencionados | B18: [E.21] Errores de mantenimiento / actualización de programas (software) | C18: defectos en los procedimientos o controles de actualización del código que permiten que sigan utilizándose programas con defectos conocidos y reparados por el fabricante. | D18: [I] integridad [D] disponibilidad | H18: X
A19: [E] Errores y fallos no intencionados | B19: [E.23] Errores de mantenimiento / actualización de equipos (hardware) | C19: defectos en los procedimientos o controles de actualización de los equipos que permiten que sigan utilizándose más allá del tiempo nominal de uso. | D19: [D] disponibilidad | I19: X | K19: X | L19: X
A20: [E] Errores y fallos no intencionados | B20: [E.24] Caída del sistema por agotamiento de recursos | C20: la carencia de recursos suficientes provoca la caída del sistema cuando la carga de trabajo es desmesurada. | D20: [D] disponibilidad | G20: X | I20: X | J20: X
A21: [E] Errores y fallos no intencionados | B21: [E.25] Pérdida de equipos | C21: la pérdida de equipos provoca directamente la carencia de un medio para prestar los servicios, es decir una indisponibilidad. Se puede perder todo tipo de equipamiento, siendo la pérdida de equipos y soportes de información los más habituales. En el caso de equipos que hospedan datos, además se puede sufrir una fuga de información. | D21: [C] confidencialidad [D] disponibilidad | I21: X | K21: X | L21: X
A22: [E] Errores y fallos no intencionados | B22: [E.28] Indisponibilidad del personal | C22: ausencia accidental del puesto de trabajo: enfermedad, alteraciones del orden público, guerra bacteriológica, … | D22: [D] disponibilidad | N22: X
A23: [A] Ataques intencionados | B23: [A.3] Manipulación de los registros de actividad (log) | D23: [I] integridad (trazabilidad) | E23: X
A24: [A] Ataques intencionados | B24: [A.4] Manipulación de la configuración | C24: prácticamente todos los activos dependen de su configuración y ésta de la diligencia del administrador: privilegios de acceso, flujos de actividades, registro de actividad, encaminamiento, etc. | D24: [I] integridad [C] confidencialidad [A] Autenticidad | E24: X
A25: [A] Ataques intencionados | B25: [A.5] Suplantación de la identidad del usuario | C25: cuando un atacante consigue hacerse pasar por un usuario autorizado, disfruta de los privilegios de este para sus fines propios. Esta amenaza puede ser perpetrada por personal interno, por personas ajenas a la Organización o por personal contratado temporalmente. | D25: [I] integridad [C] confidencialidad [A] Autenticidad | E25: X | F25: X | G25: X | H25: X | J25: X
A26: [A] Ataques intencionados | B26: [A.6] Abuso de privilegios de acceso | C26: cada usuario disfruta de un nivel de privilegios para un determinado propósito; cuando un usuario abusa de su nivel de privilegios para realizar tareas que no son de su competencia, hay problemas. | D26: [I] integridad [C] confidencialidad [D] disponibilidad | E26: X | F26: X | G26: X | H26: X | I26: X | J26: X
A27: [A] Ataques intencionados | B27: [A.7] Uso no previsto | C27: utilización de los recursos del sistema para fines no previstos, típicamente de interés personal: juegos, consultas personales en Internet, bases de datos personales, programas personales, almacenamiento de datos personales, etc. | D27: [I] integridad [C] confidencialidad [D] disponibilidad | E27: X | H27: X | I27: X | J27: X | K27: X | L27: X | M27: X
A28: [A] Ataques intencionados | B28: [A.8] Difusión de software dañino | C28: propagación intencionada de virus, espías (spyware), gusanos, troyanos, bombas lógicas, etc. | D28: [I] integridad [C] confidencialidad [D] disponibilidad | H28: X
A29: [A] Ataques intencionados | B29: [A.9] [Re-]encaminamiento de mensajes | C29: envío de información a un destino incorrecto a través de un sistema o una red, que llevan la información a donde o por donde no es debido; puede tratarse de mensajes entre personas, entre procesos o entre unos y otros. Un atacante puede forzar un mensaje para circular a través de un nodo determinado de la red donde puede ser interceptado. Es particularmente destacable el caso de que el ataque de encaminamiento lleve a una entrega fraudulenta, acabando la información en manos de quien no debe. | D29: [C] confidencialidad | G29: X | H29: X | J29: X
A30: [A] Ataques intencionados | B30: [A.10] Alteración de secuencia | C30: alteración del orden de los mensajes transmitidos. Con ánimo de que el nuevo orden altere el significado del conjunto de mensajes, perjudicando a la integridad de los datos afectados. | D30: [I] integridad (trazabilidad) | G30: X | H30: X | J30: X
A31: [A] Ataques intencionados | B31: [A.11] Acceso no autorizado | C31: el atacante consigue acceder a los recursos del sistema sin tener autorización para ello, típicamente aprovechando un fallo del sistema de identificación y autorización. | D31: [I] integridad [C] confidencialidad | E31: X | F31: X | G31: X | H31: X | I31: X | J31: X | K31: X | L31: X | M31: X
A32: [A] Ataques intencionados | B32: [A.12] Análisis de tráfico | C32: el atacante, sin necesidad de entrar a analizar el contenido de las comunicaciones, es capaz de extraer conclusiones a partir del análisis del origen, destino, volumen y frecuencia de los intercambios. A veces se denomina “monitorización de tráfico”. | D32: [C] confidencialidad | J32: X
A33: [A] Ataques intencionados | B33: [A.13] Repudio | C33: negación a posteriori de actuaciones o compromisos adquiridos en el pasado. Repudio de origen: negación de ser el remitente u origen de un mensaje o comunicación. Repudio de recepción: negación de haber recibido un mensaje o comunicación. Repudio de entrega: negación de haber recibido un mensaje para su entrega a otro. | D33: [I] integridad (trazabilidad) | E33: X | G33: X
A34: [A] Ataques intencionados | B34: [A.14] Interceptación de información (escucha) | C34: el atacante llega a tener acceso a información que no le corresponde, sin que la información en sí misma se vea alterada. | D34: [C] confidencialidad | J34: X
A35: [A] Ataques intencionados | B35: [A.15] Modificación deliberada de la información | C35: alteración intencional de la información, con ánimo de obtener un beneficio o causar un perjuicio. | D35: [I] integridad | E35: X | F35: X | G35: X | H35: X | J35: X | K35: X | M35: X
A36: [A] Ataques intencionados | B36: [A.18] Destrucción de información | C36: eliminación intencional de información, con ánimo de obtener un beneficio o causar un perjuicio. | D36: [D] disponibilidad | E36: X | F36: X | G36: X | H36: X | K36: X | M36: X
A37: [A] Ataques intencionados | B37: [A.19] Divulgación de información | C37: revelación de información. | D37: [C] confidencialidad | E37: X | F37: X | G37: X | H37: X | J37: X | K37: X | M37: X
A38: [A] Ataques intencionados | B38: [A.22] Manipulación de programas | C38: alteración intencionada del funcionamiento de los programas, persiguiendo un beneficio indirecto cuando una persona autorizada lo utiliza. | D38: [I] integridad [C] confidencialidad [D] disponibilidad | H38: X
A39: [A] Ataques intencionados | B39: [A.23] Manipulación de los equipos | C39: alteración intencionada del funcionamiento de los programas, persiguiendo un beneficio indirecto cuando una persona autorizada lo utiliza. | D39: [C] confidencialidad [D] disponibilidad | I39: X | K39: X | L39: X
A40: [A] Ataques intencionados | B40: [A.24] Denegación de servicio | C40: la carencia de recursos suficientes provoca la caída del sistema cuando la carga de trabajo es desmesurada. | D40: [D] disponibilidad | G40: X | I40: X | J40: X
A41: [A] Ataques intencionados | B41: [A.25] Robo | C41: la sustracción de equipamiento provoca directamente la carencia de un medio para prestar los servicios, es decir una indisponibilidad. El robo puede afectar a todo tipo de equipamiento, siendo el robo de equipos y el robo de soportes de información los más habituales. El robo puede realizarlo personal interno, personas ajenas a la Organización o personas contratadas de forma temporal, lo que establece diferentes grados de facilidad para acceder al objeto sustraído y diferentes consecuencias. En el caso de equipos que hospedan datos, además se puede sufrir una fuga de información. | D41: [C] confidencialidad [D] disponibilidad | H41: X | K41: X | L41: X
A42: [A] Ataques intencionados | B42: [A.26] Ataque destructivo | C42: vandalismo, terrorismo, acción militar, ... Esta amenaza puede ser perpetrada por personal interno, por personas ajenas a la Organización o por personas contratadas de forma temporal. | D42: [D] disponibilidad | I42: X | K42: X | L42: X | M42: X
A43: [A] Ataques intencionados | B43: [A.27] Ocupación enemiga | C43: cuando los locales han sido invadidos y se carece de control sobre los propios medios de trabajo. | D43: [C] confidencialidad [D] disponibilidad | M43: X
A44: [A] Ataques intencionados | B44: [A.28] Indisponibilidad del personal | C44: ausencia deliberada del puesto de trabajo: como huelgas, absentismo laboral, bajas no justificadas, bloqueo de los accesos, … | D44: [D] disponibilidad | N44: X
A45: [A] Ataques intencionados | B45: [A.29] Extorsión | C45: presión que, mediante amenazas, se ejerce sobre alguien para obligarle a obrar en determinado sentido. | D45: [I] integridad [C] confidencialidad [D] disponibilidad | N45: X
A46: [A] Ataques intencionados | B46: [A.30] Ingeniería social (picaresca) | C46: abuso de la buena fe de las personas para que realicen actividades que interesan a un tercero. | D46: [I] integridad [C] confidencialidad [D] disponibilidad | N46: X

Sheet TIPOS DE ACTIVOS
A1: TIPO DE ACTIVO | B1: DESCRIPCION
A2: [D] Datos / Información / datos de configuración | B2: Los datos son el corazón que permite a una organización prestar sus servicios. La información es un activo abstracto que será almacenado en equipos o soportes de información (normalmente agrupado como ficheros o bases de datos) o será transferido de un lugar a otro por los medios de transmisión de datos.
A3: [K] Claves criptográficas | B3: Las criptografía se emplea para proteger el secreto o autenticar a las partes. Las claves criptográficas, combinando secretos e información pública, son esenciales para garantizar el funcionamiento de los mecanismos criptográficos.
A4: [S] Servicios | B4: Función que satisface una necesidad de los usuarios (del servicio). Esta sección contempla servicios prestados por el sistema.
A5: [SW] Software - Aplicaciones informáticas | B5: Con múltiples denominaciones (programas, aplicativos, desarrollos, etc.) este epígrafe se refiere a tareas que han sido automatizadas para su desempeño por un equipo informático. Las aplicaciones gestionan, analizan y transforman los datos permitiendo la explotación de la información para la prestación de los servicios.
A6: [HW] Equipamiento informático (hardware) | B6: Dícese de los medios materiales, físicos, destinados a soportar directa o indirectamente los servicios que presta la organización, siendo pues depositarios temporales o permanentes de los datos, soporte de ejecución de las aplicaciones informáticas o responsables del procesado o la transmisión de datos.
A7: [COM] Redes de comunicaciones | B7: Incluyendo tanto instalaciones dedicadas como servicios de comunicaciones contratados a terceros; pero siempre centrándose en que son medios de transporte que llevan datos de un sitio a otro.
A8: [Media] Soportes de información | B8: En este epígrafe se consideran dispositivos físicos que permiten almacenar información de forma permanente o, al menos, durante largos periodos de tiempo.
A9: [AUX] equipamiento auxiliar | B9: En este epígrafe se consideran otros equipos que sirven de soporte a los sistemas de información, sin estar directamente relacionados con datos.
A10: [L] Instalaciones | B10: En este epígrafe entran los lugares donde se hospedan los sistemas de información y comunicaciones.
A11: [P] Personal | B11: En este epígrafe aparecen las personas relacionadas con los sistemas de información.

Sheet CATALOGO CONTROLES
A1: CONTROLES IMPLEMENTADOS
A2: Código | B2: Descripción
A3: 1. Política de Seguridad de la Información | C3: 1. Política de Seguridad de la Información-
A4: C1 | B4: Revisión periódica de las políticas y procedimientos TI | C4: C1- Revisión periódica de las políticas y procedimientos TI
A5: C2 | B5: Evaluación de riesgos de seguridad de la información documentada y actualizada | C5: C2- Evaluación de riesgos de seguridad de la información documentada y actualizada
A6: C3 | B6: Auditorías internas y externas de seguridad de la información | C6: C3- Auditorías internas y externas de seguridad de la información
A7: C4 | B7: Control de acceso basado en roles (RBAC) y necesidad funcional | C7: C4- Control de acceso basado en roles (RBAC) y necesidad funcional
A8: 2. Organización de la Seguridad de la Información | C8: 2. Organización de la Seguridad de la Información-
A9: C5 | B9: Acuerdos de confidencialidad | C9: C5- Acuerdos de confidencialidad
A10: C6 | B10: Clasificación de la información (público, uso interno, restringido) | C10: C6- Clasificación de la información (público, uso interno, restringido)
A11: C7 | B11: Control de cambios en sistemas, aplicaciones y configuraciones | C11: C7- Control de cambios en sistemas, aplicaciones y configuraciones
A12: 3. Gestión de Activos | C12: 3. Gestión de Activos-
A13: C8 | B13: Mantenimiento periódico de activos físicos | C13: C8- Mantenimiento periódico de activos físicos
A14: C9 | B14: Gestión segura del ciclo de vida de los activos | C14: C9- Gestión segura del ciclo de vida de los activos
A15: C10 | B15: Registro de actividades críticas de usuarios con privilegios | C15: C10- Registro de actividades críticas de usuarios con privilegios
A16: 4. Seguridad de los Recursos Humanos | C16: 4. Seguridad de los Recursos Humanos-
A17: C11 | B17: Programas de concienciación, educación y capacitación en seguridad de la información y otros | C17: C11- Programas de concienciación, educación y capacitación en seguridad de la información y otros
A18: C12 | B18: Evaluación de seguridad a proveedores y contratos con cláusulas de seguridad | C18: C12- Evaluación de seguridad a proveedores y contratos con cláusulas de seguridad
A19: 5. Control de Acceso | C19: 5. Control de Acceso-
A20: C13 | B20: Restricción del control de acceso | C20: C13- Restricción del control de acceso
A21: C14 | B21: Revisión periódica de los derechos de acceso | C21: C14- Revisión periódica de los derechos de acceso
A22: C15 | B22: Uso de contraseñas fuertes de acuerdo con las recomendaciones de buenas prácticas | C22: C15- Uso de contraseñas fuertes de acuerdo con las recomendaciones de buenas prácticas
A23: C16 | B23: Implementación del principio de mínimos privilegios | C23: C16- Implementación del principio de mínimos privilegios
A24: C17 | B24: Registro de fallos en el control de acceso | C24: C17- Registro de fallos en el control de acceso
A25: C18 | B25: Control de acceso basado en roles (RBAC) y necesidad funcional | C25: C18- Control de acceso basado en roles (RBAC) y necesidad funcional
A26: 6. Criptografía | C26: 6. Criptografía-
A27: C19 | B27: Cifrado de datos sensibles en tránsito y en reposo | C27: C19- Cifrado de datos sensibles en tránsito y en reposo
A28: C20 | B28: Aseguramiento de canales de comunicación (uso de VPN, cifrado TLS) | C28: C20- Aseguramiento de canales de comunicación (uso de VPN, cifrado TLS)
A29: 7. Seguridad Física y del Entorno | C29: 7. Seguridad Física y del Entorno-
A30: C21 | B30: Mantenimiento periódico de activos físicos | C30: C21- Mantenimiento periódico de activos físicos
A31: C22 | B31: Aplicación de actualizaciones de firmware en hardware y dispositivos de red | C31: C22- Aplicación de actualizaciones de firmware en hardware y dispositivos de red
A32: 8. Seguridad de las Operaciones | C32: 8. Seguridad de las Operaciones-
A33: C23 | B33: Procedimientos de reversión (rollback) | C33: C23- Procedimientos de reversión (rollback)
A34: C24 | B34: Monitoreo y control | C34: C24- Monitoreo y control
A35: C25 | B35: Respaldo periódico de información crítica y verificación de restauración | C35: C25- Respaldo periódico de información crítica y verificación de restauración
A36: C26 | B36: Uso de soluciones antivirus y antimalware actualizadas | C36: C26- Uso de soluciones antivirus y antimalware actualizadas
A37: C27 | B37: Gestión de vulnerabilidades (escaneo periódico y remediación) | C37: C27- Gestión de vulnerabilidades (escaneo periódico y remediación)
A38: C28 | B38: Control de dispositivos externos (USB, almacenamiento removible) | C38: C28- Control de dispositivos externos (USB, almacenamiento removible)
A39: C29 | B39: Revisión de logs y alertas de seguridad periódicamente | C39: C29- Revisión de logs y alertas de seguridad periódicamente
A40: 9. Seguridad en las Comunicaciones | C40: 9. Seguridad en las Comunicaciones-
A41: C30 | B41: Aseguramiento de canales de comunicación (uso de VPN, cifrado TLS) | C41: C30- Aseguramiento de canales de comunicación (uso de VPN, cifrado TLS)
A42: C31 | B42: Monitoreo y control | C42: C31- Monitoreo y control
A43: 10. Adquisición, desarrollo y mantenimiento | C43: 10. Adquisición, desarrollo y mantenimiento-
A44: C32 | B44: Aplicación de actualizaciones o firmware periódicos | C44: C32- Aplicación de actualizaciones o firmware periódicos
A45: C33 | B45: Detección y respuesta ante incidentes de seguridad (plan de respuesta) | C45: C33- Detección y respuesta ante incidentes de seguridad (plan de respuesta)
A46: C34 | B46: Control de cambios en sistemas, aplicaciones y configuraciones | C46: C34- Control de cambios en sistemas, aplicaciones y configuraciones
A47: C35 | B47: Revisión y pruebas de continuidad del negocio y recuperación ante desastres | C47: C35- Revisión y pruebas de continuidad del negocio y recuperación ante desastres
A48: 11. Relaciones con Proveedores | C48: 11. Relaciones con Proveedores-
A49: C36 | B49: Evaluación de seguridad a proveedores y contratos con cláusulas de seguridad | C49: C36- Evaluación de seguridad a proveedores y contratos con cláusulas de seguridad
A50: C37 | B50: Principio de mínimo privilegio (en contratos de tercerización de servicios) | C50: C37- Principio de mínimo privilegio (en contratos de tercerización de servicios)
A51: 12. Gestión de Incidentes de Seguridad | C51: 12. Gestión de Incidentes de Seguridad-
A52: C38 | B52: Detección y respuesta ante incidentes de seguridad | C52: C38- Detección y respuesta ante incidentes de seguridad
A53: C39 | B53: Revisión de logs y alertas de seguridad | C53: C39- Revisión de logs y alertas de seguridad
A54: 13. Gestión de Continuidad del Negocio | C54: 13. Gestión de Continuidad del Negocio-
A55: C40 | B55: Respaldo y restauración | C55: C40- Respaldo y restauración
A56: C41 | B56: Revisión y pruebas de continuidad del negocio | C56: C41- Revisión y pruebas de continuidad del negocio
A57: 14. Cumplimiento | C57: 14. Cumplimiento-
A58: C42 | B58: Auditorías internas y externas | C58: C42- Auditorías internas y externas
A59: C43 | B59: Evaluación de cumplimiento legal y regulatorio | C59: C43- Evaluación de cumplimiento legal y regulatorio

Sheet ANEXO A
A1: Identificador de control IEC 27002 | B1: Nombre del control | C1: Tipo de control | D1: Propiedades de seguridad de la información | E1: Conceptos de ciberseguridad | F1: Capacidades operativas | G1: Dominios de seguridad | H1: Obligatoriedad Regulatoria SEPS 002-2022 | I1: Control Metodología GSO-GSI (Secc. 10.2.2) | J1: Origen de Aplicabilidad | K1: ¿Aplica? | L1: Criterio / Justificación Técnica
A2: 5.1 | B2: Políticas para la seguridad de la información | C2: #Preventivo | D2: #Confidencialidad, #Integridad, #Disponibilidad | E2: #Identificar | F2: #Gobernanza | G2: #Gobernanza_y_Ecosistema | H2: Obligatorio SEPS (Régimen General) | I2: C1: Revisión periódica de políticas y procedimientos | J2: 2. Metodología Interna GSO-GSI + ISO 27001 | K2: Aplica | L2: Requisito interno GSO-GSI
A3: 5.2 | B3: Funciones y responsabilidades de seguridad de la información | C3: #Preventivo | D3: #Confidencialidad, #Integridad, #Disponibilidad | E3: #Identificar | F3: #Gobernanza | G3: #Gobernanza_y_Ecosistema | H3: Obligatorio SEPS (Régimen General) | I3: - | J3: 1. Regulatorio SEPS 002-2022 + ISO 27001 | K3: Aplica | L3: Requerido por ente regulador SEPS
A4: 5.3 | B4: Segregación de funciones | C4: #Preventivo | D4: #Confidencialidad, #Integridad | E4: #Proteger | F4: #Gobernanza | G4: #Gobernanza_y_Ecosistema | H4: Obligatorio SEPS (Régimen General) | I4: - | J4: 1. Regulatorio SEPS 002-2022 + ISO 27001 | K4: Aplica | L4: Requerido por ente regulador SEPS
A5: 5.4 | B5: Responsabilidades de la dirección | C5: #Preventivo | D5: #Confidencialidad, #Integridad, #Disponibilidad | E5: #Identificar | F5: #Gobernanza | G5: #Gobernanza_y_Ecosistema | H5: Obligatorio SEPS (Régimen General) | I5: - | J5: 1. Regulatorio SEPS 002-2022 + ISO 27001 | K5: Aplica | L5: Requerido por ente regulador SEPS
A6: 5.5 | B6: Contacto con las autoridades | C6: #Preventivo | D6: #Disponibilidad | E6: #Responder | F6: #Gobernanza | G6: #Gobernanza_y_Ecosistema | H6: Obligatorio SEPS (Régimen General) | I6: - | J6: 1. Regulatorio SEPS 002-2022 + ISO 27001 | K6: Aplica | L6: Requerido por ente regulador SEPS
A7: 5.6 | B7: Contacto con grupos de interés especial | C7: #Preventivo | D7: #Disponibilidad | E7: #Identificar | F7: #Gobernanza | G7: #Gobernanza_y_Ecosistema | H7: Mejor Práctica (No obligatorio SEPS) | I7: - | J7: 3. Tratamiento de Riesgos Específico (ISO 27002 / MAGERIT) | K7: Aplica | L7: Requisito de control complementario y mejor práctica de seguridad
A8: 5.7 | B8: Inteligencia de amenazas | C8: #Detectivo, #Preventivo | D8: #Confidencialidad, #Integridad, #Disponibilidad | E8: #Identificar | F8: #Gestión_de_amenazas_y_vulnerabilidades | G8: #Gobernanza_y_Ecosistema | H8: Mejor Práctica (No obligatorio SEPS) | I8: - | J8: 3. Tratamiento de Riesgos Específico (ISO 27002 / MAGERIT) | K8: Aplica | L8: Requisito de control complementario y mejor práctica de seguridad
A9: 5.8 | B9: Seguridad de la información en la gestión de proyectos | C9: #Preventivo | D9: #Confidencialidad, #Integridad, #Disponibilidad | E9: #Proteger | F9: #Gobernanza | G9: #Gobernanza_y_Ecosistema | H9: Obligatorio SEPS (Régimen General) | I9: - | J9: 1. Regulatorio SEPS 002-2022 + ISO 27001 | K9: Aplica | L9: Requerido por ente regulador SEPS
A10: 5.9 | B10: Inventario de información y otros activos asociados | C10: #Preventivo | D10: #Confidencialidad, #Integridad, #Disponibilidad | E10: #Identificar | F10: #Gestión_de_activos | G10: #Gobernanza_y_Ecosistema | H10: Obligatorio SEPS (Régimen General) | I10: - | J10: 1. Regulatorio SEPS 002-2022 + ISO 27001 | K10: Aplica | L10: Requerido por ente regulador SEPS
A11: 5.10 | B11: Uso aceptable de la información y otros activos asociados | C11: #Preventivo | D11: #Confidencialidad, #Integridad, #Disponibilidad | E11: #Proteger | F11: #Protección_de_la_información | G11: #Gobernanza_y_Ecosistema | H11: Obligatorio SEPS (Régimen General) | I11: - | J11: 1. Regulatorio SEPS 002-2022 + ISO 27001 | K11: Aplica | L11: Requerido por ente regulador SEPS
A12: 5.11 | B12: Devolución de activos | C12: #Preventivo | D12: #Confidencialidad, #Integridad, #Disponibilidad | E12: #Proteger | F12: #Gestión_de_activos | G12: #Gobernanza_y_Ecosistema | H12: Obligatorio SEPS (Régimen General) | I12: - | J12: 1. Regulatorio SEPS 002-2022 + ISO 27001 | K12: Aplica | L12: Requerido por ente regulador SEPS
... A94: 8.34 | B94: Protección de los sistemas de información durante las pruebas de auditoría | C94: #Preventivo | D94: #Confidencialidad, #Integridad, #Disponibilidad | E94: #Proteger | F94: #Seguridad_de_sistemas_y_redes | G94: #Proteccion | H94: Mejor Práctica (No obligatorio SEPS) | I94: - | J94: 3. Tratamiento de Riesgos Específico (ISO 27002 / MAGERIT) | K94: No Aplica | L94: No aplicable a la arquitectura/infraestructura actual

Sheet Hoja1

Sheet Declaración Aplicabilidad (SoA)
A1: ID Control | B1: Nombre del Control | C1: Dominio ISO 27001 | D1: ¿Aplica? | E1: Obligatoriedad Regulatoria SEPS | F1: Control Metodología GSO-GSI | G1: Origen de Aplicabilidad | H1: Justificación Inclusión/Exclusión | I1: Acción | J1: Estado de Implementación | K1: Tipo de Protección MAGERIT | L1: Nivel de Madurez / Efectividad | M1: Riesgos / Amenazas que Mitiga | N1: Evidencia / Documentación Asociada
A2: ='ANEXO A'!A2 | B2: =IFERROR(VLOOKUP(A2, 'ANEXO A'!$A$2:$L$94, 2, FALSE), "") | C2: =IF(LEFT(A2,1)="5", "5. Organizacionales", IF(LEFT(A2,1)="6", "6. Personas", IF(LEFT(A2,1)="7", "7. Físicos", "8. Tecnológicos"))) | D2: =IFERROR(VLOOKUP(A2, 'ANEXO A'!$A$2:$L$94, 11, FALSE), "") | E2: =IFERROR(VLOOKUP(A2, 'ANEXO A'!$A$2:$L$94, 8, FALSE), "") | F2: =IFERROR(VLOOKUP(A2, 'ANEXO A'!$A$2:$L$94, 9, FALSE), "") | G2: =IFERROR(VLOOKUP(A2, 'ANEXO A'!$A$2:$L$94, 10, FALSE), "") | H2: =IFERROR(VLOOKUP(A2, 'ANEXO A'!$A$2:$L$94, 12, FALSE), "") | I2: 6.1. Políticas Generales - Establecer directrices de seguridad (GSO-GSI-MP-GSI)
A3: ='ANEXO A'!A3 | B3: =IFERROR(VLOOKUP(A3, 'ANEXO A'!$A$2:$L$94, 2, FALSE), "") | C3: =IF(LEFT(A3,1)="5", "5. Organizacionales", IF(LEFT(A3,1)="6", "6. Personas", IF(LEFT(A3,1)="7", "7. Físicos", "8. Tecnológicos"))) | D3: =IFERROR(VLOOKUP(A3, 'ANEXO A'!$A$2:$L$94, 11, FALSE), "") | E3: =IFERROR(VLOOKUP(A3, 'ANEXO A'!$A$2:$L$94, 8, FALSE), "") | F3: =IFERROR(VLOOKUP(A3, 'ANEXO A'!$A$2:$L$94, 9, FALSE), "") | G3: =IFERROR(VLOOKUP(A3, 'ANEXO A'!$A$2:$L$94, 10, FALSE), "") | H3: =IFERROR(VLOOKUP(A3, 'ANEXO A'!$A$2:$L$94, 12, FALSE), "")
A4: ='ANEXO A'!A4 | B4: =IFERROR(VLOOKUP(A4, 'ANEXO A'!$A$2:$L$94, 2, FALSE), "") | C4: =IF(LEFT(A4,1)="5", "5. Organizacionales", IF(LEFT(A4,1)="6", "6. Personas", IF(LEFT(A4,1)="7", "7. Físicos", "8. Tecnológicos"))) | D4: =IFERROR(VLOOKUP(A4, 'ANEXO A'!$A$2:$L$94, 11, FALSE), "") | E4: =IFERROR(VLOOKUP(A4, 'ANEXO A'!$A$2:$L$94, 8, FALSE), "") | F4: =IFERROR(VLOOKUP(A4, 'ANEXO A'!$A$2:$L$94, 9, FALSE), "") | G4: =IFERROR(VLOOKUP(A4, 'ANEXO A'!$A$2:$L$94, 10, FALSE), "") | H4: =IFERROR(VLOOKUP(A4, 'ANEXO A'!$A$2:$L$94, 12, FALSE), "")
A5: ='ANEXO A'!A5 | B5: =IFERROR(VLOOKUP(A5, 'ANEXO A'!$A$2:$L$94, 2, FALSE), "") | C5: =IF(LEFT(A5,1)="5", "5. Organizacionales", IF(LEFT(A5,1)="6", "6. Personas", IF(LEFT(A5,1)="7", "7. Físicos", "8. Tecnológicos"))) | D5: =IFERROR(VLOOKUP(A5, 'ANEXO A'!$A$2:$L$94, 11, FALSE), "") | E5: =IFERROR(VLOOKUP(A5, 'ANEXO A'!$A$2:$L$94, 8, FALSE), "") | F5: =IFERROR(VLOOKUP(A5, 'ANEXO A'!$A$2:$L$94, 9, FALSE), "") | G5: =IFERROR(VLOOKUP(A5, 'ANEXO A'!$A$2:$L$94, 10, FALSE), "") | H5: =IFERROR(VLOOKUP(A5, 'ANEXO A'!$A$2:$L$94, 12, FALSE), "")
A6: ='ANEXO A'!A6 | B6: =IFERROR(VLOOKUP(A6, 'ANEXO A'!$A$2:$L$94, 2, FALSE), "") | C6: =IF(LEFT(A6,1)="5", "5. Organizacionales", IF(LEFT(A6,1)="6", "6. Personas", IF(LEFT(A6,1)="7", "7. Físicos", "8. Tecnológicos"))) | D6: =IFERROR(VLOOKUP(A6, 'ANEXO A'!$A$2:$L$94, 11, FALSE), "") | E6: =IFERROR(VLOOKUP(A6, 'ANEXO A'!$A$2:$L$94, 8, FALSE), "") | F6: =IFERROR(VLOOKUP(A6, 'ANEXO A'!$A$2:$L$94, 9, FALSE), "") | G6: =IFERROR(VLOOKUP(A6, 'ANEXO A'!$A$2:$L$94, 10, FALSE), "") | H6: =IFERROR(VLOOKUP(A6, 'ANEXO A'!$A$2:$L$94, 12, FALSE), "")
A7: ='ANEXO A'!A7 | B7: =IFERROR(VLOOKUP(A7, 'ANEXO A'!$A$2:$L$94, 2, FALSE), "") | C7: =IF(LEFT(A7,1)="5", "5. Organizacionales", IF(LEFT(A7,1)="6", "6. Personas", IF(LEFT(A7,1)="7", "7. Físicos", "8. Tecnológicos"))) | D7: =IFERROR(VLOOKUP(A7, 'ANEXO A'!$A$2:$L$94, 11, FALSE), "") | E7: =IFERROR(VLOOKUP(A7, 'ANEXO A'!$A$2:$L$94, 8, FALSE), "") | F7: =IFERROR(VLOOKUP(A7, 'ANEXO A'!$A$2:$L$94, 9, FALSE), "") | G7: =IFERROR(VLOOKUP(A7, 'ANEXO A'!$A$2:$L$94, 10, FALSE), "") | H7: =IFERROR(VLOOKUP(A7, 'ANEXO A'!$A$2:$L$94, 12, FALSE), "")
A8: ='ANEXO A'!A8 | B8: =IFERROR(VLOOKUP(A8, 'ANEXO A'!$A$2:$L$94, 2, FALSE), "") | C8: =IF(LEFT(A8,1)="5", "5. Organizacionales", IF(LEFT(A8,1)="6", "6. Personas", IF(LEFT(A8,1)="7", "7. Físicos", "8. Tecnológicos"))) | D8: =IFERROR(VLOOKUP(A8, 'ANEXO A'!$A$2:$L$94, 11, FALSE), "") | E8: =IFERROR(VLOOKUP(A8, 'ANEXO A'!$A$2:$L$94, 8, FALSE), "") | F8: =IFERROR(VLOOKUP(A8, 'ANEXO A'!$A$2:$L$94, 9, FALSE), "") | G8: =IFERROR(VLOOKUP(A8, 'ANEXO A'!$A$2:$L$94, 10, FALSE), "") | H8: =IFERROR(VLOOKUP(A8, 'ANEXO A'!$A$2:$L$94, 12, FALSE), "")
A9: ='ANEXO A'!A9 | B9: =IFERROR(VLOOKUP(A9, 'ANEXO A'!$A$2:$L$94, 2, FALSE), "") | C9: =IF(LEFT(A9,1)="5", "5. Organizacionales", IF(LEFT(A9,1)="6", "6. Personas", IF(LEFT(A9,1)="7", "7. Físicos", "8. Tecnológicos"))) | D9: =IFERROR(VLOOKUP(A9, 'ANEXO A'!$A$2:$L$94, 11, FALSE), "") | E9: =IFERROR(VLOOKUP(A9, 'ANEXO A'!$A$2:$L$94, 8, FALSE), "") | F9: =IFERROR(VLOOKUP(A9, 'ANEXO A'!$A$2:$L$94, 9, FALSE), "") | G9: =IFERROR(VLOOKUP(A9, 'ANEXO A'!$A$2:$L$94, 10, FALSE), "") | H9: =IFERROR(VLOOKUP(A9, 'ANEXO A'!$A$2:$L$94, 12, FALSE), "")
A10: ='ANEXO A'!A10 | B10: =IFERROR(VLOOKUP(A10, 'ANEXO A'!$A$2:$L$94, 2, FALSE), "") | C10: =IF(LEFT(A10,1)="5", "5. Organizacionales", IF(LEFT(A10,1)="6", "6. Personas", IF(LEFT(A10,1)="7", "7. Físicos", "8. Tecnológicos"))) | D10: =IFERROR(VLOOKUP(A10, 'ANEXO A'!$A$2:$L$94, 11, FALSE), "") | E10: =IFERROR(VLOOKUP(A10, 'ANEXO A'!$A$2:$L$94, 8, FALSE), "") | F10: =IFERROR(VLOOKUP(A10, 'ANEXO A'!$A$2:$L$94, 9, FALSE), "") | G10: =IFERROR(VLOOKUP(A10, 'ANEXO A'!$A$2:$L$94, 10, FALSE), "") | H10: =IFERROR(VLOOKUP(A10, 'ANEXO A'!$A$2:$L$94, 12, FALSE), "") | I10: 6.13. Gestión de activos de información - Mantener un inventario actualizado (GSO-GSI-MP-GSI)
A11: ='ANEXO A'!A11 | B11: =IFERROR(VLOOKUP(A11, 'ANEXO A'!$A$2:$L$94, 2, FALSE), "") | C11: =IF(LEFT(A11,1)="5", "5. Organizacionales", IF(LEFT(A11,1)="6", "6. Personas", IF(LEFT(A11,1)="7", "7. Físicos", "8. Tecnológicos"))) | D11: =IFERROR(VLOOKUP(A11, 'ANEXO A'!$A$2:$L$94, 11, FALSE), "") | E11: =IFERROR(VLOOKUP(A11, 'ANEXO A'!$A$2:$L$94, 8, FALSE), "") | F11: =IFERROR(VLOOKUP(A11, 'ANEXO A'!$A$2:$L$94, 9, FALSE), "") | G11: =IFERROR(VLOOKUP(A11, 'ANEXO A'!$A$2:$L$94, 10, FALSE), "") | H11: =IFERROR(VLOOKUP(A11, 'ANEXO A'!$A$2:$L$94, 12, FALSE), "")
A12: ='ANEXO A'!A12 | B12: =IFERROR(VLOOKUP(A12, 'ANEXO A'!$A$2:$L$94, 2, FALSE), "") | C12: =IF(LEFT(A12,1)="5", "5. Organizacionales", IF(LEFT(A12,1)="6", "6. Personas", IF(LEFT(A12,1)="7", "7. Físicos", "8. Tecnológicos"))) | D12: =IFERROR(VLOOKUP(A12, 'ANEXO A'!$A$2:$L$94, 11, FALSE), "") | E12: =IFERROR(VLOOKUP(A12, 'ANEXO A'!$A$2:$L$94, 8, FALSE), "") | F12: =IFERROR(VLOOKUP(A12, 'ANEXO A'!$A$2:$L$94, 9, FALSE), "") | G12: =IFERROR(VLOOKUP(A12, 'ANEXO A'!$A$2:$L$94, 10, FALSE), "") | H12: =IFERROR(VLOOKUP(A12, 'ANEXO A'!$A$2:$L$94, 12, FALSE), "")
A13: ='ANEXO A'!A13 | B13: =IFERROR(VLOOKUP(A13, 'ANEXO A'!$A$2:$L$94, 2, FALSE), "") | C13: =IF(LEFT(A13,1)="5", "5. Organizacionales", IF(LEFT(A13,1)="6", "6. Personas", IF(LEFT(A13,1)="7", "7. Físicos", "8. Tecnológicos"))) | D13: =IFERROR(VLOOKUP(A13, 'ANEXO A'!$A$2:$L$94, 11, FALSE), "") | E13: =IFERROR(VLOOKUP(A13, 'ANEXO A'!$A$2:$L$94, 8, FALSE), "") | F13: =IFERROR(VLOOKUP(A13, 'ANEXO A'!$A$2:$L$94, 9, FALSE), "") | G13: =IFERROR(VLOOKUP(A13, 'ANEXO A'!$A$2:$L$94, 10, FALSE), "") | H13: =IFERROR(VLOOKUP(A13, 'ANEXO A'!$A$2:$L$94, 12, FALSE), "")
A14: ='ANEXO A'!A14 | B14: =IFERROR(VLOOKUP(A14, 'ANEXO A'!$A$2:$L$94, 2, FALSE), "") | C14: =IF(LEFT(A14,1)="5", "5. Organizacionales", IF(LEFT(A14,1)="6", "6. Personas", IF(LEFT(A14,1)="7", "7. Físicos", "8. Tecnológicos"))) | D14: =IFERROR(VLOOKUP(A14, 'ANEXO A'!$A$2:$L$94, 11, FALSE), "") | E14: =IFERROR(VLOOKUP(A14, 'ANEXO A'!$A$2:$L$94, 8, FALSE), "") | F14: =IFERROR(VLOOKUP(A14, 'ANEXO A'!$A$2:$L$94, 9, FALSE), "") | G14: =IFERROR(VLOOKUP(A14, 'ANEXO A'!$A$2:$L$94, 10, FALSE), "") | H14: =IFERROR(VLOOKUP(A14, 'ANEXO A'!$A$2:$L$94, 12, FALSE), "")
